Workbook

Sheet Overview
A1: Date | B1: Training_Name | C1: # Registrations | D1: m+f+d | E1: # Participants | F1: Attend_Rate | G1: Male | H1: Female | I1: Diverse | J1: Female % | K1: ECS | L1: ECS % | M1: SME | N1: SME % | O1: Familar? | P1: Familiar? % | Q1: FeedbackF | R1: FeedbackF % | S1: wideningC | T1: wideningC % | U1: #Scientific fields | V1: #Countries | W1: non-EU | X1: non-EU % | Y1: America
A2: 45200 | B2: EPOSMetadata | C2: {=COUNT(INDIRECT(B2&"!A$2:A$1000"))} -> 89 | D2: =G2+H2+I2 -> 89 | E2: 81 | F2: =E2/C2 -> 0.91011236 | G2: {=COUNTIF(INDIRECT($B2&"!B$2:B$1000"),"Male")} -> 43 | H2: {=COUNTIF(INDIRECT($B2&"!B$2:B$1000"),"Female")} -> 44 | I2: {=COUNTIF(INDIRECT($B2&"!B$2:B$1000"),"Diverse")} -> 2 | J2: =H2/C2 -> 0.49438202 | K2: {=COUNTIF(INDIRECT($B2&"!E$2:E$1000"),"Yes")} -> 36 | L2: =K2/C2 -> 0.40449438 | M2: {=COUNTIF(INDIRECT($B2&"!F$2:F$1000"),"Yes")} -> 7 | N2: =M2/C2 -> 0.078651685 | O2: {=COUNTIF(INDIRECT($B2&"!I$2:I$1000"),"Yes")} -> 39 | P2: =O2/C2 -> 0.43820225 | Q2: 19 | R2: =Q2/E2 -> 0.2345679 | S2: 15 | T2: =S2/C2 -> 0.16853933 | U2: 18 | V2: 22 | W2: 6 | X2: =W2/C2 -> 0.06741573
A3: 45315 | B3: EPOS Data Portal Trg | C3: 399 | D3: =G3+H3+I3 -> 399 | E3: 212 | F3: =E3/C3 -> 0.53132832 | G3: 187 | H3: 212 | I3: 0 | J3: =H3/C3 -> 0.53132832 | K3: 25 | L3: =K3/C3 -> 0.062656642 | M3: 13 | N3: =M3/C3 -> 0.032581454 | Q3: 69 | R3: =Q3/C3 -> 0.17293233 | S3: 12 | T3: =S3/Q3 -> 0.17391304 | U3: 16 | V3: 34 | W3: 13 | X3: =W3/C3 -> 0.032581454
A4: 45413 | B4: EPOS Data Portal Trg 2 | C4: 103 | D4: =G4+H4+I4 -> 65 | E4: 65 | F4: =E4/C4 -> 0.63106796 | G4: 32 | H4: 33 | I4: 0 | J4: =H4/C4 -> 0.32038835 | K4: 13 | L4: =K4/C4 -> 0.12621359 | M4: 0 | N4: 0 | O4: 22 | P4: =O4/C4 -> 0.21359223 | Q4: 33 | R4: =Q4/C4 -> 0.32038835 | S4: 7 | T4: =S4/C4 -> 0.067961165 | U4: 14 | V4: 28 | W4: 8 | X4: =W4/C4 -> 0.077669903
A5: Oct-24 | B5: EPOS Data Portal Trg 3 | C5: 72 | D5: =G5+H5+I5 -> 72 | E5: 44 | F5: =E5/C5 -> 0.61111111 | G5: 25 | H5: 47 | I5: 0 | J5: =H5/C5 -> 0.65277778 | K5: 3 | L5: =K5/C5 -> 0.041666667 | M5: 0 | N5: 0 | O5: 10 | P5: =O5/C5 -> 0.13888889 | Q5: 24 | R5: =Q5/C5 -> 0.33333333 | S5: 39 | T5: =S4/C4 -> 0.067961165 | U5: =AVERAGE(U2:U4) -> 16 | V5: 20 | W5: 2 | X5: =W5/C5 -> 0.027777778
A6: Mar-2025 | B6: EPOS Platform Trg - Online 12-03-2025 | C6: 90 | D6: 37 | E6: 17 | F6: =E6/C6 -> 0.18888889 | G6: 8 | H6: 9 | I6: 0 | J6: 0.53 | K6: 3 | L6: 0.18 | M6: 0 | N6: 0 | O6: 5 | P6: 0.29 | Q6: 17 | R6: =Q6/C6 -> 0.18888889 | S6: 0 | T6: 0 | U6: 14 | V6: 6 | W6: 0 | X6: 0
A7: 45748 | B7: EPOS Platform Trg - EGU25 | C7: =E7 -> 21 | D7: 21 | E7: 21 | F7: =E7/C7 -> 1 | G7: 3 | H7: 5 | I7: 0 | J7: 0.62 | K7: 4 | L7: 0.5 | M7: 0 | N7: 0 | O7: 3 | P7: 0.38 | Q7: 8 | R7: =Q7/D7 -> 0.38095238 | S7: 1 | T7: 0.13 | U7: 10 | V7: 6 | W7: 0 | X7: 0
A8: May-2025 | B8: EPOS Platform Trg - Clermont-Ferrand | C8: =E8 -> 8 | D8: 8 | E8: 8 | F8: =E8/C8 -> 1 | G8: 4 | H8: 4 | I8: 0 | J8: 0.5 | K8: 3 | L8: 0.38 | M8: 0 | N8: 0 | O8: 3 | P8: 0.38 | Q8: 8 | R8: 1 | S8: 0 | T8: 0 | U8: 9 | V8: 1 | W8: 0 | X8: 0
A9: May-2025 | B9: EPOS Platform Trg - S4E | C9: =E9 -> 6 | D9: 6 | E9: 6 | F9: =E9/C9 -> 1 | G9: 3 | H9: 3 | I9: 0 | J9: 0.5 | K9: 4 | L9: 0.67 | M9: 0 | N9: 0 | O9: 1 | P9: 0.17 | Q9: 6 | R9: 0.75 | S9: 0 | T9: 0 | U9: 4 | V9: 2 | W9: 0 | X9: 0
A10: Jun-2025 | B10: EPOS Platform Trg - EPOS Summer School | C10: =E10 -> 25 | D10: 25 | E10: 25 | F10: =E10/C10 -> 1 | G10: 8 | H10: 17 | I10: 0 | J10: 0.68 | K10: 13 | L10: 0.52 | M10: 0 | N10: 0 | O10: 10 | P10: 0.4 | Q10: 25 | R10: 1 | S10: 5 | T10: 0.2 | U10: 19 | V10: 15 | W10: 6 | X10: 0.24
A11: July-2025 | B11: EPOS Platform Trg - Spain | C11: =E11 -> 26 | D11: 26 | E11: 26 | F11: =E11/C11 -> 1 | G11: 12 | H11: 14 | I11: 0 | J11: 0.54 | K11: 10 | L11: 0.38 | M11: 0 | N11: 0 | O11: 10 | P11: 0.38 | Q11: 26 | R11: 1 | S11: 1 | T11: 0.04 | U11: 20 | V11: 2 | W11: 0 | X11: 0
A12: Sep-2025 | B12: EPOS Platform Trg - CZ | C12: =E12 -> 9 | D12: 9 | E12: 9 | F12: =E12/C12 -> 1 | G12: 8 | H12: 1 | I12: 0 | J12: 0.11 | K12: 2 | L12: 0.29 | M12: 0 | N12: 0 | O12: 4 | P12: 0.44 | Q12: 7 | R12: 0.88 | S12: 6 | T12: 0.14 | U12: 21 | V12: 2 | W12: 0 | X12: 0
A13: May-2026 | B13: EPOS Platform Trg - EGU26 | C13: 10 | D13: 10 | E13: 10 | F13: 1 | G13: 5 | H13: 5 | I13: 0 | J13: 0.5 | K13: 2 | L13: =K13/D13 -> 0.2 | M13: 2 | N13: 0.2 | O13: 1 | P13: 0.1 | Q13: 2 | R13: 0.2
A14: May-2026 | B14: EPOS Platform Trg - CZ | C14: 7 | D14: 7 | E14: 7 | F14: 1 | G14: 4 | H14: 3 | I14: 0 | J14: =H14/C14 -> 0.42857143 | K14: 2 | L14: =K14/C14 -> 0.28571429 | M14: 0 | N14: 0 | O14: 2 | P14: =O14/C14 -> 0.28571429 | Q14: 7 | R14: 1 | S14: 0 | T14: 0 | U14: 9 | V14: 1 | W14: 0 | X14: 0
A15: Summary | B15: 11 EPOS Trg | C15: =SUM(C2:C14) -> 865 | D15: =SUM(D2:D14) -> 774 | E15: =SUM(E2:E14) -> 531 | F15: =E15/C15 -> 0.61387283 | G15: =SUM(G2:G14) -> 342 | H15: =SUM(H2:H14) -> 397 | I15: =SUM(I2:I14) -> 2 | J15: =H15/(G15+H15+I15) -> 0.53576248 | K15: =SUM(K2:K14) -> 120 | L15: =K15/C15 -> 0.13872832 | M15: =SUM(M2:M14) -> 22 | N15: =M15/C15 -> 0.025433526 | O15: =SUM(O2:O14) -> 110 | P15: =O15/(C15-C3) -> 0.2360515
B16: .
A17: 45047 | B17: HPS-SCOPED1 | C17: 205 | D17: =G17+H17+I17 -> 205 | E17: 134 | F17: =E17/C17 -> 0.65365854 | G17: 128 | H17: 70 | I17: 7 | J17: =H17/C17 -> 0.34146341 | K17: 84 | L17: =K17/C17 -> 0.4097561 | M17: 15 | N17: =M17/C17 -> 0.073170732 | O17: 186 | P17: =O17/C17 -> 0.90731707 | S17: 10 | T17: =S17/C17 -> 0.048780488 | U17: 4 | V17: 33 | W17: 113 | X17: =W17/C17 -> 0.55121951 | Y17: 90
A18: 45231 | B18: ETRiS | C18: =COUNT(INDIRECT(B18&"!A$2:A$1000")) -> 234 | D18: =G18+H18+I18 -> 234 | E18: 144 | F18: =E18/C18 -> 0.61538462 | G18: =COUNTIF(INDIRECT($B18&"!B$2:B$1000"),"Male") -> 145 | H18: =COUNTIF(INDIRECT($B18&"!B$2:B$1000"),"Female") -> 89 | I18: =COUNTIF(INDIRECT($B18&"!B$2:B$1000"),"Diverse") -> 0 | J18: =H18/C18 -> 0.38034188 | K18: =COUNTIF(INDIRECT($B18&"!E$2:E$1000"),"Yes") -> 171 | L18: =K18/C18 -> 0.73076923 | M18: =COUNTIF(INDIRECT($B18&"!F$2:F$1000"),"Yes") -> 67 | N18: =M18/C18 -> 0.28632479 | O18: =COUNTIF(INDIRECT($B18&"!I$2:I$1000"),"Yes") -> 3 | P18: =O18/C18 -> 0.012820513 | Q18: 28 | R18: =Q18/E18 -> 0.19444444 | S18: 20 | T18: =S18/C18 -> 0.085470085 | U18: 27 | V18: 46 | W18: 109 | X18: =W18/C18 -> 0.46581197
A19: 45383 | B19: HySEA_T | C19: =COUNT(INDIRECT(B19&"!A$2:A$1000")) -> 66 | D19: =G19+H19+I19 -> 66 | E19: 57 | F19: =E19/C19 -> 0.86363636 | G19: =COUNTIF(INDIRECT($B19&"!B$2:B$1000"),"Male") -> 37 | H19: =COUNTIF(INDIRECT($B19&"!B$2:B$1000"),"Female") -> 27 | I19: =COUNTIF(INDIRECT($B19&"!B$2:B$1000"),"Diverse") -> 2 | J19: =H19/C19 -> 0.40909091 | K19: =COUNTIF(INDIRECT($B19&"!E$2:E$1000"),"Yes") -> 46 | L19: =K19/C19 -> 0.6969697 | M19: =COUNTIF(INDIRECT($B19&"!F$2:F$1000"),"Yes") -> 7 | N19: =M19/C19 -> 0.10606061 | O19: =COUNTIF(INDIRECT($B19&"!I$2:I$1000"),"Yes") -> 16 | P19: =O19/C19 -> 0.24242424 | Q19: 20 | R19: =Q19/E19 -> 0.35087719 | S19: 3 | T19: =S19/C19 -> 0.045454545 | U19: 15 | V19: 19 | W19: 31 | X19: =W19/C19 -> 0.46969697
A20: 45754 | B20: HySEA_L | C20: =COUNT(INDIRECT(B20&"!A$2:A$1000")) -> 105 | D20: =G20+H20+I20 -> 105 | E20: 79 | F20: =E20/C20 -> 0.75238095 | G20: =COUNTIF(INDIRECT($B20&"!B$2:B$1000"),"Male") -> 64 | H20: =COUNTIF(INDIRECT($B20&"!B$2:B$1000"),"Female") -> 40 | I20: =COUNTIF(INDIRECT($B20&"!B$2:B$1000"),"Diverse") -> 1 | J20: =H20/C20 -> 0.38095238 | K20: =COUNTIF(INDIRECT($B20&"!E$2:E$1000"),"Yes") -> 74 | L20: =K20/C20 -> 0.7047619 | M20: =COUNTIF(INDIRECT($B20&"!F$2:F$1000"),"Yes") -> 14 | N20: =M20/C20 -> 0.13333333 | P20: =O20/C20 -> 0 | Q20: 6 | R20: =Q20/E20 -> 0.075949367 | S20: 21 | T20: =S20/C20 -> 0.2 | U20: 12 | V20: 28 | W20: 48 | X20: =W20/C20 -> 0.45714286
A21: 45536 | B21: PyBET | C21: 18 | D21: =G21+H21+I21 -> 18 | E21: 18 | F21: =E21/C21 -> 1 | G21: =COUNTIF(INDIRECT($B21&"!B$2:B$1000"),"Male") -> 13 | H21: =COUNTIF(INDIRECT($B21&"!B$2:B$1000"),"Female") -> 5 | I21: =COUNTIF(INDIRECT($B21&"!B$2:B$1000"),"Diverse") -> 0 | J21: =H21/C21 -> 0.27777778 | K21: =COUNTIF(INDIRECT($B21&"!E$2:E$1000"),"Yes") -> 13 | L21: =K21/C21 -> 0.72222222 | M21: =COUNTIF(INDIRECT($B21&"!F$2:F$1000"),"Yes") -> 1 | N21: =M21/C21 -> 0.055555556 | O21: =COUNTIF(INDIRECT($B21&"!I$2:I$1000"),"Yes") -> 2 | P21: =O21/C21 -> 0.11111111 | Q21: 5 | R21: =Q21/E21 -> 0.27777778 | S21: 2 | T21: =S21/C21 -> 0.11111111 | U21: 8 | V21: 11 | W21: 11 | X21: =W21/C21 -> 0.61111111 | Z21: preliminary results from feedback, survey still open
A22: 45536 | B22: SDL_WS | C22: 130 | D22: =G22+H22+I22 -> 126 | E22: 126 | F22: =E22/C22 -> 0.96923077 | G22: =COUNTIF(INDIRECT($B22&"!B$2:B$1000"),"Male") -> 73 | H22: =COUNTIF(INDIRECT($B22&"!B$2:B$1000"),"Female") -> 53 | I22: =COUNTIF(INDIRECT($B22&"!B$2:B$1000"),"Diverse") -> 0 | J22: =H22/C22 -> 0.40769231 | K22: =COUNTIF(INDIRECT($B22&"!E$2:E$1000"),"Yes") -> 61 | L22: =K22/C22 -> 0.46923077 | M22: =COUNTIF(INDIRECT($B22&"!F$2:F$1000"),"Yes") -> 8 | N22: =M22/C22 -> 0.061538462 | O22: =COUNTIF(INDIRECT($B22&"!I$2:I$1000"),"Yes") -> 23 | P22: =O22/C22 -> 0.17692308 | Q22: 21 | R22: =Q22/E22 -> 0.16666667 | S22: 4 | T22: =S22/C22 -> 0.030769231 | U22: 12 | V22: 26 | W22: 42 | X22: =W22/C22 -> 0.32307692 | Z22: preliminary results from feedback, survey still open
A23: 45678 | B23: Quakeworx | C23: {=COUNT(INDIRECT(B23&"!A$2:A$1000"))} -> 149 | D23: =G23+H23+I23 -> 148 | E23: 81 | F23: =E23/C23 -> 0.54362416 | G23: =COUNTIF(INDIRECT($B23&"!B$2:B$1000"),"Male") -> 101 | H23: =COUNTIF(INDIRECT($B23&"!B$2:B$1000"),"Female") -> 44 | I23: =COUNTIF(INDIRECT($B23&"!B$2:B$1000"),"Diverse") -> 3 | J23: =H23/C23 -> 0.29530201 | K23: =COUNTIF(INDIRECT($B23&"!E$2:E$1000"),"Yes") -> 0 | L23: =K23/C23 -> 0 | M23: =COUNTIF(INDIRECT($B23&"!F$2:F$1000"),"Yes") -> 1 | N23: =M23/C23 -> 0.0067114094 | O23: =COUNTIF(INDIRECT($B23&"!I$2:I$1000"),"Yes") -> 14 | P23: =O23/C23 -> 0.093959732 | R23: =Q23/E23 -> 0 | T23: =S23/C23 -> 0 | U23: =AVERAGE(U17:U22) -> 13 | X23: =W23/C23 -> 0
A24: 45897 | B24: VIS_WS | C24: 22 | D24: =G24+H24+I24 -> 16 | E24: 16 | F24: =E24/C24 -> 0.72727273 | G24: =COUNTIF(INDIRECT($B24&"!B$2:B$1000"),"Male") -> 7 | H24: =COUNTIF(INDIRECT($B24&"!B$2:B$1000"),"Female") -> 9 | I24: =COUNTIF(INDIRECT($B24&"!B$2:B$1000"),"Diverse") -> 0 | J24: =H24/C24 -> 0.40909091 | K24: =COUNTIF(INDIRECT($B24&"!E$2:E$1000"),"Yes") -> 14 | L24: =K24/C24 -> 0.63636364 | M24: =COUNTIF(INDIRECT($B24&"!F$2:F$1000"),"Yes") -> 1 | N24: =M24/C24 -> 0.045454545 | O24: =COUNTIF(INDIRECT($B24&"!I$2:I$1000"),"Yes") -> 4 | P24: =O24/C24 -> 0.18181818 | Q24: 7 | R24: =Q24/E24 -> 0.4375 | S24: 3 | T24: =S24/C24 -> 0.13636364 | U24: 14 | V24: 3 | W24: 0 | X24: =W24/C24 -> 0
A25: 45909 | B25: SDL_Trg | C25: 39 | D25: =G25+H25+I25 -> 39 | E25: 30 | F25: =E25/C25 -> 0.76923077 | G25: =COUNTIF(INDIRECT($B25&"!B$2:B$1000"),"Male") -> 21 | H25: =COUNTIF(INDIRECT($B25&"!B$2:B$1000"),"Female") -> 16 | I25: =COUNTIF(INDIRECT($B25&"!B$2:B$1000"),"Diverse") -> 2 | J25: =H25/C25 -> 0.41025641 | K25: =COUNTIF(INDIRECT($B25&"!E$2:E$1000"),"Yes") -> 14 | L25: =K25/C25 -> 0.35897436 | M25: =COUNTIF(INDIRECT($B25&"!F$2:F$1000"),"Yes") -> 7 | N25: =M25/C25 -> 0.17948718 | O25: =COUNTIF(INDIRECT($B25&"!I$2:I$1000"),"Yes") -> 0 | P25: =O25/C25 -> 0 | Q25: 6 | R25: =Q25/E25 -> 0.2 | S25: 6 | T25: =S25/C25 -> 0.15384615 | U25: 14 | V25: 11 | W25: 4 | X25: =W25/C25 -> 0.1025641
A26: June 2026 | B26: SeisSol_ExaHyPE_WS | C26: 59 | D26: =G26+H26+I26 -> 59 | E26: 59 | F26: =E26/C26 -> 1 | G26: =COUNTIF(INDIRECT($B26&"!B$2:B$1000"),"Male") -> 47 | H26: =COUNTIF(INDIRECT($B26&"!B$2:B$1000"),"Female") -> 12 | I26: =COUNTIF(INDIRECT($B26&"!B$2:B$1000"),"Diverse") -> 0 | J26: =H26/C26 -> 0.20338983 | K26: =COUNTIF(INDIRECT($B26&"!E$2:E$1000"),"Yes") -> 34 | L26: =K26/C26 -> 0.57627119 | M26: =COUNTIF(INDIRECT($B26&"!F$2:F$1000"),"Yes") -> 10 | N26: =M26/C26 -> 0.16949153 | O26: =COUNTIF(INDIRECT($B26&"!I$2:I$1000"),"Yes") -> 0 | P26: =O26/C26 -> 0 | Q26: 32 | R26: =Q26/E26 -> 0.54237288 | S26: 4 | T26: =S26/C26 -> 0.06779661 | U26: 14 | V26: 13 | W26: 11 | X26: =W26/C26 -> 0.18644068
A27: Summary | B27: 10 HPC Events | C27: =SUM(C17:C26) -> 1027 | D27: =SUM(D17:D23) -> 902 | E27: =SUM(E17:E26) -> 744 | F27: =E27/C27 -> 0.72444012 | G27: =SUM(G17:G26) -> 636 | H27: =SUM(H17:H26) -> 365 | I27: =SUM(I17:I23) -> 13 | J27: =H27/C27 -> 0.35540409 | K27: =SUM(K17:K23) -> 449 | L27: =K27/C27 -> 0.43719572 | M27: =SUM(M17:M23) -> 113 | N27: =M27/C27 -> 0.11002921 | O27: =SUM(O17:O26) -> 248 | P27: =O27/(C27-C20-C25-C26) -> 0.30097087
B28: .
A29: 45383 | B29: FAIR1 | C29: {=COUNT(INDIRECT(B29&"!A$2:A$1000"))} -> 86 | D29: =G29+H29+I29 -> 86 | E29: 55 | F29: =E29/C29 -> 0.63953488 | G29: =COUNTIF(INDIRECT($B29&"!B$2:B$1000"),"Male") -> 28 | H29: =COUNTIF(INDIRECT($B29&"!B$2:B$1000"),"Female") -> 58 | I29: =COUNTIF(INDIRECT($B29&"!B$2:B$1000"),"Diverse") -> 0 | J29: =H29/C29 -> 0.6744186 | K29: =COUNTIF(INDIRECT($B29&"!E$2:E$1000"),"Yes") -> 40 | L29: =K29/C29 -> 0.46511628 | M29: =COUNTIF(INDIRECT($B29&"!F$2:F$1000"),"Yes") -> 6 | N29: =M29/C29 -> 0.069767442 | O29: =COUNTIF(INDIRECT($B29&"!I$2:I$1000"),"Yes") -> 60 | P29: =O29/C29 -> 0.69767442 | Q29: 9 | R29: =Q29/C29 -> 0.10465116 | S29: 46 | T29: =S29/C29 -> 0.53488372 | U29: 21 | V29: 13 | W29: 3 | X29: =W29/C29 -> 0.034883721
A30: 45444 | B30: FAIR2 | C30: 59 | D30: =G30+H30+I30 -> 59 | E30: 49 | F30: =E30/C30 -> 0.83050847 | G30: =COUNTIF(INDIRECT($B30&"!B$2:B$1000"),"Male") -> 18 | H30: =COUNTIF(INDIRECT($B30&"!B$2:B$1000"),"Female") -> 39 | I30: =COUNTIF(INDIRECT($B30&"!B$2:B$1000"),"Diverse") -> 2 | J30: =H30/C30 -> 0.66101695 | K30: =COUNTIF(INDIRECT($B30&"!E$2:E$1000"),"Yes") -> 25 | L30: =K30/C30 -> 0.42372881 | M30: =COUNTIF(INDIRECT($B30&"!F$2:F$1000"),"Yes") -> 4 | N30: =M30/C30 -> 0.06779661 | O30: =COUNTIF(INDIRECT($B30&"!I$2:I$1000"),"Yes") -> 46 | P30: =O30/C30 -> 0.77966102 | Q30: 13 | R30: =Q30/E30 -> 0.26530612 | S30: 21 | T30: =S30/C30 -> 0.3559322 | U30: 22 | V30: 14 | W30: 3 | X30: =W30/C30 -> 0.050847458
A31: 45580 | B31: FAIR3 | C31: =COUNT(INDIRECT(B31&"!A$2:A$1000")) -> 54 | D31: =G31+H31+I31 -> 54 | E31: 43 | F31: =E31/C31 -> 0.7962963 | G31: =COUNTIF(INDIRECT($B31&"!B$2:B$1000"),"Male") -> 28 | H31: =COUNTIF(INDIRECT($B31&"!B$2:B$1000"),"Female") -> 26 | I31: =COUNTIF(INDIRECT($B31&"!B$2:B$1000"),"Diverse") -> 0 | J31: =H31/C31 -> 0.48148148 | K31: =COUNTIF(INDIRECT($B31&"!E$2:E$1000"),"Yes") -> 28 | L31: =K31/C31 -> 0.51851852 | M31: =COUNTIF(INDIRECT($B31&"!F$2:F$1000"),"Yes") -> 5 | N31: =M31/C31 -> 0.092592593 | O31: =COUNTIF(INDIRECT($B31&"!I$2:I$1000"),"Yes") -> 34 | P31: =O31/C31 -> 0.62962963 | Q31: 13 | R31: =Q31/E31 -> 0.30232558 | S31: 12 | T31: =S31/C31 -> 0.22222222 | U31: 11 | V31: 21 | W31: 9 | X31: =W31/C31 -> 0.16666667
A32: 45622 | B32: FAIR4 | C32: =COUNT(INDIRECT(B32&"!A$2:A$1000")) -> 60 | D32: =G32+H32+I32 -> 60 | E32: 29 | F32: =E32/C32 -> 0.48333333 | G32: =COUNTIF(INDIRECT($B32&"!B$2:B$1000"),"Male") -> 30 | H32: =COUNTIF(INDIRECT($B32&"!B$2:B$1000"),"Female") -> 29 | I32: =COUNTIF(INDIRECT($B32&"!B$2:B$1000"),"Diverse") -> 1 | J32: =H32/C32 -> 0.48333333 | K32: =COUNTIF(INDIRECT($B32&"!E$2:E$1000"),"Yes") -> 13 | L32: =K32/C32 -> 0.21666667 | M32: =COUNTIF(INDIRECT($B32&"!F$2:F$1000"),"Yes") -> 4 | N32: =M32/C32 -> 0.066666667 | O32: =COUNTIF(INDIRECT($B32&"!I$2:I$1000"),"Yes") -> 42 | P32: =O32/C32 -> 0.7 | Q32: 14 | R32: =Q32/E32 -> 0.48275862 | S32: 17 | T32: =S32/C32 -> 0.28333333 | U32: 11 | V32: 18 | W32: 5 | X32: =W32/C32 -> 0.083333333
A33: 45713 | B33: FAIR5 | C33: =COUNT(INDIRECT(B33&"!A$2:A$1000")) -> 54 | D33: =G33+H33+I33 -> 54 | E33: 33 | F33: =E33/C33 -> 0.61111111 | G33: =COUNTIF(INDIRECT($B33&"!B$2:B$1000"),"Male") -> 26 | H33: =COUNTIF(INDIRECT($B33&"!B$2:B$1000"),"Female") -> 28 | I33: =COUNTIF(INDIRECT($B33&"!B$2:B$1000"),"Diverse") -> 0 | J33: =H33/C33 -> 0.51851852 | K33: =COUNTIF(INDIRECT($B33&"!E$2:E$1000"),"Yes") -> 18 | L33: =K33/C33 -> 0.33333333 | M33: =COUNTIF(INDIRECT($B33&"!F$2:F$1000"),"Yes") -> 2 | N33: =M33/C33 -> 0.037037037 | O33: =COUNTIF(INDIRECT($B33&"!I$2:I$1000"),"Yes") -> 40 | P33: =O33/C33 -> 0.74074074 | Q33: 12 | R33: =Q33/E33 -> 0.36363636 | S33: 25 | T33: =S33/C33 -> 0.46296296 | U33: 16 | V33: 15 | W33: 1 | X33: =W33/C33 -> 0.018518519
A34: 45755 | B34: FAIR6 | C34: =COUNT(INDIRECT(B34&"!A$2:A$1000")) -> 33 | D34: =G34+H34+I34 -> 33 | E34: 31 | F34: =E34/C34 -> 0.93939394 | G34: =COUNTIF(INDIRECT($B34&"!B$2:B$1000"),"Male") -> 16 | H34: =COUNTIF(INDIRECT($B34&"!B$2:B$1000"),"Female") -> 17 | I34: =COUNTIF(INDIRECT($B34&"!B$2:B$1000"),"Diverse") -> 0 | J34: =H34/C34 -> 0.51515152 | K34: =COUNTIF(INDIRECT($B34&"!E$2:E$1000"),"Yes") -> 9 | L34: =K34/C34 -> 0.27272727 | M34: =COUNTIF(INDIRECT($B34&"!F$2:F$1000"),"Yes") -> 3 | N34: =M34/C34 -> 0.090909091 | O34: =COUNTIF(INDIRECT($B34&"!I$2:I$1000"),"Yes") -> 26 | P34: =O34/C34 -> 0.78787879 | Q34: 4 | R34: =Q34/E34 -> 0.12903226 | S34: 8 | T34: =S34/C34 -> 0.24242424 | U34: 10 | V34: 10 | W34: 2 | X34: =W34/C34 -> 0.060606061
A35: 45797 | B35: FAIR7 | C35: =COUNT(INDIRECT(B35&"!A$2:A$1000")) -> 20 | D35: =G35+H35+I35 -> 20 | E35: 18 | F35: =E35/C35 -> 0.9 | G35: =COUNTIF(INDIRECT($B35&"!B$2:B$1000"),"Male") -> 9 | H35: =COUNTIF(INDIRECT($B35&"!B$2:B$1000"),"Female") -> 10 | I35: =COUNTIF(INDIRECT($B35&"!B$2:B$1000"),"Diverse") -> 1 | J35: =H35/C35 -> 0.5 | K35: =COUNTIF(INDIRECT($B35&"!E$2:E$1000"),"Yes") -> 7 | L35: =K35/C35 -> 0.35 | M35: =COUNTIF(INDIRECT($B35&"!F$2:F$1000"),"Yes") -> 1 | N35: =M35/C35 -> 0.05 | O35: =COUNTIF(INDIRECT($B35&"!I$2:I$1000"),"Yes") -> 15 | P35: =O35/C35 -> 0.75 | Q35: 3 | R35: =Q35/E35 -> 0.16666667 | S35: 4 | T35: =S35/C35 -> 0.2 | U35: 13 | V35: 9 | W35: 1 | X35: =W35/C35 -> 0.05
A36: Summary | B36: 7 FAIR Trg | C36: =SUM(C29:C35) -> 366 | D36: =SUM(D29:D35) -> 366 | E36: =SUM(E29:E35) -> 258 | F36: =E36/C36 -> 0.70491803 | G36: =SUM(G29:G35) -> 155 | H36: =SUM(H29:H35) -> 207 | I36: =SUM(I29:I35) -> 4 | J36: =H36/C36 -> 0.56557377 | K36: =SUM(K29:K35) -> 140 | L36: =K36/C36 -> 0.38251366 | M36: =SUM(M29:M35) -> 25 | N36: =M36/C36 -> 0.068306011 | O36: =SUM(O29:O35) -> 263 | P36: =O36/C36 -> 0.71857923
B37: .
A38: 45383 | B38: EPISODES_WS | C38: 14 | D38: =G38+H38+I38 -> 14 | E38: 14 | F38: =E38/C38 -> 1 | G38: =COUNTIF(INDIRECT($B38&"!B$2:B$1000"),"Male") -> 9 | H38: =COUNTIF(INDIRECT($B38&"!B$2:B$1000"),"Female") -> 5 | I38: =COUNTIF(INDIRECT($B38&"!B$2:B$1000"),"Diverse") -> 0 | J38: =H38/C38 -> 0.35714286 | K38: =COUNTIF(INDIRECT($B38&"!E$2:E$1000"),"Yes") -> 10 | L38: =K38/C38 -> 0.71428571 | M38: =COUNTIF(INDIRECT($B38&"!F$2:F$1000"),"Yes") -> 6 | N38: =M38/C38 -> 0.42857143 | O38: 8 | P38: =O38/C38 -> 0.57142857 | Q38: 7 | R38: =Q38/C38 -> 0.5 | S38: 13 | T38: =S38/C38 -> 0.92857143 | U38: 13 | V38: 2 | W38: 0 | X38: =W38/C38 -> 0
A39: 45599 | B39: SiteEffects | C39: =COUNT(INDIRECT(B39&"!A$2:A$1000")) -> 50 | D39: =G39+H39+I39 -> 50 | E39: 29 | F39: =E39/C39 -> 0.58 | G39: =COUNTIF(INDIRECT($B39&"!B$2:B$1000"),"Male") -> 29 | H39: =COUNTIF(INDIRECT($B39&"!B$2:B$1000"),"Female") -> 19 | I39: =COUNTIF(INDIRECT($B39&"!B$2:B$1000"),"Diverse") -> 2 | J39: =H39/C39 -> 0.38 | K39: =COUNTIF(INDIRECT($B39&"!E$2:E$1000"),"Yes") -> 33 | L39: =K39/C39 -> 0.66 | M39: =COUNTIF(INDIRECT($B39&"!F$2:F$1000"),"Yes") -> 10 | N39: =M39/C39 -> 0.2 | O39: =COUNTIF(INDIRECT($B39&"!I$2:I$1000"),"Yes") -> 37 | P39: =O39/C39 -> 0.74 | Q39: 8 | R39: =Q39/C39 -> 0.16 | S39: 8 | T39: =S39/C39 -> 0.16 | U39: 12 | V39: 22 | W39: 21 | X39: =W39/C39 -> 0.42
A40: 45600 | B40: SLIP | C40: =COUNT(INDIRECT(B40&"!A$2:A$1000")) -> 89 | D40: =G40+H40+I40 -> 89 | E40: 60 | F40: =E40/C40 -> 0.6741573 | G40: =COUNTIF(INDIRECT($B40&"!B$2:B$1000"),"Male") -> 59 | H40: =COUNTIF(INDIRECT($B40&"!B$2:B$1000"),"Female") -> 30 | I40: =COUNTIF(INDIRECT($B40&"!B$2:B$1000"),"Diverse") -> 0 | J40: =H40/C40 -> 0.33707865 | K40: =COUNTIF(INDIRECT($B40&"!E$2:E$1000"),"Yes") -> 57 | L40: =K40/C40 -> 0.64044944 | M40: =COUNTIF(INDIRECT($B40&"!F$2:F$1000"),"Yes") -> 18 | N40: =M40/C40 -> 0.20224719 | O40: =COUNTIF(INDIRECT($B40&"!I$2:I$1000"),"Yes") -> 45 | P40: =O40/C40 -> 0.50561798 | Q40: 17 | R40: =Q40/E40 -> 0.28333333 | S40: 17 | T40: =S40/C40 -> 0.19101124 | U40: 11 | V40: 22 | W40: 19 | X40: =W40/C40 -> 0.21348315
A41: 45742 | B41: SLSMF | C41: =COUNT(INDIRECT(B41&"!A$2:A$1000")) -> 95 | D41: =G41+H41+I41 -> 95 | E41: 67 | F41: =E41/C41 -> 0.70526316 | G41: =COUNTIF(INDIRECT($B41&"!B$2:B$1000"),"Male") -> 58 | H41: =COUNTIF(INDIRECT($B41&"!B$2:B$1000"),"Female") -> 37 | I41: =COUNTIF(INDIRECT($B41&"!B$2:B$1000"),"Diverse") -> 0 | J41: =H41/C41 -> 0.38947368 | K41: =COUNTIF(INDIRECT($B41&"!E$2:E$1000"),"Yes") -> 33 | L41: =K41/C41 -> 0.34736842 | M41: =COUNTIF(INDIRECT($B41&"!F$2:F$1000"),"Yes") -> 15 | N41: =M41/C41 -> 0.15789474 | O41: =COUNTIF(INDIRECT($B41&"!I$2:I$1000"),"Yes") -> 39 | P41: =O41/C41 -> 0.41052632 | Q41: 8 | R41: =Q41/E41 -> 0.11940299 | S41: 29 | T41: =S41/C41 -> 0.30526316 | U41: 15 | V41: 29 | W41: 28 | X41: =W41/C41 -> 0.29473684
A42: May-25 | B42: EPISODES_Trg | C42: =COUNT(INDIRECT(B42&"!A$2:A$1000")) -> 26 | D42: =G42+H42+I42 -> 26 | E42: 17 | F42: =E42/C42 -> 0.65384615 | G42: =COUNTIF(INDIRECT($B42&"!B$2:B$1000"),"Male") -> 19 | H42: =COUNTIF(INDIRECT($B42&"!B$2:B$1000"),"Female") -> 7 | I42: =COUNTIF(INDIRECT($B42&"!B$2:B$1000"),"Diverse") -> 0 | J42: =H42/C42 -> 0.26923077 | K42: =COUNTIF(INDIRECT($B42&"!E$2:E$1000"),"Yes") -> 19 | L42: =K42/C42 -> 0.73076923 | M42: =COUNTIF(INDIRECT($B42&"!F$2:F$1000"),"Yes") -> 4 | N42: =M42/C42 -> 0.15384615 | O42: =COUNTIF(INDIRECT($B42&"!I$2:I$1000"),"Yes") -> 6 | P42: =O42/C42 -> 0.23076923 | Q42: 6 | R42: =Q42/C42 -> 0.23076923 | S42: 9 | T42: =S42/C42 -> 0.34615385 | U42: 11 | V42: 12 | W42: 11 | X42: =W42/C42 -> 0.42307692
A43: 46162 | B43: Boreholes | C43: 68 | E43: 41
A44: Summary | B44: 6 Portal Trg | C44: =SUM(C38:C43) -> 342 | D44: =SUM(D38:D42) -> 274 | E44: =SUM(E38:E43) -> 228 | F44: =E44/C44 -> 0.66666667 | G44: =SUM(G38:G42) -> 174 | H44: =SUM(H38:H42) -> 98 | I44: =SUM(I38:I42) -> 2 | J44: =H44/C44 -> 0.28654971 | K44: =SUM(K38:K42) -> 152 | L44: =K44/C44 -> 0.44444444 | M44: =SUM(M38:M42) -> 53 | N44: =M44/C44 -> 0.15497076 | O44: =SUM(O38:O42) -> 135 | P44: =O44/C44 -> 0.39473684
B45: .
A46: 45047 | B46: ShakeMap1 | C46: 40 | D46: =G46+H46+I46 -> 38 | E46: =22+16 -> 38 | F46: =E46/C46 -> 0.95 | G46: 25 | H46: 13 | I46: 0 | J46: =H46/C46 -> 0.325 | S46: 12 | T46: =S46/C46 -> 0.3
A47: 45444 | B47: ShakeMap2 | C47: {=COUNT(INDIRECT(B47&"!A$2:A$1000"))} -> 74 | D47: =G47+H47+I47 -> 74 | E47: 70 | F47: =E47/C47 -> 0.94594595 | G47: {=COUNTIF(INDIRECT($B47&"!B$2:B$1000"),"Male")} -> 34 | H47: {=COUNTIF(INDIRECT($B47&"!B$2:B$1000"),"Female")} -> 40 | I47: {=COUNTIF(INDIRECT($B47&"!B$2:B$1000"),"Diverse")} -> 0 | J47: =H47/C47 -> 0.54054054 | K47: {=COUNTIF(INDIRECT($B47&"!E$2:E$1000"),"Yes")} -> 15 | L47: =K47/C47 -> 0.2027027 | M47: {=COUNTIF(INDIRECT($B47&"!F$2:F$1000"),"Yes")} -> 2 | N47: =M47/C47 -> 0.027027027 | S47: 20 | T47: =S47/C47 -> 0.27027027 | U47: 8 | V47: 26 | W47: 9 | X47: =W47/C47 -> 0.12162162
A48: 45813 | B48: ShakeMap3 | C48: 72 | D48: =G48+H48+I48 -> 69 | E48: =23+46 -> 69 | F48: =E48/C48 -> 0.95833333 | G48: 39 | H48: =11+19 -> 30 | I48: 0 | J48: =H48/C48 -> 0.41666667
A49: Summary | B49: 3 ShakeMap WS | C49: =SUM(C46:C48) -> 186 | D49: =SUM(D46:D47) -> 112 | E49: =SUM(E46:E48) -> 177 | F49: =E49/C49 -> 0.9516129 | G49: =SUM(G46:G48) -> 98 | H49: =SUM(H46:H48) -> 83 | I49: =SUM(I46:I47) -> 0 | J49: =H49/C49 -> 0.44623656
A51: 45901 | B51: Barcelona_TsunamiGenesis | C51: 26 | D51: =G51+H51+I51 -> 26 | E51: 26 | F51: =E51/$C51 -> 1 | G51: {=COUNTIF(INDIRECT($B51&"!B$2:B$1000"),"Male")} -> 19 | H51: {=COUNTIF(INDIRECT($B51&"!B$2:B$1000"),"Female")} -> 7 | I51: {=COUNTIF(INDIRECT($B51&"!B$2:B$1000"),"Diverse")} -> 0 | J51: =H51/C51 -> 0.26923077 | K51: {=COUNTIF(INDIRECT($B51&"!E$2:E$1000"),"Yes")} -> 16 | L51: =K51/$C$23 -> 0.10738255 | M51: {=COUNTIF(INDIRECT($B51&"!F$2:F$1000"),"Yes")} -> 2 | N51: =M51/C51 -> 0.076923077 | O51: {=COUNTIF(INDIRECT($B51&"!I$2:I$1000"),"Yes")} -> 19 | P51: =O51/$C$23 -> 0.12751678 | Q51: 19 | R51: =Q51/E51 -> 0.73076923 | S51: 3 | T51: =S51/$C$23 -> 0.020134228 | U51: 13 | V51: 11 | W51: 8 | X51: =W51/C51 -> 0.30769231
A52: 46113 | B52: Messina_EQTsunamiWFs | C52: 68 | D52: =G52+H52+I52 -> 28 | E52: 28 | G52: 16 | H52: 12 | I52: 0 | J52: =H52/C52 -> 0.17647059 | K52: 15 | L52: =K52/E52 -> 0.53571429
A53: June 2026 | B53: Potsdam_PTRA | C53: 31 | E53: 26 | J53: =H53/C53 -> 0
A54: Summary | B54: 3 Geohazard WS | C54: =SUM(C51:C53) -> 125 | D54: =SUM(D51:D52) -> 54 | E54: =SUM(E51:E53) -> 80 | F54: =E54/C54 -> 0.64 | G54: =SUM(G51:G53) -> 35 | H54: =SUM(H51:H53) -> 19 | I54: =SUM(I51:I52) -> 0 | J54: =H54/C54 -> 0.152
B55: .
A56: March 2024 | B56: ORFEUS_1_SMS | C56: 68 | D56: =G56+H56+I56 -> 68 | E56: 53 | F56: =E56/C56 -> 0.77941176 | G56: =C56-H56-I56 -> 31 | H56: 36 | I56: 1 | J56: =H56/C56 -> 0.52941176 | K56: 21 | L56: =K56/C56 -> 0.30882353 | M56: 5 | N56: =M56/C56 -> 0.073529412 | O56: =C56-31 -> 37 | P56: =O56/C56 -> 0.54411765 | Q56: 25 | R56: =Q56/E56 -> 0.47169811 | S56: 28 | T56: =S56/C56 -> 0.41176471 | U56: 12 | V56: 25 | W56: 5 | X56: =W56/C56 -> 0.073529412
A57: March 2024 | B57: ORFEUS_2_ESM | C57: 53 | D57: =G57+H57+I57 -> 53 | E57: 30 | F57: =E57/C57 -> 0.56603774 | G57: =C57-H57-I57 -> 30 | H57: 23 | I57: 0 | J57: =H57/C57 -> 0.43396226 | K57: 19 | L57: =K57/C57 -> 0.35849057 | M57: 4 | N57: =M57/C57 -> 0.075471698 | O57: =C57-33 -> 20 | P57: =O57/C57 -> 0.37735849 | Q57: 25 | R57: =Q57/E57 -> 0.83333333 | S57: 24 | T57: =S57/C57 -> 0.45283019 | U57: 12 | V57: 21 | W57: 4 | X57: =W57/C57 -> 0.075471698
A58: 45383 | B58: ORFEUS_3_EIDA | C58: 71 | D58: =G58+H58+I58 -> 71 | E58: 44 | F58: =E58/C58 -> 0.61971831 | G58: =C58-H58-I58 -> 35 | H58: 35 | I58: 1 | J58: =H58/C58 -> 0.49295775 | K58: 26 | L58: =K58/C58 -> 0.36619718 | M58: 3 | N58: =M58/C58 -> 0.042253521 | O58: =C58-25 -> 46 | P58: =O58/C58 -> 0.64788732 | Q58: 25 | R58: =Q58/E58 -> 0.56818182 | S58: 33 | T58: =S58/C58 -> 0.46478873 | U58: 12 | V58: 23 | W58: 1 | X58: =W58/C58 -> 0.014084507
A59: May 2024 | B59: ORFEUS_4_Curate | C59: 64 | D59: =G59+H59+I59 -> 64 | E59: 36 | F59: =E59/C59 -> 0.5625 | G59: =C59-H59-I59 -> 41 | H59: 23 | I59: 0 | J59: =H59/C59 -> 0.359375 | K59: 15 | L59: =K59/C59 -> 0.234375 | M59: 3 | N59: =M59/C59 -> 0.046875 | O59: =C59-9 -> 55 | P59: =O59/C59 -> 0.859375 | Q59: 25 | R59: =Q59/E59 -> 0.69444444 | S59: 27 | T59: =S59/C59 -> 0.421875 | U59: 12 | V59: 23 | W59: 1 | X59: =W59/C59 -> 0.015625
A60: June 2024 | B60: ORFEUS_5_EIDAWFCat. | C60: 54 | D60: =G60+H60+I60 -> 54 | E60: 33 | F60: =E60/C60 -> 0.61111111 | G60: =C60-H60-I60 -> 31 | H60: 22 | I60: 1 | J60: =H60/C60 -> 0.40740741 | K60: 17 | L60: =K60/C60 -> 0.31481481 | M60: 3 | N60: =M60/C60 -> 0.055555556 | O60: =C60-6 -> 48 | P60: =O60/C60 -> 0.88888889 | Q60: 25 | R60: =Q60/E60 -> 0.75757576 | S60: 33 | T60: =S60/C60 -> 0.61111111 | U60: 13 | V60: 19 | W60: 0 | X60: =W60/C60 -> 0
A61: 45597 | B61: ORFEUS_WS_Helsinki (attendance onsite+online) - to review | C61: 128 | D61: 128 | E61: 117 | F61: =E61/C61 -> 0.9140625 | G61: 67 | H61: 57 | I61: 4 | J61: =H61/C61 -> 0.4453125 | K61: 49 | L61: =K61/C61 -> 0.3828125 | M61: 6 | N61: =M61/C61 -> 0.046875 | O61: 73 | P61: =O61/C61 -> 0.5703125 | Q61: 26 | R61: =Q61/E61 -> 0.22222222 | S61: 45 | T61: =S61/C61 -> 0.3515625 | U61: 13 | V61: 33 | W61: 6 | X61: =W61/C61 -> 0.046875
A62: 45748 | B62: ORFEUS_6_SubMachine | C62: 57 | D62: 57 | E62: 39 | F62: =E62/C62 -> 0.68421053 | G62: 28 | H62: 24 | I62: 5 | J62: =H62/C62 -> 0.42105263 | K62: 19 | L62: =K62/C62 -> 0.33333333 | M62: 5 | N62: =M62/C62 -> 0.087719298 | O62: 13 | P62: =O62/C62 -> 0.22807018 | Q62: 19 | R62: =Q62/E62 -> 0.48717949 | S62: 19 | T62: =S62/C62 -> 0.33333333 | U62: 13 | V62: 21 | W62: 5 | X62: =W62/C62 -> 0.087719298 | Y62: 1
A63: May 2025 | B63: ORFEUS_7_AdriaArray | C63: 93 | D63: 93 | E63: 76 | F63: =E63/C63 -> 0.8172043 | G63: 47 | H63: 41 | I63: 5 | J63: =H63/C63 -> 0.44086022 | K63: 36 | L63: =K63/C63 -> 0.38709677 | M63: 3 | N63: =M63/C63 -> 0.032258065 | O63: 78 | P63: =O63/C63 -> 0.83870968 | Q63: 19 | R63: =Q63/E63 -> 0.25 | S63: 55 | T63: =S63/C63 -> 0.59139785 | U63: 13 | V63: 29 | W63: 10 | X63: =W63/C63 -> 0.10752688 | Y63: 3
A64: 45839 | B64: ORFEUS_8_Conrad/BlackForest | C64: 60 | D64: 60 | E64: 30 | F64: =E64/C64 -> 0.5 | G64: 34 | H64: 23 | I64: 3 | J64: =H64/C64 -> 0.38333333 | K64: 17 | L64: =K64/C64 -> 0.28333333 | M64: 4 | N64: =M64/C64 -> 0.066666667 | O64: 25 | P64: =O64/C64 -> 0.41666667 | Q64: 19 | R64: =Q64/E64 -> 0.63333333 | S64: 22 | T64: =S64/C64 -> 0.36666667 | U64: 12 | V64: 22 | W64: 4 | X64: =W64/C64 -> 0.066666667 | Y64: 2
A65: 45962 | B65: ORFEUS_WS_Athens (attendance onsite + online) | C65: =125+93 -> 218 | D65: =125+93 -> 218 | E65: =120+59 -> 179 | F65: =E65/C65 -> 0.82110092 | G65: =68+57 -> 125 | H65: =54+46 -> 100 | I65: =3+2 -> 5 | J65: =H65/C65 -> 0.4587156 | K65: =28+52 -> 80 | L65: =K65/C65 -> 0.36697248 | M65: =10+3 -> 13 | N65: =M65/C65 -> 0.059633028 | O65: =94+75 -> 169 | P65: =O65/C65 -> 0.77522936 | Q65: 58 | R65: =Q65/E65 -> 0.32402235 | S65: =65+29 -> 94 | T65: =S65/C65 -> 0.43119266 | U65: 15 | V65: 43 | W65: 35 | X65: =W65/C65 -> 0.16055046 | Y65: 5
A66: May 2026 | B66: ORFEUS_9_StationExpl | C66: 83 | D66: 83 | E66: 49 | F66: =E66/C66 -> 0.59036145 | G66: 43 | H66: 32 | I66: 8 | J66: =H66/C66 -> 0.38554217 | K66: 39 | L66: =K66/C66 -> 0.46987952 | M66: 4 | N66: =M66/C66 -> 0.048192771 | O66: 38 | P66: =O66/C66 -> 0.45783133 | Q66: 14 | R66: =Q66/E66 -> 0.28571429 | S66: 32 | T66: =S66/C66 -> 0.38554217 | U66: 16 | V66: 31 | W66: 10 | X66: =W66/C66 -> 0.12048193 | Y66: 0
A67: June 2026 | B67: ORFEUS_10_obsinfo_yasmine | C67: 44 | D67: 44 | E67: 34 | F67: =E67/C67 -> 0.77272727 | G67: 22 | H67: 19 | I67: 3 | J67: =H67/C67 -> 0.43181818 | K67: 16 | L67: =K67/C67 -> 0.36363636 | M67: 3 | N67: =M67/C67 -> 0.068181818 | O67: 7 | P67: =O67/C67 -> 0.15909091 | Q67: 14 | R67: =Q67/E67 -> 0.41176471 | S67: 15 | T67: =S67/C67 -> 0.34090909 | U67: 11 | V67: 17 | W67: 7 | X67: =W67/C67 -> 0.15909091 | Y67: 0
A68: 46266 | B68: ORFEUS_WS_Istanbul | C68: 110 | D68: 110 | E68: 100 | F68: =E68/C68 -> 0.90909091 | G68: =29+14 -> 43 | H68: =39+26 -> 65 | I68: =1+1 -> 2 | J68: =H68/C68 -> 0.59090909 | K68: 71 | L68: =K68/C68 -> 0.64545455 | M68: 3 | N68: =M68/C68 -> 0.027272727 | S68: =31+14 -> 45 | T68: =S68/C68 -> 0.40909091 | U68: 16 | V68: 33 | W68: 30 | X68: =W68/C68 -> 0.27272727 | Y68: 2 | Z68: preliminary data based on current registrations
A69: Summary | B69: 13 ORFEUS Events | C69: =SUM(C56:C68) -> 1103 | D69: =SUM(D56:D68) -> 1103 | E69: =SUM(E56:E68) -> 820 | F69: =E69/C69 -> 0.74342702 | G69: =SUM(G56:G68) -> 577 | H69: =SUM(H56:H68) -> 500 | I69: =SUM(I56:I68) -> 38 | J69: =H69/C69 -> 0.45330916 | K69: =SUM(K56:K68) -> 425 | L69: =K69/C69 -> 0.38531278 | M69: =SUM(M56:M68) -> 59 | N69: =M69/C69 -> 0.053490481 | O69: =SUM(O56:O68) -> 609 | P69: =O69/C69 -> 0.55213055
B70: .
A71: July 2024 | B71: EGU Galileo Conf | C71: 149 | D71: =G71+H71+I71 -> 148 | E71: 148 | F71: =E71/C71 -> 0.99328859 | G71: 108 | H71: 38 | I71: 2 | J71: =H71/C71 -> 0.25503356 | K71: 79 | L71: =K71/C71 -> 0.53020134 | O71: 134 | P71: =O71/C71 -> 0.89932886 | S71: 4 | T71: =S71/C71 -> 0.026845638 | U71: 5 | V71: 19 | W71: 20 | X71: =W71/C71 -> 0.13422819
A72: 45536 | B72: GEM-EGU SummerSchool | C72: 22 | D72: =G72+H72+I72 -> 22 | E72: 22 | F72: 1 | G72: 13 | H72: 9 | I72: 0 | J72: =H72/E72 -> 0.40909091 | K72: 19 | L72: =K72/C72 -> 0.86363636 | M72: 6 | N72: =M72/C72 -> 0.27272727 | Q72: 22 | R72: =Q72/E72 -> 1 | S72: 5 | T72: =S72/C72 -> 0.22727273 | U72: 7 | V72: 14 | W72: 5 | X72: =W72/C72 -> 0.22727273 | Z72: 70 applications for 20 seats
A73: 45772 | B73: EPISODES_Hackathon | C73: {=COUNT(INDIRECT(B73&"!A$2:A$1000"))} -> 20 | D73: =G73+H73+I73 -> 20 | E73: 14 | F73: =E73/C73 -> 0.7 | G73: {=COUNTIF(INDIRECT($B73&"!B$2:B$1000"),"Male")} -> 11 | H73: {=COUNTIF(INDIRECT($B73&"!B$2:B$1000"),"Female")} -> 9 | I73: {=COUNTIF(INDIRECT($B73&"!B$2:B$1000"),"Diverse")} -> 0 | J73: =H73/C73 -> 0.45 | K73: {=COUNTIF(INDIRECT($B73&"!E$2:E$1000"),"Yes")} -> 14 | L73: =K73/C73 -> 0.7 | M73: {=COUNTIF(INDIRECT($B73&"!F$2:F$1000"),"Yes")} -> 1 | N73: =M73/C73 -> 0.05 | O73: {=COUNTIF(INDIRECT($B73&"!I$2:I$1000"),"Yes")} -> 4 | P73: =O73/C73 -> 0.2 | Q73: 3 | R73: =Q73/C73 -> 0.15 | S73: 16 | T73: =S73/C73 -> 0.8 | U73: 14 | V73: 7 | W73: 1 | X73: =W73/C73 -> 0.05
A74: May 2025 | B74: AI4Seismology | C74: 33 | D74: 33 | E74: 33 | F74: 1 | G74: 18 | H74: 15 | I74: 0 | J74: =H74/C74 -> 0.45454545 | K74: 30 | L74: =K74/C74 -> 0.90909091 | M74: 0 | N74: =M74/C74 -> 0 | O74: 30 | P74: =O74/C74 -> 0.90909091 | Q74: 33 | R74: =Q74/E74 -> 1 | S74: 22 | T74: =S74/C74 -> 0.66666667 | U74: 5 | V74: 11 | W74: 4 | X74: =W74/C74 -> 0.12121212
A75: Oct. 2025 | B75: Geo-i SummerSchool | C75: 104 | D75: 38 | E75: 38 | F75: 1 | G75: 19 | H75: 19 | I75: 0 | J75: =H75/E75 -> 0.5 | Q75: 25
A76: June 2026 | B76: GFZ_Intl_Trg_Course | C76: 105 | E76: 20
A77: Summary | B77: 5 Schools | C77: =SUM(C71:C76) -> 433 | D77: =SUM(D71:D76) -> 261 | E77: =SUM(E71:E76) -> 275 | F77: =E77/C77 -> 0.63510393 | G77: =SUM(G71:G76) -> 169 | H77: =SUM(H71:H76) -> 90 | I77: =SUM(I71:I76) -> 2 | J77: =H77/C77 -> 0.20785219 | K77: =SUM(K71:K76) -> 142 | L77: =K77/C77 -> 0.32794457 | M77: =SUM(M71:M72) -> 6 | N77: =SUM(N71:N72) -> 0.27272727 | P77: =AVERAGE(P71:P74) -> 0.66947326
B79: Sum | C79: =SUM(C2:C77)/2 -> 4447 | D79: =G79+H79+I79 -> 4007 | E79: =SUM(E2:E77)/2 -> 3113 | F79: =E79/C79 -> 0.70002249 | G79: =SUM(G2:G77)/2 -> 2186 | H79: =SUM(H2:H77)/2 -> 1759 | I79: =SUM(I2:I77)/2 -> 62 | J79: =H79/C79 -> 0.39554756 | K79: =SUM(K2:K77)/2 -> 1482 | L79: =AVERAGE(L2:L77) -> 0.42293633 | N79: =AVERAGE(N2:N77) -> 0.082844227 | P79: =AVERAGE(P2:P77) -> 0.44032348 | R79: =AVERAGE(R2:R77) -> 0.43269546 | S79: =SUM(S2:S77)/2 -> 461 | U79: =AVERAGE(U2:U77) -> 13.037736 | V79: =AVERAGE(V2:V77) -> 18.153846

Sheet AllParticpants
A1: ID | B1: Gender | C1: Affiliation | D1: Country of Affiliation | E1: Are you an Early Career Scientist? | F1: Do you work in industry, a Start-up or Small and Medium Enterprise? | G1: What is your scientific expertise? (Multiple Choice) | H1: Scientific expertise - Other(s): | I1: Have you used this installation before? | J1: Registration date | K1: Registration state | L1: Training | N1: Events | O1: Countries | P1: No_Countries | Q1: Category | S1: Countries | T1: No_Countries | U1: Category | X1: Country | Y1: # Registrations
A2: 37 | B2: Male | C2: IPGP | D2: France | E2: Yes | F2: No | G2: Seismology | I2: No | J2: Sep 29, 2023, 11:59 AM | K2: Completed | L2: EPOSMetadata | N2: {=UNIQUE(L2:L3120)} -> EPOSMetadata | O2: {=UNIQUE(D2:D3120)} -> France | P2: =COUNTIF(D$2:D$3120,O2) -> 131 | Q2: {=XLOOKUP(O2,Countries!A$2:A$120,Countries!B$2:B$120,"tbd",0)} -> Europe | S2: Algeria | T2: 4 | U2: Africa | X2: Africa | Y2: =SUM(T2:T12) -> 56
A3: 34 | B3: Male | C3: EMSO ERIC | D3: Italy | E3: No | F3: No | G3: Marine Sciences | I3: No | J3: Sep 29, 2023, 11:05 AM | K3: Completed | L3: EPOSMetadata | N3: ETRIS | O3: Italy | P3: =COUNTIF(D$2:D$3120,O3) -> 277 | Q3: {=XLOOKUP(O3,Countries!A$2:A$120,Countries!B$2:B$120,"tbd",0)} -> Europe | S3: Cameroon | T3: 3 | U3: Africa | X3: Asia | Y3: =SUM(T13:T25) -> 121
A4: 15 | B4: Female | C4: CNRS | D4: France | E4: Yes | F4: No | G4: Geohazard | H4: Data manager | I4: Yes | J4: Sep 28, 2023, 3:09 PM | K4: Completed | L4: EPOSMetadata | N4: HySEA_T | O4: Turkey | P4: =COUNTIF(D$2:D$3120,O4) -> 62 | Q4: {=XLOOKUP(O4,Countries!A$2:A$120,Countries!B$2:B$120,"tbd",0)} -> associated countries | S4: Congo - Kinshasa | T4: 1 | U4: Africa | X4: Middle East | Y4: 153
A5: 19 | B5: Male | C5: CNRS - OPGC | D5: France | E5: Yes | F5: No | G5: Engineering | I5: Yes | J5: Sep 28, 2023, 3:32 PM | K5: Completed | L5: EPOSMetadata | N5: FAIR1 | O5: New Zealand | P5: =COUNTIF(D$2:D$3120,O5) -> 13 | Q5: {=XLOOKUP(O5,Countries!A$2:A$120,Countries!B$2:B$120,"tbd",0)} -> associated countries | S5: Ethiopia | T5: 3 | U5: Africa | X5: Middle/South America | Y5: 90
A6: 9 | B6: Male | C6: ISTerre | D6: France | E6: Yes | F6: No | G6: Seismology | I6: No | J6: Sep 28, 2023, 1:59 PM | K6: Completed | L6: EPOSMetadata | N6: EPISODES_WS | O6: Germany | P6: =COUNTIF(D$2:D$3120,O6) -> 187 | Q6: {=XLOOKUP(O6,Countries!A$2:A$120,Countries!B$2:B$120,"tbd",0)} -> Europe | S6: Ghana | T6: 4 | U6: Africa | X6: Australia | Y6: 9
A7: 5 | B7: Female | C7: Istituto Nazionale di Geofisica e Vulcanologia | D7: Italy | E7: No | F7: No | G7: Geohazard; Tsunami | I7: Yes | J7: Sep 28, 2023, 1:27 PM | K7: Completed | L7: EPOSMetadata | N7: FAIR2 | O7: Finland | P7: =COUNTIF(D$2:D$3120,O7) -> 28 | Q7: {=XLOOKUP(O7,Countries!A$2:A$120,Countries!B$2:B$120,"tbd",0)} -> Europe | S7: Malawi | T7: 1 | U7: Africa | X7: US+Canada | Y7: =SUM(T78:T79) -> 200
A8: 70 | B8: Female | C8: Ingv | D8: Italy | E8: No | F8: No | G8: Computer Science | I8: Yes | J8: Oct 13, 2023, 5:54 PM | K8: Completed | L8: EPOSMetadata | N8: SDL_WS | O8: Romania | P8: =COUNTIF(D$2:D$3120,O8) -> 43 | Q8: {=XLOOKUP(O8,Countries!A$2:A$120,Countries!B$2:B$120,"tbd",0)} -> widening countries | S8: Morocco | T8: 25 | U8: Africa | X8: EU | Y8: 1159
A9: 12 | B9: Female | C9: Boğaziçi University- KOERI | D9: Turkey | E9: No | F9: No | G9: Seismology; Tsunami | I9: Yes | J9: Sep 28, 2023, 2:23 PM | K9: Completed | L9: EPOSMetadata | N9: ShakeMap2 | O9: Australia | P9: =COUNTIF(D$2:D$3120,O9) -> 9 | Q9: {=XLOOKUP(O9,Countries!A$2:A$120,Countries!B$2:B$120,"tbd",0)} -> Oceania | S9: Mozambique | T9: 5 | U9: Africa | X9: EU Widening Countries | Y9: 390
A10: 52 | B10: Female | C10: CINECA | D10: Italy | E10: No | F10: No | G10: Other | I10: No | J10: Oct 5, 2023, 10:25 AM | K10: Completed | L10: EPOSMetadata | N10: PyBET | O10: Switzerland | P10: =COUNTIF(D$2:D$3120,O10) -> 38 | Q10: {=XLOOKUP(O10,Countries!A$2:A$120,Countries!B$2:B$120,"tbd",0)} -> Europe | S10: Nigeria | T10: 6 | U10: Africa | X10: EU Associated Countries | Y10: =SUM(T26:T38) -> 281
A11: 80 | B11: Female | C11: WSP | D11: New Zealand | E11: Yes | F11: Yes | G11: Engineering; Seismology | I11: No | J11: Oct 16, 2023, 8:48 PM | K11: Completed | L11: EPOSMetadata | N11: SLIP | O11: United Kingdom | P11: =COUNTIF(D$2:D$3120,O11) -> 65 | Q11: {=XLOOKUP(O11,Countries!A$2:A$120,Countries!B$2:B$120,"tbd",0)} -> associated countries | S11: Uganda | T11: 3 | U11: Africa | Y11: Sum | Z11: =SUM(Y2:Y10) -> 2459
A12: 36 | B12: Female | C12: LMU - Dept. of Geophysics | D12: Germany | E12: No | F12: No | G12: Computer Science | I12: Yes | J12: Sep 29, 2023, 11:31 AM | K12: Completed | L12: EPOSMetadata | N12: FAIR3 | O12: Belgium | P12: =COUNTIF(D$2:D$3120,O12) -> 44 | Q12: {=XLOOKUP(O12,Countries!A$2:A$120,Countries!B$2:B$120,"tbd",0)} -> Europe | S12: Zimbabwe | T12: 1 | U12: Africa | V12: =SUM(T2:T12) -> 56 | Y12: EU Percentage | Z12: =SUM(Y8:Y10)/Z11 -> 0.74420496
A13: 16 | B13: Female | C13: ISPRA | D13: Italy | E13: No | F13: No | G13: Computer Science | I13: No | J13: Sep 28, 2023, 3:15 PM | K13: Completed | L13: EPOSMetadata | N13: SiteEffects | O13: Spain | P13: =COUNTIF(D$2:D$3120,O13) -> 205 | Q13: {=XLOOKUP(O13,Countries!A$2:A$120,Countries!B$2:B$120,"tbd",0)} -> Europe | S13: China | T13: 30 | U13: Asia
A14: 73 | B14: Male | C14: University of Helsinki | D14: Finland | E14: No | F14: No | G14: Computer Science; Engineering; Seismology | H14: Seismic ambient noise | I14: No | J14: Oct 16, 2023, 10:36 AM | K14: Completed | L14: EPOSMetadata | N14: HPS1 | O14: Iceland | P14: =COUNTIF(D$2:D$3120,O14) -> 34 | Q14: {=XLOOKUP(O14,Countries!A$2:A$120,Countries!B$2:B$120,"tbd",0)} -> associated countries | S14: Hongkong | T14: 3 | U14: Asia
A15: 79 | B15: Female | C15: National Institute for Earth Physics | D15: Romania | E15: No | F15: No | G15: Seismology | I15: Yes | J15: Oct 16, 2023, 3:53 PM | K15: Completed | L15: EPOSMetadata | N15: FAIR4 | O15: Greece | P15: =COUNTIF(D$2:D$3120,O15) -> 86 | Q15: {=XLOOKUP(O15,Countries!A$2:A$120,Countries!B$2:B$120,"tbd",0)} -> widening countries | S15: Indonesia | T15: 31 | U15: Asia
A16: 28 | B16: Female | C16: National Computational Infrastructure | D16: Australia | E16: No | F16: No | G16: Other | H16: Metadata, repository administration | I16: No | J16: Sep 29, 2023, 12:19 AM | K16: Completed | L16: EPOSMetadata | N16: FAIR5 | O16: Norway | P16: =COUNTIF(D$2:D$3120,O16) -> 41 | Q16: {=XLOOKUP(O16,Countries!A$2:A$120,Countries!B$2:B$120,"tbd",0)} -> associated countries | S16: Japan | T16: 14 | U16: Asia
A17: 17 | B17: Male | C17: ETH Zurich | D17: Switzerland | E17: No | F17: No | G17: Geohazard; Seismology | I17: Yes | J17: Sep 28, 2023, 3:18 PM | K17: Completed | L17: EPOSMetadata | N17: SLSMF | O17: Croatia | P17: =COUNTIF(D$2:D$3120,O17) -> 23 | Q17: {=XLOOKUP(O17,Countries!A$2:A$120,Countries!B$2:B$120,"tbd",0)} -> widening countries | S17: Kyrgyzstan | T17: 1 | U17: Asia
A18: 55 | B18: Female | C18: EPOS ERIC | D18: Italy | E18: No | F18: No | G18: Energy Transformation/Storage; Engineering | I18: No | J18: Oct 7, 2023, 11:52 PM | K18: Completed | L18: EPOSMetadata | N18: HySEA_L | O18: Poland | P18: =COUNTIF(D$2:D$3120,O18) -> 69 | Q18: {=XLOOKUP(O18,Countries!A$2:A$120,Countries!B$2:B$120,"tbd",0)} -> widening countries | S18: Malaysia | T18: 2 | U18: Asia
A19: 38 | B19: Female | C19: British Geological Survey/University of Edinburgh | D19: United Kingdom | E19: Yes | F19: No | G19: Computer Science; Engineering | I19: No | J19: Sep 29, 2023, 3:31 PM | K19: Completed | L19: EPOSMetadata | N19: FAIR6 | O19: Portugal | P19: =COUNTIF(D$2:D$3120,O19) -> 109 | Q19: {=XLOOKUP(O19,Countries!A$2:A$120,Countries!B$2:B$120,"tbd",0)} -> widening countries | S19: Maldives | T19: 1 | U19: Asia
A20: 4 | B20: Diverse | C20: GFZ Potsdam | D20: Germany | E20: No | F20: No | G20: Engineering; Seismology | I20: No | J20: Sep 28, 2023, 1:09 PM | K20: Completed | L20: EPOSMetadata | N20: EPOS_3 | O20: Bulgaria | P20: =COUNTIF(D$2:D$3120,O20) -> 12 | Q20: {=XLOOKUP(O20,Countries!A$2:A$120,Countries!B$2:B$120,"tbd",0)} -> widening countries | S20: Philippines | T20: 10 | U20: Asia
A21: 48 | B21: Male | C21: ROB | D21: Belgium | E21: No | F21: No | G21: Computer Science; Solid Earth | I21: Yes | J21: Oct 4, 2023, 9:54 AM | K21: Completed | L21: EPOSMetadata | N21: EPISODES_Trg | O21: Iran | P21: =COUNTIF(D$2:D$3120,O21) -> 57 | Q21: {=XLOOKUP(O21,Countries!A$2:A$120,Countries!B$2:B$120,"tbd",0)} -> Middle East | S21: Singapore | T21: 10 | U21: Asia
A22: 13 | B22: Male | C22: CSIC | D22: Spain | E22: No | F22: No | G22: Atmospheric Physics; Computer Science; Geohazard; Solid Earth; Volcanology | I22: Yes | J22: Sep 28, 2023, 2:58 PM | K22: Completed | L22: EPOSMetadata | N22: FAIR7 | O22: Netherlands | P22: =COUNTIF(D$2:D$3120,O22) -> 10 | Q22: {=XLOOKUP(O22,Countries!A$2:A$120,Countries!B$2:B$120,"tbd",0)} -> Europe | S22: South Korea | T22: 4 | U22: Asia
A23: 45 | B23: Female | C23: Icelandic Meteorological Office | D23: Iceland | E23: Yes | F23: No | G23: Solid Earth; Volcanology | H23: geodesy | I23: Yes | J23: Oct 3, 2023, 3:09 PM | K23: Completed | L23: EPOSMetadata | N23: ORFEUS_unique | O23: Taiwan | P23: =COUNTIF(D$2:D$3120,O23) -> 10 | Q23: {=XLOOKUP(O23,Countries!A$2:A$120,Countries!B$2:B$120,"tbd",0)} -> Asia | S23: Taiwan | T23: 10 | U23: Asia
A24: 88 | B24: Female | C24: ISPRA | D24: Italy | E24: Yes | F24: Yes | G24: Environmental Protection; Geohazard | I24: No | J24: Oct 19, 2023, 10:05 AM | K24: Completed | L24: EPOSMetadata | N24: Quakeworx | O24: Canada | P24: =COUNTIF(D$2:D$3120,O24) -> 14 | Q24: {=XLOOKUP(O24,Countries!A$2:A$120,Countries!B$2:B$120,"tbd",0)} -> U.S. + Canada | S24: United Arab Emirates | T24: 2 | U24: Asia
A25: 67 | B25: Male | C25: Aristotle University of Thessaloniki - Dpt of Geophysics | D25: Greece | E25: No | F25: No | G25: Seismology | I25: Yes | J25: Oct 13, 2023, 12:50 PM | K25: Completed | L25: EPOSMetadata | N25: Hackathon1 | O25: United States | P25: =COUNTIF(D$2:D$3120,O25) -> 186 | Q25: {=XLOOKUP(O25,Countries!A$2:A$120,Countries!B$2:B$120,"tbd",0)} -> U.S. + Canada | S25: Vietnam | T25: 3 | U25: Asia | V25: =SUM(T13:T25) -> 121
A26: 58 | B26: Female | C26: National Institute for Earth Physics | D26: Romania | E26: No | F26: No | G26: Atmospheric Physics; Seismology | I26: Yes | J26: Oct 10, 2023, 2:01 PM | K26: Completed | L26: EPOSMetadata | N26: EPOS_Trg_CZ | O26: Japan | P26: =COUNTIF(D$2:D$3120,O26) -> 14 | Q26: {=XLOOKUP(O26,Countries!A$2:A$120,Countries!B$2:B$120,"tbd",0)} -> Asia | S26: Albania | T26: 24 | U26: associated countries
A27: 32 | B27: Male | C27: University of Grenoble Alpes | D27: France | E27: Yes | F27: No | G27: Engineering; Geohazard; Seismology | I27: No | J27: Sep 29, 2023, 10:48 AM | K27: Completed | L27: EPOSMetadata | N27: EPOS_Trg_Spain | O27: Malta | P27: =COUNTIF(D$2:D$3120,O27) -> 3 | Q27: {=XLOOKUP(O27,Countries!A$2:A$120,Countries!B$2:B$120,"tbd",0)} -> widening countries | S27: Bosnia and Herzegovina | T27: 3 | U27: associated countries
A28: 56 | B28: Female | C28: NORSAR | D28: Norway | E28: Yes | F28: No | G28: Geohazard; Seismology | I28: Yes | J28: Oct 9, 2023, 3:36 PM | K28: Completed | L28: EPOSMetadata | N28: EPOS_SummerSchool | O28: Bangladesh | P28: =COUNTIF(D$2:D$3120,O28) -> 3 | Q28: {=XLOOKUP(O28,Countries!A$2:A$120,Countries!B$2:B$120,"tbd",0)} -> Middle East | S28: Iceland | T28: 34 | U28: associated countries
A29: 49 | B29: Male | C29: Universidad de Málaga | D29: Spain | E29: No | F29: No | G29: Computer Science; Geohazard; Tsunami | I29: No | J29: Oct 4, 2023, 5:41 PM | K29: Completed | L29: EPOSMetadata | N29: EPOSTrg_S4E | O29: Pakistan | P29: =COUNTIF(D$2:D$3120,O29) -> 13 | Q29: {=XLOOKUP(O29,Countries!A$2:A$120,Countries!B$2:B$120,"tbd",0)} -> Middle East | S29: Israel | T29: 7 | U29: associated countries
A30: 23 | B30: Female | C30: Geosciences Barcelona- CSIC | D30: Spain | E30: Yes | F30: No | G30: Atmospheric Physics; Computer Science; Geohazard; Volcanology | I30: No | J30: Sep 28, 2023, 3:59 PM | K30: Completed | L30: EPOSMetadata | N30: EPOSTrg_France | O30: India | P30: =COUNTIF(D$2:D$3120,O30) -> 49 | Q30: {=XLOOKUP(O30,Countries!A$2:A$120,Countries!B$2:B$120,"tbd",0)} -> Middle East | S30: Montenegro | T30: 6 | U30: associated countries
A31: 7 | B31: Female | C31: University of Helsinki | D31: Finland | E31: No | F31: No | G31: Atmospheric Physics | H31: Research infrastructure coordination | I31: Yes | J31: Sep 28, 2023, 1:53 PM | K31: Completed | L31: EPOSMetadata | N31: EPOSTrg_EGU25 | O31: Egypt | P31: =COUNTIF(D$2:D$3120,O31) -> 13 | Q31: {=XLOOKUP(O31,Countries!A$2:A$120,Countries!B$2:B$120,"tbd",0)} -> Middle East | S31: New Zealand | T31: 13 | U31: associated countries
A32: 46 | B32: Male | C32: National Computational Infrastructure | D32: Australia | E32: Yes | F32: Yes | G32: Computer Science; Seismology | H32: Glaciology | I32: No | J32: Oct 3, 2023, 4:03 PM | K32: Completed | L32: EPOSMetadata | N32: EPOSTrg_Online25 | O32: Nepal | P32: =COUNTIF(D$2:D$3120,O32) -> 4 | Q32: {=XLOOKUP(O32,Countries!A$2:A$120,Countries!B$2:B$120,"tbd",0)} -> Middle East | S32: North Macedonia | T32: 17 | U32: associated countries
A33: 30 | B33: Male | C33: Federal Institute for Geosciences and Natural Resources (BGR) | D33: Germany | E33: Yes | F33: No | G33: Atmospheric Physics | H33: infrasound | I33: Yes | J33: Sep 29, 2023, 9:27 AM | K33: Completed | L33: EPOSMetadata | N33: VIS_WS | O33: Albania | P33: =COUNTIF(D$2:D$3120,O33) -> 24 | Q33: {=XLOOKUP(O33,Countries!A$2:A$120,Countries!B$2:B$120,"tbd",0)} -> associated countries | S33: Norway | T33: 41 | U33: associated countries
A34: 31 | B34: Male | C34: Università degli Studi di Firenze | D34: Italy | E34: Yes | F34: No | G34: Atmospheric Physics; Computer Science; Geohazard; Seismology; Solid Earth; Tsunami; Volcanology | I34: No | J34: Sep 29, 2023, 10:40 AM | K34: Completed | L34: EPOSMetadata | N34: SDL_Trg | O34: Singapore | P34: =COUNTIF(D$2:D$3120,O34) -> 10 | Q34: {=XLOOKUP(O34,Countries!A$2:A$120,Countries!B$2:B$120,"tbd",0)} -> Asia | S34: Serbia | T34: 4 | U34: associated countries
A35: 76 | B35: Diverse | C35: GFZ Potsdam | D35: Germany | E35: Yes | F35: Yes | G35: Computer Science; Seismology; Solid Earth | I35: Yes | J35: Oct 16, 2023, 1:22 PM | K35: Completed | L35: EPOSMetadata | N35: Geohazard_WS1 | O35: Mexico | P35: =COUNTIF(D$2:D$3120,O35) -> 11 | Q35: {=XLOOKUP(O35,Countries!A$2:A$120,Countries!B$2:B$120,"tbd",0)} -> Middle/South America | S35: Tunisia | T35: 1 | U35: associated countries
A36: 2 | B36: Male | C36: GFZ | D36: Germany | E36: Yes | F36: No | G36: Computer Science; Engineering; Geohazard; Seismology | I36: No | J36: Sep 28, 2023, 1:00 PM | K36: Completed | L36: EPOSMetadata | O36: Peru | P36: =COUNTIF(D$2:D$3120,O36) -> 5 | Q36: {=XLOOKUP(O36,Countries!A$2:A$120,Countries!B$2:B$120,"tbd",0)} -> Middle/South America | S36: Turkey | T36: 62 | U36: associated countries
A37: 72 | B37: Female | C37: Seismologist | D37: Croatia | E37: No | F37: No | G37: Seismology; Solid Earth | I37: No | J37: Oct 15, 2023, 9:49 PM | K37: Completed | L37: EPOSMetadata | O37: China | P37: =COUNTIF(D$2:D$3120,O37) -> 30 | Q37: {=XLOOKUP(O37,Countries!A$2:A$120,Countries!B$2:B$120,"tbd",0)} -> Asia | S37: Ukraine | T37: 4 | U37: associated countries
A38: 6 | B38: Female | C38: University of Potsdam | D38: Germany | E38: Yes | F38: No | G38: Seismology | I38: No | J38: Sep 28, 2023, 1:47 PM | K38: Completed | L38: EPOSMetadata | O38: Tunisia | P38: =COUNTIF(D$2:D$3120,O38) -> 1 | Q38: {=XLOOKUP(O38,Countries!A$2:A$120,Countries!B$2:B$120,"tbd",0)} -> associated countries | S38: United Kingdom | T38: 65 | U38: associated countries | V38: =SUM(T26:T38) -> 281
A39: 21 | B39: Male | C39: DT-GEO / UKRI-BGS | D39: United Kingdom | E39: No | F39: No | G39: Computer Science | I39: Yes | J39: Sep 28, 2023, 3:52 PM | K39: Completed | L39: EPOSMetadata | O39: Philippines | P39: =COUNTIF(D$2:D$3120,O39) -> 10 | Q39: {=XLOOKUP(O39,Countries!A$2:A$120,Countries!B$2:B$120,"tbd",0)} -> Asia | S39: Andorra | T39: 2 | U39: Europe
A40: 86 | B40: Male | C40: National and Kapodistrian University of Athens | D40: Greece | E40: Yes | F40: No | G40: Seismology | I40: Yes | J40: Oct 18, 2023, 8:50 PM | K40: Completed | L40: EPOSMetadata | O40: Malaysia | P40: =COUNTIF(D$2:D$3120,O40) -> 2 | Q40: {=XLOOKUP(O40,Countries!A$2:A$120,Countries!B$2:B$120,"tbd",0)} -> Asia | S40: Austria | T40: 12 | U40: Europe
A41: 10 | B41: Female | C41: GFZ Potsdam | D41: Germany | E41: Yes | F41: No | G41: Atmospheric Physics; Computer Science; Environmental Protection; Energy Transformation/Storage; Engineering; Geohazard; Marine Sciences; Seismology; Solid Earth; Tsunami; Volcanology | I41: Yes | J41: Sep 28, 2023, 2:11 PM | K41: Completed | L41: EPOSMetadata | O41: Indonesia | P41: =COUNTIF(D$2:D$3120,O41) -> 31 | Q41: {=XLOOKUP(O41,Countries!A$2:A$120,Countries!B$2:B$120,"tbd",0)} -> Asia | S41: Belgium | T41: 44 | U41: Europe
A42: 87 | B42: Female | C42: Institute of Geophysics PAS | D42: Poland | E42: No | F42: No | G42: Geohazard; Solid Earth | I42: Yes | J42: Oct 19, 2023, 10:01 AM | K42: Completed | L42: EPOSMetadata | O42: Israel | P42: =COUNTIF(D$2:D$3120,O42) -> 7 | Q42: {=XLOOKUP(O42,Countries!A$2:A$120,Countries!B$2:B$120,"tbd",0)} -> associated countries | S42: Denmark | T42: 2 | U42: Europe
A43: 69 | B43: Male | C43: INGV | D43: Italy | E43: No | F43: No | G43: Seismology | H43: Historical Seismology, Open Science, Metadata | I43: Yes | J43: Oct 13, 2023, 5:49 PM | K43: Completed | L43: EPOSMetadata | O43: Trinidad & Tobago | P43: =COUNTIF(D$2:D$3120,O43) -> 1 | Q43: {=XLOOKUP(O43,Countries!A$2:A$120,Countries!B$2:B$120,"tbd",0)} -> Middle/South America | S43: Finland | T43: 28 | U43: Europe
A44: 26 | B44: Male | C44: NGI | D44: Norway | E44: No | F44: No | G44: Geohazard; Solid Earth | I44: Yes | J44: Sep 28, 2023, 5:35 PM | K44: Completed | L44: EPOSMetadata | O44: Uganda | P44: =COUNTIF(D$2:D$3120,O44) -> 3 | Q44: {=XLOOKUP(O44,Countries!A$2:A$120,Countries!B$2:B$120,"tbd",0)} -> Africa | S44: France | T44: 131 | U44: Europe
A45: 85 | B45: Male | C45: INCD | D45: Portugal | E45: No | F45: No | G45: Computer Science; Marine Sciences | I45: No | J45: Oct 18, 2023, 4:54 PM | K45: Completed | L45: EPOSMetadata | O45: Colombia | P45: =COUNTIF(D$2:D$3120,O45) -> 13 | Q45: {=XLOOKUP(O45,Countries!A$2:A$120,Countries!B$2:B$120,"tbd",0)} -> Middle/South America | S45: Germany | T45: 187 | U45: Europe
A46: 20 | B46: Male | C46: Universidad de Málaga (UMA) | D46: Spain | E46: No | F46: No | G46: Tsunami | H46: Numerical Modeling | I46: Yes | J46: Sep 28, 2023, 3:37 PM | K46: Completed | L46: EPOSMetadata | O46: Hungary | P46: =COUNTIF(D$2:D$3120,O46) -> 13 | Q46: {=XLOOKUP(O46,Countries!A$2:A$120,Countries!B$2:B$120,"tbd",0)} -> widening countries | S46: Ireland | T46: 6 | U46: Europe
A47: 18 | B47: Female | C47: NGI | D47: Norway | E47: No | F47: No | G47: Computer Science; Geohazard; Solid Earth; Tsunami | I47: No | J47: Sep 28, 2023, 3:19 PM | K47: Completed | L47: EPOSMetadata | O47: North Macedonia | P47: =COUNTIF(D$2:D$3120,O47) -> 17 | Q47: {=XLOOKUP(O47,Countries!A$2:A$120,Countries!B$2:B$120,"tbd",0)} -> associated countries | S47: Italy | T47: 277 | U47: Europe
A48: 42 | B48: Male | C48: Institute of Geophysics Polish Academy of Sciences | D48: Poland | E48: Yes | F48: No | G48: Engineering; Geohazard; Seismology | I48: Yes | J48: Oct 2, 2023, 5:02 PM | K48: Completed | L48: EPOSMetadata | O48: Saudi Arabia | P48: =COUNTIF(D$2:D$3120,O48) -> 13 | Q48: {=XLOOKUP(O48,Countries!A$2:A$120,Countries!B$2:B$120,"tbd",0)} -> Middle East | S48: Luxembourg | T48: 1 | U48: Europe
A49: 25 | B49: Male | C49: University of Firenze | D49: Italy | E49: No | F49: No | G49: Geohazard | I49: No | J49: Sep 28, 2023, 4:55 PM | K49: Completed | L49: EPOSMetadata | O49: Mozambique | P49: =COUNTIF(D$2:D$3120,O49) -> 5 | Q49: {=XLOOKUP(O49,Countries!A$2:A$120,Countries!B$2:B$120,"tbd",0)} -> Africa | S49: Netherlands | T49: 10 | U49: Europe
A50: 44 | B50: Male | C50: PLOCAN | D50: Spain | E50: No | F50: No | G50: Engineering; Marine Sciences | I50: Yes | J50: Oct 2, 2023, 5:34 PM | K50: Completed | L50: EPOSMetadata | O50: Cyprus | P50: =COUNTIF(D$2:D$3120,O50) -> 1 | Q50: {=XLOOKUP(O50,Countries!A$2:A$120,Countries!B$2:B$120,"tbd",0)} -> widening countries | S50: Spain | T50: 205 | U50: Europe
A51: 22 | B51: Male | C51: University of Bergen | D51: Norway | E51: No | F51: No | G51: Geohazard; Seismology; Solid Earth | I51: Yes | J51: Sep 28, 2023, 3:54 PM | K51: Completed | L51: EPOSMetadata | O51: Chile | P51: =COUNTIF(D$2:D$3120,O51) -> 32 | Q51: {=XLOOKUP(O51,Countries!A$2:A$120,Countries!B$2:B$120,"tbd",0)} -> Middle/South America | S51: spain | T51: 205 | U51: Europe
A52: 47 | B52: Female | C52: Royal observatory of Belgium | D52: Belgium | E52: No | F52: No | G52: Computer Science; Engineering | I52: Yes | J52: Oct 4, 2023, 9:50 AM | K52: Completed | L52: EPOSMetadata | O52: Ecuador | P52: =COUNTIF(D$2:D$3120,O52) -> 6 | Q52: {=XLOOKUP(O52,Countries!A$2:A$120,Countries!B$2:B$120,"tbd",0)} -> Middle/South America | S52: Sweden | T52: 11 | U52: Europe
A53: 74 | B53: Male | C53: NIEP | D53: Romania | E53: Yes | F53: No | G53: Seismology | I53: No | J53: Oct 16, 2023, 11:28 AM | K53: Completed | L53: EPOSMetadata | O53: Austria | P53: =COUNTIF(D$2:D$3120,O53) -> 12 | Q53: {=XLOOKUP(O53,Countries!A$2:A$120,Countries!B$2:B$120,"tbd",0)} -> Europe | S53: Switzerland | T53: 38 | U53: Europe | V53: =SUM(T39:T53) -> 1159
A54: 40 | B54: Female | C54: Istituto Nazionale di Geofisica e Vulcanologia | D54: Italy | E54: No | F54: No | G54: Computer Science; Solid Earth; Volcanology | I54: Yes | J54: Oct 2, 2023, 1:28 PM | K54: Completed | L54: EPOSMetadata | O54: Ukraine | P54: =COUNTIF(D$2:D$3120,O54) -> 4 | Q54: {=XLOOKUP(O54,Countries!A$2:A$120,Countries!B$2:B$120,"tbd",0)} -> associated countries | S54: Bangladesh | T54: 3 | U54: Middle East
A55: 29 | B55: Female | C55: Barcelona Supercomputing Center | D55: Spain | E55: No | F55: No | G55: Geohazard; Seismology; Solid Earth | H55: computational seismology | I55: No | J55: Sep 29, 2023, 9:14 AM | K55: Completed | L55: EPOSMetadata | O55: South Korea | P55: =COUNTIF(D$2:D$3120,O55) -> 4 | Q55: {=XLOOKUP(O55,Countries!A$2:A$120,Countries!B$2:B$120,"tbd",0)} -> Asia | S55: Egypt | T55: 13 | U55: Middle East
A56: 43 | B56: Female | C56: PLOCAN | D56: Spain | E56: Yes | F56: No | G56: Environmental Protection; Marine Sciences | I56: No | J56: Oct 2, 2023, 5:02 PM | K56: Completed | L56: EPOSMetadata | O56: Czechia | P56: =COUNTIF(D$2:D$3120,O56) -> 16 | Q56: {=XLOOKUP(O56,Countries!A$2:A$120,Countries!B$2:B$120,"tbd",0)} -> widening countries | S56: India | T56: 49 | U56: Middle East
A57: 75 | B57: Female | C57: INGV OV | D57: Italy | E57: No | F57: No | G57: Volcanology | I57: Yes | J57: Oct 16, 2023, 1:20 PM | K57: Completed | L57: EPOSMetadata | O57: Ghana | P57: =COUNTIF(D$2:D$3120,O57) -> 4 | Q57: {=XLOOKUP(O57,Countries!A$2:A$120,Countries!B$2:B$120,"tbd",0)} -> Africa | S57: Iran | T57: 57 | U57: Middle East
A58: 54 | B58: Female | C58: Naples Federico II | D58: Italy | E58: Yes | F58: No | G58: Seismology | I58: No | J58: Oct 6, 2023, 8:37 PM | K58: Completed | L58: EPOSMetadata | O58: United Arab Emirates | P58: =COUNTIF(D$2:D$3120,O58) -> 2 | Q58: {=XLOOKUP(O58,Countries!A$2:A$120,Countries!B$2:B$120,"tbd",0)} -> Asia | S58: Nepal | T58: 4 | U58: Middle East
A59: 89 | B59: Female | C59: Naples Federico II | D59: Italy | E59: Yes | F59: No | G59: Seismology | I59: No | J59: Oct 19, 2023, 10:06 AM | K59: Completed | L59: EPOSMetadata | O59: Costa Rica | P59: =COUNTIF(D$2:D$3120,O59) -> 4 | Q59: {=XLOOKUP(O59,Countries!A$2:A$120,Countries!B$2:B$120,"tbd",0)} -> Middle/South America | S59: Pakistan | T59: 13 | U59: Middle East
A60: 41 | B60: Female | C60: PLOCAN -Plataforma Oceánica de Canarias | D60: Spain | E60: No | F60: No | G60: Marine Sciences | H60: bioacoustics, biodiversity | I60: No | J60: Oct 2, 2023, 4:00 PM | K60: Completed | L60: EPOSMetadata | O60: Morocco | P60: =COUNTIF(D$2:D$3120,O60) -> 25 | Q60: {=XLOOKUP(O60,Countries!A$2:A$120,Countries!B$2:B$120,"tbd",0)} -> Africa | S60: Palestine | T60: 1 | U60: Middle East
A61: 62 | B61: Male | C61: GFZ | D61: Germany | E61: Yes | F61: No | G61: Computer Science; Geohazard; Seismology | H61: geo-information | I61: No | J61: Oct 12, 2023, 11:12 AM | K61: Completed | L61: EPOSMetadata | O61: Slovenia | P61: =COUNTIF(D$2:D$3120,O61) -> 15 | Q61: {=XLOOKUP(O61,Countries!A$2:A$120,Countries!B$2:B$120,"tbd",0)} -> widening countries | S61: Saudi Arabia | T61: 13 | U61: Middle East | V61: =SUM(T54:T61) -> 153
A62: 35 | B62: Male | C62: CSIC | D62: Spain | E62: No | F62: No | G62: Computer Science | I62: No | J62: Sep 29, 2023, 11:17 AM | K62: Completed | L62: EPOSMetadata | O62: Montenegro | P62: =COUNTIF(D$2:D$3120,O62) -> 6 | Q62: {=XLOOKUP(O62,Countries!A$2:A$120,Countries!B$2:B$120,"tbd",0)} -> associated countries | S62: Bolivia | T62: 3 | U62: Middle/South America
A63: 57 | B63: Female | C63: CNRS | D63: France | E63: No | F63: No | G63: Solid Earth | I63: No | J63: Oct 9, 2023, 3:57 PM | K63: Completed | L63: EPOSMetadata | O63: Cameroon | P63: =COUNTIF(D$2:D$3120,O63) -> 3 | Q63: {=XLOOKUP(O63,Countries!A$2:A$120,Countries!B$2:B$120,"tbd",0)} -> Africa | S63: Brazil | T63: 4 | U63: Middle/South America
A64: 84 | B64: Male | C64: CSIC | D64: Spain | E64: Yes | F64: No | G64: Other | H64: Physics | I64: No | J64: Oct 18, 2023, 3:07 PM | K64: Completed | L64: EPOSMetadata | O64: Andorra | P64: =COUNTIF(D$2:D$3120,O64) -> 2 | Q64: {=XLOOKUP(O64,Countries!A$2:A$120,Countries!B$2:B$120,"tbd",0)} -> Europe | S64: Chile | T64: 32 | U64: Middle/South America
A65: 59 | B65: Female | C65: NATIONAL OBSERVATORY OF ATHENS | D65: Greece | E65: Yes | F65: No | G65: Seismology; Tsunami | H65: Earthquake analyst with a degree in Geology and geoenvironment | I65: No | J65: Oct 11, 2023, 6:46 AM | K65: Completed | L65: EPOSMetadata | O65: Bolivia | P65: =COUNTIF(D$2:D$3120,O65) -> 3 | Q65: {=XLOOKUP(O65,Countries!A$2:A$120,Countries!B$2:B$120,"tbd",0)} -> Middle/South America | S65: Colombia | T65: 13 | U65: Middle/South America
A66: 68 | B66: Female | C66: NIGGG-BAS | D66: Bulgaria | E66: No | F66: No | G66: Engineering; Geohazard; Solid Earth | H66: Geodesy | I66: No | J66: Oct 13, 2023, 4:55 PM | K66: Completed | L66: EPOSMetadata | O66: Ethiopia | P66: =COUNTIF(D$2:D$3120,O66) -> 3 | Q66: {=XLOOKUP(O66,Countries!A$2:A$120,Countries!B$2:B$120,"tbd",0)} -> Africa | S66: Costa Rica | T66: 4 | U66: Middle/South America
A67: 83 | B67: Female | C67: EMSO ERIC | D67: Italy | E67: No | F67: No | G67: Other | I67: No | J67: Oct 18, 2023, 12:51 PM | K67: Completed | L67: EPOSMetadata | O67: Nigeria | P67: =COUNTIF(D$2:D$3120,O67) -> 6 | Q67: {=XLOOKUP(O67,Countries!A$2:A$120,Countries!B$2:B$120,"tbd",0)} -> Africa | S67: Ecuador | T67: 6 | U67: Middle/South America
A68: 63 | B68: Male | C68: NOA | D68: Greece | E68: Yes | F68: No | G68: Computer Science; Engineering | I68: Yes | J68: Oct 12, 2023, 7:16 PM | K68: Completed | L68: EPOSMetadata | O68: unknown | P68: =COUNTIF(D$2:D$3120,O68) -> 31 | Q68: {=XLOOKUP(O68,Countries!A$2:A$120,Countries!B$2:B$120,"tbd",0)} -> unknown | S68: Honduras | T68: 1 | U68: Middle/South America
A69: 81 | B69: Female | C69: NIEP | D69: Romania | E69: No | F69: No | G69: Solid Earth | I69: No | J69: Oct 17, 2023, 11:11 AM | K69: Completed | L69: EPOSMetadata | O69: Vietnam | P69: =COUNTIF(D$2:D$3120,O69) -> 3 | Q69: {=XLOOKUP(O69,Countries!A$2:A$120,Countries!B$2:B$120,"tbd",0)} -> Asia | S69: Mexico | T69: 11 | U69: Middle/South America
A70: 53 | B70: Male | C70: CINECA | D70: Italy | E70: No | F70: No | G70: Computer Science | I70: No | J70: Oct 5, 2023, 11:24 AM | K70: Completed | L70: EPOSMetadata | O70: Hongkong | P70: =COUNTIF(D$2:D$3120,O70) -> 3 | Q70: {=XLOOKUP(O70,Countries!A$2:A$120,Countries!B$2:B$120,"tbd",0)} -> Asia | S70: Nicaragua | T70: 3 | U70: Middle/South America
A71: 65 | B71: Male | C71: GEOFON - GFZ | D71: Germany | E71: No | F71: No | G71: Computer Science; Seismology | I71: Yes | J71: Oct 13, 2023, 9:05 AM | K71: Completed | L71: EPOSMetadata | O71: Algeria | P71: =COUNTIF(D$2:D$3120,O71) -> 4 | Q71: {=XLOOKUP(O71,Countries!A$2:A$120,Countries!B$2:B$120,"tbd",0)} -> Africa | S71: Paraguay | T71: 1 | U71: Middle/South America
A72: 50 | B72: Female | C72: CINECA | D72: Italy | E72: No | F72: No | G72: Other | I72: No | J72: Oct 5, 2023, 10:01 AM | K72: Completed | L72: EPOSMetadata | O72: Honduras | P72: =COUNTIF(D$2:D$3120,O72) -> 1 | Q72: {=XLOOKUP(O72,Countries!A$2:A$120,Countries!B$2:B$120,"tbd",0)} -> Middle/South America | S72: Peru | T72: 5 | U72: Middle/South America
A73: 8 | B73: Male | C73: University of Helsinki | D73: Finland | E73: Yes | F73: No | G73: Seismology | I73: No | J73: Sep 28, 2023, 1:54 PM | K73: Completed | L73: EPOSMetadata | O73: Ireland | P73: =COUNTIF(D$2:D$3120,O73) -> 6 | Q73: {=XLOOKUP(O73,Countries!A$2:A$120,Countries!B$2:B$120,"tbd",0)} -> Europe | S73: Puerto Rico | T73: 5 | U73: Middle/South America
A74: 71 | B74: Male | C74: University of Tehran | D74: Iran | E74: No | F74: Yes | G74: Computer Science; Environmental Protection; Engineering | I74: No | J74: Oct 13, 2023, 10:49 PM | K74: Completed | L74: EPOSMetadata | O74: Sweden | P74: =COUNTIF(D$2:D$3120,O74) -> 11 | Q74: {=XLOOKUP(O74,Countries!A$2:A$120,Countries!B$2:B$120,"tbd",0)} -> Europe | S74: Trinidad & Tobago | T74: 1 | U74: Middle/South America
A75: 78 | B75: Female | C75: Istituto Nazionale di Geofisica e Vulcanologia, Osservatorio Vesuviano (INGV,OV) | D75: Italy | E75: Yes | F75: No | G75: Volcanology | I75: Yes | J75: Oct 16, 2023, 3:22 PM | K75: Completed | L75: EPOSMetadata | O75: Maldives | P75: =COUNTIF(D$2:D$3120,O75) -> 1 | Q75: {=XLOOKUP(O75,Countries!A$2:A$120,Countries!B$2:B$120,"tbd",0)} -> Asia | S75: Venezuela | T75: 1 | U75: Middle/South America | V75: =SUM(T62:T75) -> 90
A76: 33 | B76: Male | C76: CNRS | D76: France | E76: No | F76: No | G76: Computer Science | I76: Yes | J76: Sep 29, 2023, 10:51 AM | K76: Completed | L76: EPOSMetadata | O76: French Polynesia | P76: =COUNTIF(D$2:D$3120,O76) -> 1 | Q76: {=XLOOKUP(O76,Countries!A$2:A$120,Countries!B$2:B$120,"tbd",0)} -> outermost region | S76: Australia | T76: 9 | U76: Oceania | V76: =T76 -> 9
A77: 14 | B77: Male | C77: ETHZ | D77: Switzerland | E77: No | F77: No | G77: Computer Science; Engineering; Seismology | I77: No | J77: Sep 28, 2023, 3:05 PM | K77: Completed | L77: EPOSMetadata | O77: Nicaragua | P77: =COUNTIF(D$2:D$3120,O77) -> 3 | Q77: {=XLOOKUP(O77,Countries!A$2:A$120,Countries!B$2:B$120,"tbd",0)} -> Middle/South America | S77: French Polynesia | T77: 1 | U77: outermost region
A78: 91 | B78: Male | C78: Politecnico di Torino | D78: Italy | E78: Yes | F78: No | G78: Energy Transformation/Storage; Engineering; Geohazard | H78: Petroleum engineering | I78: No | J78: Oct 19, 2023, 9:45 PM | K78: Completed | L78: EPOSMetadata | O78: Brazil | P78: =COUNTIF(D$2:D$3120,O78) -> 4 | Q78: {=XLOOKUP(O78,Countries!A$2:A$120,Countries!B$2:B$120,"tbd",0)} -> Middle/South America | S78: Canada | T78: 14 | U78: U.S. + Canada
A79: 39 | B79: Male | C79: Barcelona Supercomputing Center | D79: Spain | E79: No | F79: No | G79: Computer Science | I79: No | J79: Oct 2, 2023, 10:59 AM | K79: Completed | L79: EPOSMetadata | O79: Bosnia and Herzegovina | P79: =COUNTIF(D$2:D$3120,O79) -> 3 | Q79: {=XLOOKUP(O79,Countries!A$2:A$120,Countries!B$2:B$120,"tbd",0)} -> associated countries | S79: United States | T79: 186 | U79: U.S. + Canada | V79: =SUM(T78:T79) -> 200
A80: 60 | B80: Male | C80: ISTERRE | D80: France | E80: Yes | F80: No | G80: Geohazard; Seismology | I80: Yes | J80: Oct 11, 2023, 4:47 PM | K80: Completed | L80: EPOSMetadata | O80: Denmark | P80: =COUNTIF(D$2:D$3120,O80) -> 2 | Q80: {=XLOOKUP(O80,Countries!A$2:A$120,Countries!B$2:B$120,"tbd",0)} -> Europe | S80: unknown | T80: 31 | U80: unknown
A81: 11 | B81: Male | C81: Dr. Engineering Geologist NTUA | D81: Greece | E81: Yes | F81: Yes | G81: Environmental Protection; Engineering; Geohazard | H81: Landslides, Risk Assessment | I81: No | J81: Sep 28, 2023, 2:20 PM | K81: Completed | L81: EPOSMetadata | O81: Luxembourg | P81: =COUNTIF(D$2:D$3120,O81) -> 1 | Q81: {=XLOOKUP(O81,Countries!A$2:A$120,Countries!B$2:B$120,"tbd",0)} -> Europe | S81: Bulgaria | T81: 12 | U81: widening countries
A82: 24 | B82: Female | C82: Icelandic Meteorological Office | D82: Iceland | E82: Yes | F82: Yes | G82: Geohazard; Seismology | I82: No | J82: Sep 28, 2023, 4:41 PM | K82: Completed | L82: EPOSMetadata | O82: Palestine | P82: =COUNTIF(D$2:D$3120,O82) -> 1 | Q82: {=XLOOKUP(O82,Countries!A$2:A$120,Countries!B$2:B$120,"tbd",0)} -> Middle East | S82: Croatia | T82: 23 | U82: widening countries
A83: 61 | B83: Female | C83: TU Delft | D83: Netherlands | E83: No | F83: No | G83: Energy Transformation/Storage | H83: Geophysics | I83: Yes | J83: Oct 12, 2023, 10:09 AM | K83: Completed | L83: EPOSMetadata | O83: Serbia | P83: =COUNTIF(D$2:D$3120,O83) -> 4 | Q83: {=XLOOKUP(O83,Countries!A$2:A$120,Countries!B$2:B$120,"tbd",0)} -> associated countries | S83: Cyprus | T83: 1 | U83: widening countries
A84: 77 | B84: Male | C84: GFZ Potsdam | D84: Germany | E84: No | F84: No | G84: Seismology; Solid Earth; Volcanology | I84: No | J84: Oct 16, 2023, 1:25 PM | K84: Completed | L84: EPOSMetadata | O84: Venezuela | P84: =COUNTIF(D$2:D$3120,O84) -> 1 | Q84: {=XLOOKUP(O84,Countries!A$2:A$120,Countries!B$2:B$120,"tbd",0)} -> Middle/South America | S84: Czechia | T84: 16 | U84: widening countries
A85: 51 | B85: Male | C85: VLIZ | D85: Belgium | E85: No | F85: No | G85: Geohazard; Marine Sciences; Tsunami | I85: Yes | J85: Oct 5, 2023, 10:18 AM | K85: Completed | L85: EPOSMetadata | O85: Paraguay | P85: =COUNTIF(D$2:D$3120,O85) -> 1 | Q85: {=XLOOKUP(O85,Countries!A$2:A$120,Countries!B$2:B$120,"tbd",0)} -> Middle/South America | S85: Greece | T85: 86 | U85: widening countries
A86: 3 | B86: Female | C86: INGV | D86: Italy | E86: No | F86: No | G86: Tsunami | I86: Yes | J86: Sep 28, 2023, 1:08 PM | K86: Completed | L86: EPOSMetadata | O86: Puerto Rico | P86: =COUNTIF(D$2:D$3120,O86) -> 5 | Q86: {=XLOOKUP(O86,Countries!A$2:A$120,Countries!B$2:B$120,"tbd",0)} -> Middle/South America | S86: Hungary | T86: 13 | U86: widening countries
A87: 66 | B87: Male | C87: National Institute of Oceanography and Applied Geophysics - OGS | D87: Italy | E87: No | F87: No | G87: Seismology; Solid Earth; Volcanology | I87: No | J87: Oct 13, 2023, 9:28 AM | K87: Completed | L87: EPOSMetadata | O87: Zimbabwe | P87: =COUNTIF(D$2:D$3120,O87) -> 1 | Q87: {=XLOOKUP(O87,Countries!A$2:A$120,Countries!B$2:B$120,"tbd",0)} -> Africa | S87: Malta | T87: 3 | U87: widening countries
A88: 82 | B88: Female | C88: GFZ | D88: Germany | E88: Yes | F88: No | G88: Other | I88: No | J88: Oct 18, 2023, 11:31 AM | K88: Completed | L88: EPOSMetadata | O88: Congo - Kinshasa | P88: =COUNTIF(D$2:D$3120,O88) -> 1 | Q88: {=XLOOKUP(O88,Countries!A$2:A$120,Countries!B$2:B$120,"tbd",0)} -> Africa | S88: Poland | T88: 69 | U88: widening countries
A89: 64 | B89: Female | C89: Institute of Earth Science,Academia Sinica | D89: Taiwan | E89: Yes | F89: No | G89: Engineering; Geohazard; Seismology; Solid Earth | I89: Yes | J89: Oct 13, 2023, 12:23 AM | K89: Completed | L89: EPOSMetadata | O89: Kyrgyzstan | P89: =COUNTIF(D$2:D$3120,O89) -> 1 | Q89: {=XLOOKUP(O89,Countries!A$2:A$120,Countries!B$2:B$120,"tbd",0)} -> Asia | S89: Portugal | T89: 109 | U89: widening countries
A90: 90 | B90: Female | C90: BSC | D90: Spain | E90: No | F90: No | G90: Geohazard | I90: No | J90: Oct 19, 2023, 10:11 AM | K90: Completed | L90: EPOSMetadata | O90: Malawi | P90: =COUNTIF(D$2:D$3120,O90) -> 1 | Q90: {=XLOOKUP(O90,Countries!A$2:A$120,Countries!B$2:B$120,"tbd",0)} -> Africa | S90: Romania | T90: 43 | U90: widening countries
A91: 105 | B91: Male | C91: International Institute of Earthquake Engineering and Seismology | D91: Iran | E91: Yes | F91: Yes | G91: Engineering; Seismology; Other | H91: Vulnerability and Risk Assessment of Buildings | I91: No | J91: Oct 12, 2023, 4:05 PM | K91: Completed | L91: ETRIS | O91: spain | P91: =COUNTIF(D$2:D$3120,O91) -> 205 | Q91: {=XLOOKUP(O91,Countries!A$2:A$120,Countries!B$2:B$120,"tbd",0)} -> Europe | S91: Slovenia | T91: 15 | U91: widening countries | V91: =SUM(T81:T91) -> 390
A92: 106 | B92: Female | C92: Postdoctoral fellow-Department of Civil Engineering | D92: Canada | E92: Yes | F92: No | G92: Engineering | I92: No | J92: Oct 12, 2023, 4:57 PM | K92: Completed | L92: ETRIS
A93: 14 | B93: Female | C93: Barcelona Supercomputing Center | D93: Spain | E93: Yes | F93: No | G93: Seismology | I93: No | J93: Sep 28, 2023, 6:52 PM | K93: Completed | L93: ETRIS
A94: 149 | B94: Male | C94: Trupt Technology Inc. | D94: Turkey | E94: Yes | F94: Yes | G94: Engineering; Geohazard | I94: No | J94: Oct 17, 2023, 9:20 AM | K94: Completed | L94: ETRIS
A95: 191 | B95: Male | C95: London Resilience Group | D95: United Kingdom | E95: No | F95: No | G95: Other | H95: Resilience Planning | I95: No | J95: Oct 26, 2023, 11:03 AM | K95: Completed | L95: ETRIS
A96: 62 | B96: Male | C96: University of Nebraska-Lincoln | D96: United States | E96: Yes | F96: No | G96: Engineering | I96: No | J96: Oct 11, 2023, 1:24 AM | K96: Completed | L96: ETRIS
A97: 212 | B97: Male | C97: Nagoya University | D97: Japan | E97: Yes | F97: No | G97: Geohazard | I97: No | J97: Nov 2, 2023, 3:38 PM | K97: Completed | L97: ETRIS
A98: 6 | B98: Male | C98: L-Universita ta' Malta | D98: Malta | E98: No | F98: No | G98: Seismology; Solid Earth | I98: No | J98: Sep 28, 2023, 2:00 PM | K98: Completed | L98: ETRIS
A99: 11 | B99: Male | C99: The University of Edinburgh | D99: United Kingdom | E99: Yes | F99: No | G99: Seismology | I99: No | J99: Sep 28, 2023, 2:42 PM | K99: Completed | L99: ETRIS
A100: 96 | B100: Male | C100: Khulna University | D100: Bangladesh | E100: Yes | F100: No | G100: Other | H100: Social Science | I100: No | J100: Oct 12, 2023, 3:26 AM | K100: Completed | L100: ETRIS
...

Sheet ISCPoster_Data
A1: Date | B1: Training_Name | C1: # Registrations | D1: m+f+d | E1: # Participants | F1: Attend_Rate | G1: Male | H1: Female | I1: Diverse | J1: Female % | K1: ECS | L1: ECS % | M1: SME | N1: SME % | O1: Familar? | P1: Familiar? % | Q1: FeedbackF | R1: FeedbackF % | S1: wideningC | T1: wideningC % | U1: #Scientific fields | V1: #Countries | W1: non-EU | X1: non-EU % | Y1: America
A2: Summary | B2: 4 EPOS Trg | C2: 663 | D2: 625 | E2: 402 | F2: 0.60633484 | G2: 287 | H2: 336 | I2: 2 | J2: 0.50678733 | K2: 77 | L2: 0.11613876 | M2: 20 | N2: 0.11123314 | O2: 71 | P2: 0.10708899
B3: .
A4: 45047 | B4: HPS-SCOPED1 | C4: 205 | D4: 205 | E4: 134 | F4: 0.65365854 | G4: 128 | H4: 70 | I4: 7 | J4: 0.34146341 | K4: 84 | L4: 0.4097561 | M4: 15 | N4: 0.073170732 | O4: 186 | P4: 0.90731707 | S4: 10 | T4: 0.048780488 | U4: 4 | V4: 33 | W4: 113 | X4: 0.55121951 | Y4: 90
A5: 45231 | B5: ETRiS | C5: 234 | D5: 234 | E5: 144 | F5: 0.61538462 | G5: 145 | H5: 89 | I5: 0 | J5: 0.38034188 | K5: 171 | L5: 0.73076923 | M5: 67 | N5: 0.28632479 | O5: 3 | P5: 0.012820513 | Q5: 28 | R5: 0.19444444 | S5: 20 | T5: 0.085470085 | U5: 27 | V5: 46 | W5: 109 | X5: 0.46581197
A6: 45383 | B6: HySEA_T | C6: 66 | D6: 66 | E6: 57 | F6: 0.86363636 | G6: 37 | H6: 27 | I6: 2 | J6: 0.40909091 | K6: 46 | L6: 0.6969697 | M6: 7 | N6: 0.10606061 | O6: 16 | P6: 0.24242424 | Q6: 20 | R6: 0.3030303 | S6: 3 | T6: 0.045454545 | U6: 15 | V6: 19 | W6: 31 | X6: 0.46969697
A7: 45754 | B7: HySEA_L | C7: 105 | D7: 105 | E7: 79 | F7: 0.75238095 | G7: 64 | H7: 40 | I7: 1 | J7: 0.38095238 | K7: 74 | L7: 0.7047619 | M7: 14 | N7: 0.13333333 | P7: 0 | R7: 0 | S7: 21 | T7: 0.2 | U7: 12 | V7: 28 | W7: 48 | X7: 0.45714286
A8: 45536 | B8: PyBET | C8: 18 | D8: 18 | E8: 18 | F8: 1 | G8: 13 | H8: 5 | I8: 0 | J8: 0.27777778 | K8: 13 | L8: 0.72222222 | M8: 1 | N8: 0.055555556 | O8: 2 | P8: 0.11111111 | Q8: 5 | R8: 0.27777778 | S8: 2 | T8: 0.11111111 | U8: 8 | V8: 11 | W8: 11 | X8: 0.61111111 | Z8: preliminary results from feedback, survey still open
A9: 45536 | B9: SDL_WS | C9: 130 | D9: 126 | E9: 126 | F9: 0.96923077 | G9: 73 | H9: 53 | I9: 0 | J9: 0.40769231 | K9: 61 | L9: 0.46923077 | M9: 8 | N9: 0.061538462 | O9: 23 | P9: 0.17692308 | Q9: 21 | R9: 0.16666667 | S9: 4 | T9: 0.030769231 | U9: 12 | V9: 26 | W9: 42 | X9: 0.32307692 | Z9: preliminary results from feedback, survey still open
A10: January 2025 | B10: Quakeworx | C10: 149 | D10: 148 | E10: 81 | F10: 0.54362416 | G10: 101 | H10: 44 | I10: 3 | J10: 0.29530201 | K10: 0 | L10: 0 | M10: 1 | N10: 0.0067114094 | O10: 14 | P10: 0.093959732 | R10: 0 | T10: 0 | X10: 0
A11: Summary | B11: 7 HPC Events | C11: 907 | D11: 902 | E11: 639 | F11: 0.7045204 | G11: 561 | H11: 328 | I11: 13 | J11: 0.36163175 | K11: 449 | L11: 0.49503859 | M11: 113 | N11: 0.12458655
B12: .
A13: Summary | B13: 7 FAIR Trg | C13: 379 | D13: 379 | E13: 271 | F13: 0.71503958 | G13: 162 | H13: 214 | I13: 3 | J13: 0.5646438 | K13: 142 | L13: 0.37467018 | M13: 27 | N13: 0.071240106 | O13: 274 | P13: 0.72295515
B14: .
A15: Summary | B15: 5 Portal Trg | C15: 274 | D15: 274 | E15: 187 | F15: 0.68248175 | G15: 174 | H15: 98 | I15: 2 | J15: 0.35766423 | K15: 152 | L15: 0.55474453 | M15: 53 | N15: 0.19343066 | O15: 135 | P15: 0.49270073
B16: .
A17: Summary | B17: 2 ShakeMapWS | C17: 114 | D17: 112 | E17: 108 | F17: 0.94736842 | G17: 59 | H17: 53 | I17: 0 | J17: 0.46491228 | K17: 15 | L17: 0.2027027 | M17: 2 | N17: 0.01754386 | O17: 0 | P17: 0
B18: .
A19: Summary | B19: 7 ORFEUS Trg | C19: 585 | D19: 585 | E19: 431 | F19: 0.73675214 | G19: 312 | H19: 256 | I19: 17 | J19: 0.43760684 | K19: 198 | L19: 2.6631312 | M19: 32 | N19: 0.054700855 | O19: 373 | P19: 0.63760684
B20: .
A21: Summary | B21: 3 Schools | C21: 171 | D21: 170 | E21: 170 | F21: 1 | G21: 121 | H21: 47 | I21: 2 | J21: 0.37288997 | K21: 98 | L21: 0.57309942 | M21: 6 | N21: 0.27272727
B23: Sum | C23: =SUM(C2:C21)-C11 -> 3093 | D23: =SUM(D2:D21)-D11 -> 3047 | E23: =SUM(E2:E21)-E11 -> 2208 | F23: =E23/C23 -> 0.71387003 | G23: =SUM(G2:G21)-G11 -> 1676 | H23: =SUM(H2:H21)-H11 -> 1332 | I23: =SUM(I2:I21)-I11 -> 39 | J23: =H23/C23 -> 0.43064985 | K23: =SUM(K2:K21)-K11 -> 1131 | L23: =K23/C23 -> 0.3656644 | M23: =SUM(M2:M21)-M11 -> 253 | N23: =M23/C23 -> 0.081797607 | O23: =SUM(O2:O21)-O11 -> 1097 | P23: =O23/C23 -> 0.35467184
B24: Sum (wrong) | C24: 2524.5 | D24: 2480 | E24: 1759 | F24: 0.69677164 | G24: 1335.5 | H24: 1123.5 | I24: 21 | J24: 0.44503862 | K24: 954 | L24: 0.37789661 | M24: 228 | N24: 0.090314914 | O24: 951 | P24: 0.37670826 | Q24: 471 | R24: 0.26776578 | S24: 515 | T24: 0.20400079 | W24: 519 | X24: 0.20558526

Sheet ORFEUS_allParticipants
A1: id | B1: Gender | C1: Affiliation | D1: Country of Affiliation | E1: ECS | F1: Do you primarily work in the private sector? | G1: What is your background? | H1: Please choose the role / career stage that best applies to you: | I1: Have you been familiar with the FAIR principles before? | J1: Registration date | K1: How did you hear about this event: | L1: Tags
A2: 236 | B2: Male | C2: Institute of Geosciences | D2: Albania | E2: Yes | F2: No | G2: Seismology | H2: Scientists | L2: ORFEUS_unique
A3: 45 | B3: Female | C3: Institute of Geosciences | D3: Albania | E3: Yes | F3: No | G3: Computer sciences | H3: Senior Scientist | L3: ORFEUS_unique
A4: 76 | B4: Female | C4: Institute of Geosciences, Tirana | D4: Albania | E4: No | F4: No | G4: Seismology | H4: PhD Candidate | L4: ORFEUS_unique
A5: 103 | B5: Male | C5: IGEO | D5: Albania | E5: Yes | F5: No | G5: Seismology, Engineering seismology / soil dynamics and earthquake engineering, Environmental protection | H5: Technician | L5: ORFEUS_unique
A6: 148 | B6: Male | C6: Institute of Geosciences | D6: Albania | E6: Yes | F6: No | G6: Seismology | H6: PhD Candidate | L6: ORFEUS_unique
A7: 232 | B7: Male | C7: Institute of Geoscience | D7: Albania | E7: Yes | F7: No | G7: Seismology, Computer sciences | H7: PhD Candidate | L7: ORFEUS_unique
A8: 275 | B8: Female | C8: Institute of Geosciences | D8: Albania | E8: No | F8: No | G8: Engineering seismology / soil dynamics and earthquake engineering, Other Earth science field | H8: Scientists | L8: ORFEUS_unique
A9: 114 | B9: Male | C9: GeoSphere Austria | D9: Austria | E9: No | F9: No | G9: Seismology | H9: Technician | L9: ORFEUS_unique
A10: 209 | B10: Female | C10: GeoSphere Austria | D10: Austria | E10: Yes | F10: No | G10: Seismology, Landslides, Atmospheric physics | H10: PhD Candidate | L10: ORFEUS_unique
A11: 267 | B11: Female | C11: GeoSphere Austria | D11: Austria | E11: Yes | F11: Yes | G11: Seismology | H11: Other | L11: ORFEUS_unique
A12: 82 | B12: Male | C12: ROB | D12: Belgium | E12: No | F12: No | G12: GNSS, Computer sciences | H12: Scientists | L12: ORFEUS_unique
A13: 101 | B13: Male | C13: Royal Observatory of Belgium | D13: Belgium | E13: No | F13: No | G13: Computer sciences | H13: Technician | L13: ORFEUS_unique
... A316: 137 | B316: Male | C316: Addis Ababa University | D316: Ethiopia | E316: Yes | F316: No | G316: Seismology | H316: Scientists | L316: ORFEUS_unique

Sheet WP5Participants
A1: ID | B1: Gender | C1: Affiliation | D1: Country of Affiliation | E1: Are you an Early Career Scientist? | F1: Do you work in industry, a Start-up or Small and Medium Enterprise? | G1: What is your scientific expertise? (Multiple Choice) | H1: Scientific expertise - Other(s): | I1: Have you used this installation (EPOS) before? | J1: Registration date | K1: Registration state | L1: Training | O1: Countries | P1: No_Countries | Q1: Category | X1: Country | Y1: # Registrations
A2: 13 | B2: Female | C2: University of Trieste | D2: Italy | E2: Yes | F2: No | G2: Tsunami | I2: Yes | J2: Apr 5, 2024, 12:39 AM | K2: Completed | L2: HySEA | O2: {=UNIQUE(D2:D600)} -> Italy | P2: =COUNTIF(D$2:D$600,O2) -> 69 | Q2: {=XLOOKUP(O2,Countries!A$2:A$98,Countries!B$2:B$98,"tbd",0)} -> Europe
A3: 55 | B3: Female | C3: LMU | D3: Germany | E3: Yes | F3: No | G3: Seismology | I3: No | J3: Apr 16, 2024, 3:08 PM | K3: Completed | L3: HySEA | O3: Germany | P3: =COUNTIF(D$2:D$600,O3) -> 62 | Q3: {=XLOOKUP(O3,Countries!A$2:A$98,Countries!B$2:B$98,"tbd",0)} -> Europe
A4: 52 | B4: Male | C4: Shoa | D4: Chile | E4: Yes | F4: No | G4: Seismology; Tsunami | I4: No | J4: Apr 12, 2024, 12:27 AM | K4: Completed | L4: HySEA | O4: Chile | P4: =COUNTIF(D$2:D$600,O4) -> 15 | Q4: {=XLOOKUP(O4,Countries!A$2:A$98,Countries!B$2:B$98,"tbd",0)} -> Middle/South America
A5: 19 | B5: Female | C5: Post-Doc | D5: Italy | E5: Yes | F5: No | G5: Seismology; Tsunami | I5: Yes | J5: Apr 5, 2024, 2:33 PM | K5: Completed | L5: HySEA | O5: France | P5: =COUNTIF(D$2:D$600,O5) -> 22 | Q5: {=XLOOKUP(O5,Countries!A$2:A$98,Countries!B$2:B$98,"tbd",0)} -> Europe
A6: 56 | B6: Male | C6: Université Côte d'Azur, Universidad de Alcalá | D6: France | E6: Yes | F6: No | G6: Energy Transformation/Storage; Engineering; Marine Sciences | H6: ocean-bottom instrumentation | I6: No | J6: Apr 20, 2024, 2:55 PM | K6: Completed | L6: HySEA | O6: Turkey | P6: =COUNTIF(D$2:D$600,O6) -> 11 | Q6: {=XLOOKUP(O6,Countries!A$2:A$98,Countries!B$2:B$98,"tbd",0)} -> associated countries
A7: 11 | B7: Female | C7: Engineer | D7: Chile | E7: Yes | F7: Yes | G7: Engineering; Marine Sciences; Tsunami | I7: Yes | J7: Apr 4, 2024, 11:40 PM | K7: Completed | L7: HySEA | O7: Greece | P7: =COUNTIF(D$2:D$600,O7) -> 14 | Q7: {=XLOOKUP(O7,Countries!A$2:A$98,Countries!B$2:B$98,"tbd",0)} -> widening countries
A8: 15 | B8: Female | C8: Bogazici University | D8: Turkey | E8: No | F8: No | G8: Seismology | I8: Yes | J8: Apr 5, 2024, 6:29 AM | K8: Completed | L8: HySEA | O8: Israel | P8: =COUNTIF(D$2:D$600,O8) -> 3 | Q8: {=XLOOKUP(O8,Countries!A$2:A$98,Countries!B$2:B$98,"tbd",0)} -> associated countries
A9: 20 | B9: Female | C9: INGV | D9: Italy | E9: Yes | F9: No | G9: Seismology; Tsunami | I9: No | J9: Apr 5, 2024, 2:34 PM | K9: Completed | L9: HySEA | O9: Spain | P9: =COUNTIF(D$2:D$600,O9) -> 42 | Q9: {=XLOOKUP(O9,Countries!A$2:A$98,Countries!B$2:B$98,"tbd",0)} -> Europe
A10: 3 | B10: Male | C10: n/a | D10: Greece | E10: Yes | F10: No | G10: Geohazard; Seismology; Solid Earth | I10: No | J10: Mar 21, 2024, 11:12 AM | K10: Completed | L10: HySEA | O10: Ecuador | P10: =COUNTIF(D$2:D$600,O10) -> 5 | Q10: {=XLOOKUP(O10,Countries!A$2:A$98,Countries!B$2:B$98,"tbd",0)} -> Middle/South America
A11: 1 | B11: Female | C11: LMU - Dept. of Geophysics | D11: Germany | E11: No | F11: No | G11: Computer Science | I11: No | J11: Mar 20, 2024, 9:21 AM | K11: Completed | L11: HySEA | O11: Indonesia | P11: =COUNTIF(D$2:D$600,O11) -> 9 | Q11: {=XLOOKUP(O11,Countries!A$2:A$98,Countries!B$2:B$98,"tbd",0)} -> Asia
A12: 45 | B12: Male | C12: None | D12: Chile | E12: Yes | F12: Yes | G12: Engineering; Seismology | I12: No | J12: Apr 8, 2024, 5:50 PM | K12: Completed | L12: HySEA | O12: Pakistan | P12: =COUNTIF(D$2:D$600,O12) -> 4 | Q12: {=XLOOKUP(O12,Countries!A$2:A$98,Countries!B$2:B$98,"tbd",0)} -> Middle East
A13: 39 | B13: Male | C13: Istituto Nazionale di Oceanografia e Geofisica Sperimentale (OGS) | D13: Italy | E13: Yes | F13: No | G13: Seismology | H13: Earthquake and Tsunami Hazard Assessment | I13: No | J13: Apr 6, 2024, 8:55 PM | K13: Completed | L13: HySEA | O13: Peru | P13: =COUNTIF(D$2:D$600,O13) -> 1 | Q13: {=XLOOKUP(O13,Countries!A$2:A$98,Countries!B$2:B$98,"tbd",0)} -> Middle/South America
A14: 7 | B14: Male | C14: Geological survey of israel | D14: Israel | E14: Yes | F14: No | G14: Engineering; Geohazard; Seismology; Tsunami | I14: No | J14: Mar 31, 2024, 12:38 PM | K14: Completed | L14: HySEA | O14: Iran | P14: =COUNTIF(D$2:D$600,O14) -> 13 | Q14: {=XLOOKUP(O14,Countries!A$2:A$98,Countries!B$2:B$98,"tbd",0)} -> Middle East
A15: 22 | B15: Female | C15: Instituto Geográfico Nacional | D15: Spain | E15: No | F15: No | G15: Seismology | I15: Yes | J15: Apr 5, 2024, 2:52 PM | K15: Completed | L15: HySEA | O15: Austria | P15: =COUNTIF(D$2:D$600,O15) -> 4 | Q15: {=XLOOKUP(O15,Countries!A$2:A$98,Countries!B$2:B$98,"tbd",0)} -> Europe
A16: 60 | B16: Male | C16: IH Cantabria | D16: Spain | E16: Yes | F16: No | G16: Marine Sciences; Tsunami | I16: Yes | J16: Apr 22, 2024, 3:23 PM | K16: Completed | L16: HySEA | O16: Romania | P16: =COUNTIF(D$2:D$600,O16) -> 7 | Q16: {=XLOOKUP(O16,Countries!A$2:A$98,Countries!B$2:B$98,"tbd",0)} -> widening countries
A17: 66 | B17: Male | C17: IHCantabria | D17: Spain | E17: Yes | F17: Yes | G17: Engineering; Marine Sciences | H17: Beach morphodynamics | I17: No | J17: Apr 24, 2024, 10:50 AM | K17: Completed | L17: HySEA | O17: United States | P17: =COUNTIF(D$2:D$600,O17) -> 106 | Q17: {=XLOOKUP(O17,Countries!A$2:A$98,Countries!B$2:B$98,"tbd",0)} -> U.S. + Canada
A18: 25 | B18: Diverse | C18: GFZ | D18: Germany | E18: Yes | F18: No | G18: Engineering; Geohazard; Seismology | I18: No | J18: Apr 5, 2024, 3:40 PM | K18: Completed | L18: HySEA | O18: Belgium | P18: =COUNTIF(D$2:D$600,O18) -> 1 | Q18: {=XLOOKUP(O18,Countries!A$2:A$98,Countries!B$2:B$98,"tbd",0)} -> Europe
A19: 32 | B19: Male | C19: Universidad Andres Bello | D19: Chile | E19: Yes | F19: No | G19: Computer Science; Geohazard; Marine Sciences; Seismology; Solid Earth; Tsunami; Volcanology | I19: No | J19: Apr 6, 2024, 12:44 AM | K19: Completed | L19: HySEA | O19: United Kingdom | P19: =COUNTIF(D$2:D$600,O19) -> 7 | Q19: {=XLOOKUP(O19,Countries!A$2:A$98,Countries!B$2:B$98,"tbd",0)} -> associated countries
A20: 30 | B20: Male | C20: ESPOL | D20: Ecuador | E20: Yes | F20: No | G20: Computer Science; Engineering; Geohazard; Marine Sciences; Tsunami; Volcanology | H20: ocean engineering | I20: No | J20: Apr 5, 2024, 9:33 PM | K20: Completed | L20: HySEA | O20: Taiwan | P20: =COUNTIF(D$2:D$600,O20) -> 5 | Q20: {=XLOOKUP(O20,Countries!A$2:A$98,Countries!B$2:B$98,"tbd",0)} -> Asia
A21: 64 | B21: Diverse | C21: UMA | D21: Spain | E21: Yes | F21: No | G21: Tsunami | I21: Yes | J21: Apr 23, 2024, 4:00 PM | K21: Completed | L21: HySEA | O21: Switzerland | P21: =COUNTIF(D$2:D$600,O21) -> 13 | Q21: {=XLOOKUP(O21,Countries!A$2:A$98,Countries!B$2:B$98,"tbd",0)} -> Europe
A22: 46 | B22: Female | C22: Cigiden | D22: Chile | E22: Yes | F22: No | G22: Tsunami | I22: Yes | J22: Apr 8, 2024, 9:25 PM | K22: Completed | L22: HySEA | O22: Iceland | P22: =COUNTIF(D$2:D$600,O22) -> 5 | Q22: {=XLOOKUP(O22,Countries!A$2:A$98,Countries!B$2:B$98,"tbd",0)} -> associated countries
A23: 54 | B23: Male | C23: Pontificia Universidad Católica de Valparaíso | D23: Chile | E23: Yes | F23: No | G23: Geohazard; Tsunami | I23: No | J23: Apr 15, 2024, 5:43 PM | K23: Completed | L23: HySEA | O23: China | P23: =COUNTIF(D$2:D$600,O23) -> 10 | Q23: {=XLOOKUP(O23,Countries!A$2:A$98,Countries!B$2:B$98,"tbd",0)} -> Asia
A24: 28 | B24: Female | C24: Escuela Superior Politécnica del Litoral | D24: Ecuador | E24: Yes | F24: No | G24: Environmental Protection; Engineering; Marine Sciences; Tsunami | I24: No | J24: Apr 5, 2024, 7:54 PM | K24: Completed | L24: HySEA | O24: South Korea | P24: =COUNTIF(D$2:D$600,O24) -> 3 | Q24: {=XLOOKUP(O24,Countries!A$2:A$98,Countries!B$2:B$98,"tbd",0)} -> Asia
A25: 57 | B25: Male | C25: Meteorology, Climatology and Geophysics Agency of Indonesia | D25: Indonesia | E25: Yes | F25: No | G25: Computer Science; Geohazard; Seismology; Tsunami | I25: No | J25: Apr 22, 2024, 3:10 AM | K25: Completed | L25: HySEA | O25: Saudi Arabia | P25: =COUNTIF(D$2:D$600,O25) -> 9 | Q25: {=XLOOKUP(O25,Countries!A$2:A$98,Countries!B$2:B$98,"tbd",0)} -> Middle East
A26: 59 | B26: Male | C26: NED University of Engineering and Technology | D26: Pakistan | E26: No | F26: No | G26: Engineering; Tsunami | H26: Mathematics and coastal engineering | I26: No | J26: Apr 22, 2024, 6:46 AM | K26: Completed | L26: HySEA | O26: Japan | P26: =COUNTIF(D$2:D$600,O26) -> 4 | Q26: {=XLOOKUP(O26,Countries!A$2:A$98,Countries!B$2:B$98,"tbd",0)} -> Asia
A27: 48 | B27: Female | C27: Shoa | D27: Chile | E27: No | F27: Yes | G27: Tsunami | I27: Yes | J27: Apr 8, 2024, 10:18 PM | K27: Completed | L27: HySEA | O27: Czechia | P27: =COUNTIF(D$2:D$600,O27) -> 3 | Q27: {=XLOOKUP(O27,Countries!A$2:A$98,Countries!B$2:B$98,"tbd",0)} -> widening countries
A28: 50 | B28: Male | C28: Grupo de Emergencias de Andalucia (GREA) - Junta de Andalucia | D28: Spain | E28: No | F28: No | G28: Tsunami | I28: No | J28: Apr 10, 2024, 1:17 PM | K28: Completed | L28: HySEA | O28: Ghana | P28: =COUNTIF(D$2:D$600,O28) -> 4 | Q28: {=XLOOKUP(O28,Countries!A$2:A$98,Countries!B$2:B$98,"tbd",0)} -> Africa
A29: 21 | B29: Male | C29: UNIVERSITY OF NAPLES FEDERICO II | D29: Italy | E29: Yes | F29: No | G29: Tsunami | I29: No | J29: Apr 5, 2024, 2:34 PM | K29: Completed | L29: HySEA | O29: United Arab Emirates | P29: =COUNTIF(D$2:D$600,O29) -> 2 | Q29: {=XLOOKUP(O29,Countries!A$2:A$98,Countries!B$2:B$98,"tbd",0)} -> Asia
A30: 62 | B30: Male | C30: Edanya Group | D30: Spain | E30: Yes | F30: No | G30: Tsunami | I30: Yes | J30: Apr 23, 2024, 11:06 AM | K30: Completed | L30: HySEA | O30: Costa Rica | P30: =COUNTIF(D$2:D$600,O30) -> 1 | Q30: {=XLOOKUP(O30,Countries!A$2:A$98,Countries!B$2:B$98,"tbd",0)} -> Middle/South America
A31: 33 | B31: Female | C31: NED University of Engineering and Technology | D31: Pakistan | E31: Yes | F31: No | G31: Tsunami | I31: No | J31: Apr 6, 2024, 9:03 AM | K31: Completed | L31: HySEA | O31: Morocco | P31: =COUNTIF(D$2:D$600,O31) -> 6 | Q31: {=XLOOKUP(O31,Countries!A$2:A$98,Countries!B$2:B$98,"tbd",0)} -> Africa
A32: 24 | B32: Female | C32: Instituto de Ciencias del Mar - CSIC | D32: Spain | E32: No | F32: No | G32: Geohazard; Marine Sciences; Solid Earth; Tsunami | H32: Active tectonics and associated geogazards | I32: No | J32: Apr 5, 2024, 3:06 PM | K32: Completed | L32: HySEA | O32: New Zealand | P32: =COUNTIF(D$2:D$600,O32) -> 5 | Q32: {=XLOOKUP(O32,Countries!A$2:A$98,Countries!B$2:B$98,"tbd",0)} -> associated countries
A33: 14 | B33: Female | C33: Universidad Continental | D33: Peru | E33: Yes | F33: No | G33: Computer Science; Tsunami | I33: No | J33: Apr 5, 2024, 12:41 AM | K33: Completed | L33: HySEA | O33: Egypt | P33: =COUNTIF(D$2:D$600,O33) -> 3 | Q33: {=XLOOKUP(O33,Countries!A$2:A$98,Countries!B$2:B$98,"tbd",0)} -> Middle East
A34: 38 | B34: Male | C34: TERC University of Hormozgan | D34: Iran | E34: No | F34: No | G34: Geohazard; Seismology; Tsunami | I34: No | J34: Apr 6, 2024, 8:04 PM | K34: Completed | L34: HySEA | O34: Australia | P34: =COUNTIF(D$2:D$600,O34) -> 1 | Q34: {=XLOOKUP(O34,Countries!A$2:A$98,Countries!B$2:B$98,"tbd",0)} -> Oceania
A35: 10 | B35: Female | C35: International institute of earthquake engineering and seismology | D35: Iran | E35: Yes | F35: Yes | G35: Geohazard; Seismology; Tsunami | I35: No | J35: Apr 2, 2024, 10:41 PM | K35: Completed | L35: HySEA | O35: Norway | P35: =COUNTIF(D$2:D$600,O35) -> 5 | Q35: {=XLOOKUP(O35,Countries!A$2:A$98,Countries!B$2:B$98,"tbd",0)} -> associated countries
A36: 12 | B36: Male | C36: Dinámica Costera | D36: Chile | E36: No | F36: Yes | G36: Engineering; Marine Sciences | I36: No | J36: Apr 4, 2024, 11:46 PM | K36: Completed | L36: HySEA | O36: Colombia | P36: =COUNTIF(D$2:D$600,O36) -> 6 | Q36: {=XLOOKUP(O36,Countries!A$2:A$98,Countries!B$2:B$98,"tbd",0)} -> Middle/South America
A37: 6 | B37: Male | C37: The Geological Survey of Israel | D37: Israel | E37: No | F37: No | G37: Geohazard; Seismology; Solid Earth | I37: Yes | J37: Mar 31, 2024, 12:33 PM | K37: Completed | L37: HySEA | O37: Portugal | P37: =COUNTIF(D$2:D$600,O37) -> 2 | Q37: {=XLOOKUP(O37,Countries!A$2:A$98,Countries!B$2:B$98,"tbd",0)} -> widening countries
A38: 58 | B38: Male | C38: BMKG | D38: Indonesia | E38: Yes | F38: No | G38: Geohazard; Seismology; Solid Earth; Tsunami; Volcanology | H38: Geology | I38: No | J38: Apr 22, 2024, 4:35 AM | K38: Completed | L38: HySEA | O38: Mexico | P38: =COUNTIF(D$2:D$600,O38) -> 2 | Q38: {=XLOOKUP(O38,Countries!A$2:A$98,Countries!B$2:B$98,"tbd",0)} -> Middle/South America
A39: 18 | B39: Male | C39: SHOA | D39: Chile | E39: No | F39: No | G39: Tsunami | I39: Yes | J39: Apr 5, 2024, 1:30 PM | K39: Completed | L39: HySEA | O39: Albania | P39: =COUNTIF(D$2:D$600,O39) -> 4 | Q39: {=XLOOKUP(O39,Countries!A$2:A$98,Countries!B$2:B$98,"tbd",0)} -> associated countries
A40: 2 | B40: Female | C40: GeoSphere Austria | D40: Austria | E40: Yes | F40: No | G40: Atmospheric Physics; Geohazard; Seismology | H40: Physics | I40: No | J40: Mar 20, 2024, 2:40 PM | K40: Completed | L40: HySEA | O40: Hungary | P40: =COUNTIF(D$2:D$600,O40) -> 2 | Q40: {=XLOOKUP(O40,Countries!A$2:A$98,Countries!B$2:B$98,"tbd",0)} -> widening countries
A41: 4 | B41: Female | C41: GFZ | D41: Germany | E41: Yes | F41: No | G41: Marine Sciences; Seismology | I41: No | J41: Mar 21, 2024, 1:42 PM | K41: Completed | L41: HySEA | O41: Cameroon | P41: =COUNTIF(D$2:D$600,O41) -> 1 | Q41: {=XLOOKUP(O41,Countries!A$2:A$98,Countries!B$2:B$98,"tbd",0)} -> Africa
A42: 42 | B42: Female | C42: National Institute for Earth Physics | D42: Romania | E42: No | F42: No | G42: Seismology; Tsunami | H42: Geophysicist | I42: No | J42: Apr 8, 2024, 10:42 AM | K42: Completed | L42: HySEA | O42: Canada | P42: =COUNTIF(D$2:D$600,O42) -> 6 | Q42: {=XLOOKUP(O42,Countries!A$2:A$98,Countries!B$2:B$98,"tbd",0)} -> U.S. + Canada
A43: 43 | B43: Male | C43: NIEP ROMANIA | D43: Romania | E43: No | F43: Yes | G43: Seismology | I43: No | J43: Apr 8, 2024, 11:51 AM | K43: Completed | L43: HySEA | O43: Andorra | P43: =COUNTIF(D$2:D$600,O43) -> 2 | Q43: {=XLOOKUP(O43,Countries!A$2:A$98,Countries!B$2:B$98,"tbd",0)} -> Europe
A44: 16 | B44: Male | C44: ICM, CSIC | D44: Spain | E44: No | F44: No | G44: Geohazard; Marine Sciences; Solid Earth | H44: Seismic tomography, dynamics rupture modelling | I44: No | J44: Apr 5, 2024, 10:16 AM | K44: Completed | L44: HySEA | O44: India | P44: =COUNTIF(D$2:D$600,O44) -> 8 | Q44: {=XLOOKUP(O44,Countries!A$2:A$98,Countries!B$2:B$98,"tbd",0)} -> Middle East
A45: 47 | B45: Female | C45: SHOA | D45: Chile | E45: No | F45: No | G45: Tsunami | I45: Yes | J45: Apr 8, 2024, 9:28 PM | K45: Completed | L45: HySEA | O45: Bolivia | P45: =COUNTIF(D$2:D$600,O45) -> 2 | Q45: {=XLOOKUP(O45,Countries!A$2:A$98,Countries!B$2:B$98,"tbd",0)} -> Middle/South America
A46: 40 | B46: Male | C46: Chilean association of port and coastal engineering | D46: Chile | E46: Yes | F46: No | G46: Engineering; Marine Sciences; Tsunami | I46: No | J46: Apr 7, 2024, 5:36 PM | K46: Completed | L46: HySEA | O46: Poland | P46: =COUNTIF(D$2:D$600,O46) -> 1 | Q46: {=XLOOKUP(O46,Countries!A$2:A$98,Countries!B$2:B$98,"tbd",0)} -> widening countries
A47: 36 | B47: Male | C47: Universidad Catolica de la Santisima Concepcion | D47: Chile | E47: Yes | F47: No | G47: Geohazard; Seismology; Solid Earth; Tsunami | I47: No | J47: Apr 6, 2024, 4:55 PM | K47: Completed | L47: HySEA | O47: Nigeria | P47: =COUNTIF(D$2:D$600,O47) -> 1 | Q47: {=XLOOKUP(O47,Countries!A$2:A$98,Countries!B$2:B$98,"tbd",0)} -> Africa
A48: 34 | B48: Male | C48: IUSS Pavia | D48: Italy | E48: Yes | F48: No | G48: Geohazard; Tsunami; Other | H48: Floods | I48: No | J48: Apr 6, 2024, 9:47 AM | K48: Completed | L48: HySEA | O48: unknown | P48: =COUNTIF(D$2:D$600,O48) -> 31 | Q48: {=XLOOKUP(O48,Countries!A$2:A$98,Countries!B$2:B$98,"tbd",0)} -> unknown
A49: 49 | B49: Male | C49: UMA | D49: Spain | E49: Yes | F49: No | G49: Other | H49: Maths | I49: No | J49: Apr 9, 2024, 9:23 PM | K49: Completed | L49: HySEA | O49: Croatia | P49: =COUNTIF(D$2:D$600,O49) -> 1 | Q49: {=XLOOKUP(O49,Countries!A$2:A$98,Countries!B$2:B$98,"tbd",0)} -> widening countries
A50: 35 | B50: Male | C50: Institute of Geophysics, University of Tehran | D50: Iran | E50: Yes | F50: No | G50: Engineering; Geohazard; Marine Sciences; Seismology; Tsunami; Volcanology | I50: No | J50: Apr 6, 2024, 11:11 AM | K50: Completed | L50: HySEA | O50: Singapore | P50: =COUNTIF(D$2:D$600,O50) -> 2 | Q50: {=XLOOKUP(O50,Countries!A$2:A$98,Countries!B$2:B$98,"tbd",0)} -> Asia
A51: 23 | B51: Female | C51: Lehigh University | D51: United States | E51: Yes | F51: No | G51: Engineering; Geohazard; Tsunami | I51: No | J51: Apr 5, 2024, 2:53 PM | K51: Completed | L51: HySEA | O51: Vietnam | P51: =COUNTIF(D$2:D$600,O51) -> 1 | Q51: {=XLOOKUP(O51,Countries!A$2:A$98,Countries!B$2:B$98,"tbd",0)} -> Asia
A52: 65 | B52: Male | C52: University of Malaga | D52: Spain | E52: Yes | F52: No | G52: Tsunami | I52: Yes | J52: Apr 24, 2024, 9:32 AM | K52: Completed | L52: HySEA | O52: Hongkong | P52: =COUNTIF(D$2:D$600,O52) -> 1 | Q52: {=XLOOKUP(O52,Countries!A$2:A$98,Countries!B$2:B$98,"tbd",0)} -> Asia
A53: 44 | B53: Female | C53: IGN | D53: Spain | E53: Yes | F53: No | G53: Tsunami | I53: No | J53: Apr 8, 2024, 12:19 PM | K53: Completed | L53: HySEA | O53: Finland | P53: =COUNTIF(D$2:D$600,O53) -> 1 | Q53: {=XLOOKUP(O53,Countries!A$2:A$98,Countries!B$2:B$98,"tbd",0)} -> Europe
A54: 29 | B54: Male | C54: Escuela Superior Politecnica Politecnica del Litoral | D54: Ecuador | E54: Yes | F54: No | G54: Engineering; Marine Sciences; Tsunami | I54: No | J54: Apr 5, 2024, 9:29 PM | K54: Completed | L54: HySEA | O54: Netherlands | P54: =COUNTIF(D$2:D$600,O54) -> 1 | Q54: {=XLOOKUP(O54,Countries!A$2:A$98,Countries!B$2:B$98,"tbd",0)} -> Europe
A55: 61 | B55: Male | C55: University of Malaga | D55: Spain | E55: No | F55: No | G55: Tsunami | I55: Yes | J55: Apr 23, 2024, 7:52 AM | K55: Completed | L55: HySEA | O55: Algeria | P55: =COUNTIF(D$2:D$600,O55) -> 1 | Q55: {=XLOOKUP(O55,Countries!A$2:A$98,Countries!B$2:B$98,"tbd",0)} -> Africa
A56: 37 | B56: Male | C56: Universidad de Zaragoza | D56: Spain | E56: Yes | F56: No | G56: Geohazard | I56: No | J56: Apr 6, 2024, 6:29 PM | K56: Completed | L56: HySEA | O56: Honduras | P56: =COUNTIF(D$2:D$600,O56) -> 1 | Q56: {=XLOOKUP(O56,Countries!A$2:A$98,Countries!B$2:B$98,"tbd",0)} -> Middle/South America
A57: 9 | B57: Male | C57: UNINA | D57: Italy | E57: Yes | F57: No | G57: Tsunami | I57: No | J57: Apr 2, 2024, 10:30 PM | K57: Completed | L57: HySEA | O57: Ireland | P57: =COUNTIF(D$2:D$600,O57) -> 2 | Q57: {=XLOOKUP(O57,Countries!A$2:A$98,Countries!B$2:B$98,"tbd",0)} -> Europe
A58: 17 | B58: Male | C58: KOERI | D58: Turkey | E58: Yes | F58: No | G58: Seismology | I58: Yes | J58: Apr 5, 2024, 10:21 AM | K58: Completed | L58: HySEA | O58: Sweden | P58: =COUNTIF(D$2:D$600,O58) -> 1 | Q58: {=XLOOKUP(O58,Countries!A$2:A$98,Countries!B$2:B$98,"tbd",0)} -> Europe
A59: 31 | B59: Male | C59: CSIC | D59: Spain | E59: No | F59: No | G59: Geohazard; Marine Sciences; Tsunami | I59: No | J59: Apr 5, 2024, 11:50 PM | K59: Completed | L59: HySEA
A60: 8 | B60: Female | C60: Escuela Superior Politécnica del Litoral | D60: Ecuador | E60: Yes | F60: No | G60: Marine Sciences; Tsunami | I60: No | J60: Apr 2, 2024, 3:59 PM | K60: Completed | L60: HySEA
A61: 53 | B61: Female | C61: Escuela Superior Politécnica del Litoral | D61: Ecuador | E61: Yes | F61: No | G61: Marine Sciences; Tsunami | I61: No | J61: Apr 12, 2024, 2:10 AM | K61: Completed | L61: HySEA
A62: 51 | B62: Male | C62: VLIZ | D62: Belgium | E62: No | F62: No | G62: Computer Science | I62: No | J62: Apr 10, 2024, 1:35 PM | K62: Completed | L62: HySEA
A63: 41 | B63: Female | C63: Institut de Ciències del Mar (ICM-CSIC) | D63: Spain | E63: Yes | F63: No | G63: Marine Sciences | I63: No | J63: Apr 8, 2024, 10:38 AM | K63: Completed | L63: HySEA
A64: 27 | B64: Female | C64: GFZ German Research Centre for Geosciences | D64: Germany | E64: No | F64: No | G64: Engineering; Geohazard; Seismology; Tsunami | I64: No | J64: Apr 5, 2024, 4:17 PM | K64: Completed | L64: HySEA
A65: 63 | B65: Female | C65: GFZ | D65: Germany | E65: No | F65: No | G65: Other | I65: No | J65: Apr 23, 2024, 12:42 PM | K65: Completed | L65: HySEA
A66: 26 | B66: Male | C66: Institute for risk and disaster reduction, University College London | D66: United Kingdom | E66: Yes | F66: No | G66: Engineering; Tsunami | I66: No | J66: Apr 5, 2024, 3:43 PM | K66: Completed | L66: HySEA
A67: 5 | B67: Female | C67: Institute of Earth Science,Academia Sinica | D67: Taiwan | E67: Yes | F67: No | G67: Engineering; Geohazard; Seismology; Solid Earth; Tsunami | H67: Geodesy, GIS, Urban Planning | I67: No | J67: Mar 25, 2024, 6:22 AM | K67: Completed | L67: HySEA
A68: 10 | B68: Male | C68: UC berkeley, USA | D68: United States | E68: No | F68: Yes | I68: No | J68: May 29, 2024, 4:41 PM | K68: Completed | L68: SDL
A69: 14 | B69: Female | C69: INGV, Italy | D69: Italy | E69: No | F69: No | I69: No | J69: May 31, 2024, 12:34 PM | K69: Completed | L69: SDL
A70: 34 | B70: Female | C70: Caltech | D70: United States | E70: No | F70: No | I70: No | J70: Jul 18, 2024, 9:41 PM | K70: Completed | L70: SDL
A71: 25 | B71: Female | C71: Middle East Technical University, Turkey | D71: Turkey | E71: No | F71: No | I71: No | J71: Jun 29, 2024, 6:30 PM | K71: Completed | L71: SDL
A72: 18 | B72: Male | C72: Université Gustve Eiffel, France | D72: France | E72: No | F72: No | I72: No | J72: Jun 4, 2024, 3:27 PM | K72: Completed | L72: SDL
A73: 12 | B73: Male | C73: ORFEUS and SED at ETH Zurich, Switzerland | D73: Switzerland | E73: No | F73: No | I73: Yes | J73: May 31, 2024, 7:40 AM | K73: Completed | L73: SDL
A74: 24 | B74: Male | C74: Sinotech Engineering Consultants (Inc.), Taipei | D74: Taiwan | E74: No | F74: No | I74: No | J74: Jun 11, 2024, 9:57 AM | K74: Completed | L74: SDL
A75: 17 | B75: Female | C75: LMU, Germany | D75: Germany | E75: No | F75: No | I75: Yes | J75: Jun 4, 2024, 12:02 PM | K75: Completed | L75: SDL
A76: 6 | B76: Male | C76: ETH Zurich, Switzerland | D76: Switzerland | E76: No | F76: No | I76: Yes | J76: May 29, 2024, 10:55 AM | K76: Completed | L76: SDL
A77: 33 | B77: Male | C77: GEO3BCN-CSIC | D77: Spain | E77: No | F77: No | I77: No | J77: Jul 18, 2024, 9:02 PM | K77: Completed | L77: SDL
A78: 30 | B78: Female | C78: Scripps Institution of Oceanography, UCSD, USA/LMU, Munich, Germany | D78: United States | E78: No | F78: No | I78: Yes | J78: Jul 6, 2024, 9:08 AM | K78: Completed | L78: SDL
A79: 20 | B79: Male | C79: HI, Island | D79: Iceland | E79: No | F79: No | I79: No | J79: Jun 7, 2024, 1:15 PM | K79: Completed | L79: SDL
... A99: 21 | B99: Male | C99: Northumbria University | D99: United Kingdom | E99: Yes | F99: No | I99: No | J99: Jun 8, 2024, 12:49 PM | K99: Completed | L99: SDL
A100: 62 | B100: male | C100: USGS | D100: United States | E100: No | F100: No | G100: Engineering seismology | I100: No | J100: 45525.662 | K100: Completed | L100: SDL
A101: 34 | B101: female | C101: Istituto Nazionale di Oceanografia e di Geofisica Sperimentale - OGS | D101: Italy | E101: Yes | F101: No | G101: earthquake seismology | I101: No | J101: Jul 5, 2024, 1:00 PM | K101: Completed | L101: SDL
A102: 16 | B102: Female | C102: LMU | D102: Germany | E102: Yes | F102: No | G102: Seismology, Physics-based numerical modeling, Seismic Hazard | I102: No | J102: Jun 4, 2024, 1:36 PM | K102: Completed | L102: SDL
A103: 43 | B103: Male | C103: Ghana Atomic Energy Commission | D103: Ghana | E103: Yes | F103: No | G103: I'm a PhD student. My expertise are earthquake geotechnical engineering, earthquake engineering, strong motions, engineering seismology and soil liquefaction studies. | I103: Yes | J103: Jul 11, 2024, 4:51 PM | K103: Completed | L103: SDL
A104: 56 | B104: Female | C104: NCM | D104: United Arab Emirates | E104: Yes | F104: Yes | G104: Seismology | I104: No | J104: 45509.571 | K104: Completed | L104: SDL
A105: 81 | B105: Male | C105: ETH Zürich | D105: Switzerland | E105: Yes | F105: No | G105: I am a PhD student working on seismology | I105: No | J105: 45532.676 | K105: Completed | L105: SDL
A106: 88 | B106: Male | C106: GFZ Potsdam | D106: Germany | E106: No | F106: No | G106: Geoscientist | I106: No | J106: 45534.672 | K106: Completed | L106: SDL
A107: 87 | B107: Male | C107: King Abdullah University of science and technology | D107: Saudi Arabia | E107: Yes | F107: No | G107: Ground motion simulation and earthquake source modeling | I107: Yes | J107: 45534.624 | K107: Completed | L107: SDL
A108: 30 | B108: Male | C108: Universidad De Costa Rica | D108: Costa Rica | E108: Yes | F108: No | G108: Neotectonics, Paleoseismology and Seismology | I108: Yes | J108: Jul 3, 2024, 12:21 AM | K108: Completed | L108: SDL
A109: 64 | B109: Male | C109: GFZ | D109: Germany | E109: Yes | F109: No | G109: Seismology / Seismic Hazard | I109: No | J109: 45527.646 | K109: Completed | L109: SDL
A110: 12 | B110: female | C110: Cadi Ayyad University Morocco | D110: Morocco | E110: Yes | F110: No | G110: I am a second-year PhD student from Morocco, studying at Cadi Ayyad University. My research focuses on tsunami risk assessment along the Atlantic coast of Morocco, with a particular emphasis on modeling and studying structural vulnerability. | I110: No | J110: Jun 2, 2024, 5:06 PM | K110: Completed | L110: SDL
A111: 35 | B111: Male | C111: North Carolina State University | D111: United States | E111: Yes | F111: No | G111: Earthquake Engineering | I111: No | J111: Jul 5, 2024, 4:41 PM | K111: Completed | L111: SDL
A112: 97 | B112: female | C112: University of Iceland | D112: Iceland | E112: Yes | F112: No | G112: Earthquake Engineering | I112: No | J112: Sep 2, 2024, 4:14 PM | K112: Completed | L112: SDL
A113: 48 | B113: Male | C113: Swiss Seismological Service at ETH Zurich | D113: Switzerland | E113: No | F113: No | G113: Engineering seismology | I113: No | J113: Jul 17, 2024, 9:33 AM | K113: Completed | L113: SDL
A114: 10 | B114: Male | C114: Barcelona Supercomputing center | D114: Spain | E114: No | F114: No | G114: Data, statistics, learned models | I114: No | J114: May 31, 2024, 3:56 PM | K114: Completed | L114: SDL
A115: 3 | B115: Male | C115: GFZ-Potsdam | D115: Germany | E115: No | F115: No | G115: Observational seismology | I115: No | J115: May 29, 2024, 12:30 PM | K115: Completed | L115: SDL
A116: 92 | B116: Male | C116: GNS Science | D116: New Zealand | E116: No | F116: No | G116: Engineering Seismology and Seismic Hazard Analysis | I116: No | J116: 45535.922 | K116: Completed | L116: SDL
A117: 82 | B117: female | C117: GFZ | D117: Germany | E117: No | F117: No | G117: 3D structural geological modelling, gravity modelling, thermal modelling | I117: No | J117: 45533.525 | K117: Completed | L117: SDL
A118: 68 | B118: Male | C118: Helmholtz-Zentrum Potsdam Deutsches GeoForschungsZentrum GFZ | D118: Germany | E118: No | F118: No | G118: Software Development | I118: No | J118: 45530.324 | K118: Completed | L118: SDL
A119: 32 | B119: female | C119: North Carolina State University | D119: United States | E119: No | F119: No | G119: Geotechnical Earthquake Engineering and Engineering Seismology | I119: No | J119: Jul 5, 2024, 10:31 AM | K119: Completed | L119: SDL
...

Sheet SeisSol_ExaHyPE_WS
A1: ID | B1: Gender | C1: Affiliation | D1: Country Of Affiliation | E1: Are You An Early Career Scientist? | F1: Do You Work In Industry, Start-Up Or Small/Medium Enterprise? | G1: What Is Your Scientific Expertise? (Multiple Choice) | H1: Scientific Expertise - Other(s): | I1: Have you been familiar with any of the involved Geo-INQUIRE services before? | J1: Registration date | K1: How did you hear about this event: | L1: Tags | O1: Countries | P1: No_Countries | Q1: Category
A2: 15 | B2: Female | C2: LMU | D2: Germany | E2: No | F2: No | G2: Seismology | L2: SeisSol_ExaHyPE_WS | O2: {=UNIQUE(D2:D187)} -> Germany | P2: =COUNTIF(D$2:D$120,O2) -> 29 | Q2: {=XLOOKUP(O2,Countries!A$2:A$98,Countries!B$2:B$98,"tbd",0)} -> Europe
A3: 55 | B3: Male | C3: Ghana Atomic Energy Commission | D3: Ghana | E3: Yes | F3: Yes | G3: Data Science; Energy Transformation/Storage; Natural Hazard Management; Marine Geology / Geophysics; Volcanology; Seismology; Tsunami; Geodesy; Remote sensing; Geology; Hydrology | L3: SeisSol_ExaHyPE_WS | O3: Ghana | P3: =COUNTIF(D$2:D$120,O3) -> 1 | Q3: {=XLOOKUP(O3,Countries!A$2:A$98,Countries!B$2:B$98,"tbd",0)} -> Africa
A4: 45 | B4: Male | C4: Technical University of Munich | D4: Germany | E4: No | F4: No | G4: Computer Science | H4: Computational Science and Engineering, Simulation software | L4: SeisSol_ExaHyPE_WS | O4: Ecuador | P4: =COUNTIF(D$2:D$120,O4) -> 1 | Q4: {=XLOOKUP(O4,Countries!A$2:A$98,Countries!B$2:B$98,"tbd",0)} -> Middle/South America
A5: 37 | B5: Male | C5: LRZ | D5: Germany | E5: No | F5: No | G5: Other | H5: Physiker | L5: SeisSol_ExaHyPE_WS | O5: Italy | P5: =COUNTIF(D$2:D$120,O5) -> 5 | Q5: {=XLOOKUP(O5,Countries!A$2:A$98,Countries!B$2:B$98,"tbd",0)} -> Europe
A6: 60 | B6: Male | C6: Earthquake Engineering | D6: Ecuador | E6: Yes | F6: Yes | G6: Computer Science; Data Science; Natural Hazard Management; Seismology; Tsunami; Geodesy; Other | H6: Earthquake resistant systems | L6: SeisSol_ExaHyPE_WS | O6: United States | P6: =COUNTIF(D$2:D$120,O6) -> 6 | Q6: {=XLOOKUP(O6,Countries!A$2:A$98,Countries!B$2:B$98,"tbd",0)} -> U.S. + Canada
A7: 31 | B7: Male | C7: Advanced Micro Devices GmbH | D7: Germany | E7: No | F7: Yes | G7: Computer Science | L7: SeisSol_ExaHyPE_WS | O7: United Kingdom | P7: =COUNTIF(D$2:D$120,O7) -> 5 | Q7: {=XLOOKUP(O7,Countries!A$2:A$98,Countries!B$2:B$98,"tbd",0)} -> associated countries
A8: 1 | B8: Female | C8: LMU | D8: Germany | E8: No | F8: No | G8: Computer Science | H8: HPC | L8: SeisSol_ExaHyPE_WS | O8: Norway | P8: =COUNTIF(D$2:D$120,O8) -> 1 | Q8: {=XLOOKUP(O8,Countries!A$2:A$98,Countries!B$2:B$98,"tbd",0)} -> associated countries
A9: 17 | B9: Female | C9: INGV | D9: Italy | E9: Yes | F9: No | G9: Seismology | H9: Rock Mechanics | L9: SeisSol_ExaHyPE_WS | O9: France | P9: =COUNTIF(D$2:D$120,O9) -> 4 | Q9: {=XLOOKUP(O9,Countries!A$2:A$98,Countries!B$2:B$98,"tbd",0)} -> Europe
A10: 20 | B10: Male | C10: University of Padua | D10: Italy | E10: Yes | F10: No | G10: Seismology | L10: SeisSol_ExaHyPE_WS | O10: Poland | P10: =COUNTIF(D$2:D$120,O10) -> 3 | Q10: {=XLOOKUP(O10,Countries!A$2:A$98,Countries!B$2:B$98,"tbd",0)} -> widening countries
A11: 41 | B11: Male | C11: University of Trento | D11: Italy | E11: No | F11: No | G11: Computer Science; Other | H11: Applied Mathematics | L11: SeisSol_ExaHyPE_WS | O11: Indonesia | P11: =COUNTIF(D$2:D$120,O11) -> 2 | Q11: {=XLOOKUP(O11,Countries!A$2:A$98,Countries!B$2:B$98,"tbd",0)} -> Asia
A12: 44 | B12: Male | C12: Johannes Gutenberg-Universität Mainz | D12: Germany | E12: Yes | F12: No | G12: Computer Science | L12: SeisSol_ExaHyPE_WS | O12: Brazil | P12: =COUNTIF(D$2:D$120,O12) -> 1 | Q12: {=XLOOKUP(O12,Countries!A$2:A$98,Countries!B$2:B$98,"tbd",0)} -> Middle/South America
A13: 8 | B13: Female | C13: UCSD | D13: United States | E13: No | F13: No | G13: Computer Science; Data Science; Seismology; Tsunami; Geodesy | L13: SeisSol_ExaHyPE_WS | O13: Switzerland | P13: =COUNTIF(D$2:D$120,O13) -> 1 | Q13: {=XLOOKUP(O13,Countries!A$2:A$98,Countries!B$2:B$98,"tbd",0)} -> Europe
A14: 10 | B14: Male | C14: Karlsruhe Institute of Technology | D14: Germany | E14: Yes | F14: No | G14: Seismology | L14: SeisSol_ExaHyPE_WS | O14: Slovenia | P14: =COUNTIF(D$2:D$120,O14) -> 1 | Q14: {=XLOOKUP(O14,Countries!A$2:A$98,Countries!B$2:B$98,"tbd",0)} -> widening countries
A15: 50 | B15: Female | C15: Starting at SCCS in July | D15: Germany | E15: Yes | F15: No | G15: Computer Science | L15: SeisSol_ExaHyPE_WS
A16: 32 | B16: Male | C16: University of Plymouth | D16: United Kingdom | E16: Yes | F16: No | G16: Natural Hazard Management; Geology | H16: Numerical modelling | L16: SeisSol_ExaHyPE_WS | P16: =SUM(P2:P14) -> 60
A17: 34 | B17: Male | C17: Norwegian Geotechnical Institute | D17: Norway | E17: No | F17: No | G17: Marine Geology / Geophysics; Seismology; Tsunami | H17: Numerical models/simulations, signal processing. | L17: SeisSol_ExaHyPE_WS
A18: 49 | B18: Male | C18: Leibniz-Rechenzentrum der BAdW | D18: Germany | E18: No | F18: No | G18: Other | H18: Research Data Management, Astrophysics | L18: SeisSol_ExaHyPE_WS
A19: 14 | B19: Female | C19: University of California San Diego | D19: United States | E19: Yes | F19: No | G19: Marine Geology / Geophysics; Seismology | L19: SeisSol_ExaHyPE_WS | P19: 4 | Q19: widening/associated countries
A20: 19 | B20: Male | C20: ASNR | D20: France | E20: No | F20: No | G20: Seismology | H20: Earthquake Rupture Dynamics | L20: SeisSol_ExaHyPE_WS | P20: 11 | Q20: non-EU
A21: 47 | B21: Male | C21: LMU | D21: Germany | E21: No | F21: No | G21: Seismology | L21: SeisSol_ExaHyPE_WS | P21: 13 | Q21: different countries
A22: 12 | B22: Male | C22: TUM | D22: Germany | E22: Yes | F22: No | G22: Computer Science | L22: SeisSol_ExaHyPE_WS | P22: 14 | Q22: different scientific fields
A23: 39 | B23: Male | C23: Technical University of Munich | D23: Germany | E23: Yes | F23: No | G23: Computer Science | L23: SeisSol_ExaHyPE_WS
A24: 28 | B24: Male | C24: MunichRE | D24: Germany | E24: No | F24: Yes | G24: Natural Hazard Management; Marine Geology / Geophysics; Volcanology; Seismology; Tsunami | L24: SeisSol_ExaHyPE_WS
A25: 51 | B25: Male | C25: NVIDIA | D25: Germany | E25: No | F25: Yes | G25: Computer Science; Data Science; Seismology; Tsunami | L25: SeisSol_ExaHyPE_WS
A26: 61 | B26: Male | C26: IGF PAN | D26: Poland | E26: Yes | F26: No | G26: Marine Geology / Geophysics; Seismology | L26: SeisSol_ExaHyPE_WS
A27: 5 | B27: Male | C27: Technical University of Munich | D27: Germany | E27: Yes | F27: No | G27: Computer Science; Seismology | L27: SeisSol_ExaHyPE_WS
A28: 6 | B28: Male | C28: Institute of Geophysics and Planetary Physics, Scripps Institution of Oceanography, University of California San Diego, La Jolla, CA, USA | D28: United States | E28: Yes | F28: No | G28: Seismology; Tsunami | L28: SeisSol_ExaHyPE_WS
A29: 57 | B29: Other | C29: GFZ | D29: Germany | E29: Yes | F29: No | G29: Seismology | L29: SeisSol_ExaHyPE_WS
A30: 42 | B30: Male | C30: IPGP - Institut de Physique du Globe de Paris | D30: France | E30: Yes | F30: No | G30: Remote sensing; Geology | L30: SeisSol_ExaHyPE_WS
A31: 36 | B31: Male | C31: Durham University | D31: United Kingdom | E31: Yes | F31: No | G31: Computer Science | L31: SeisSol_ExaHyPE_WS
A32: 25 | B32: Male | C32: National Science Foundation - National Center for Atmospheric Research (NSF-NCAR) | D32: United States | E32: No | F32: No | G32: Computer Science; Oceanography; Tsunami; Other | H32: storm surge, climate change, risk analysis | L32: SeisSol_ExaHyPE_WS
A33: 7 | B33: Female | C33: LMU | D33: Germany | E33: Yes | F33: No | G33: Seismology; Geodesy; Remote sensing | L33: SeisSol_ExaHyPE_WS
A34: 30 | B34: Male | C34: TUM | D34: Germany | E34: Yes | F34: No | G34: Computer Science | L34: SeisSol_ExaHyPE_WS
A35: 24 | B35: Male | C35: LRZ | D35: Germany | E35: No | F35: No | G35: Computer Science; Other | H35: Physics, Chemistry, Biology | L35: SeisSol_ExaHyPE_WS
A36: 48 | B36: Female | C36: TU Dortmund, Germany | D36: Germany | E36: Yes | F36: No | G36: Natural Hazard Management; Seismology; Remote sensing; Geology | L36: SeisSol_ExaHyPE_WS
A37: 16 | B37: Male | C37: Ifremer | D37: France | E37: No | F37: No | G37: Seismology; Tsunami | L37: SeisSol_ExaHyPE_WS
A38: 26 | B38: Male | C38: Institut Teknologi Sepuluh Nopember | D38: Indonesia | E38: Yes | F38: No | G38: Seismology | L38: SeisSol_ExaHyPE_WS
A39: 29 | B39: Male | C39: BMKG | D39: Indonesia | E39: Yes | F39: No | G39: Seismology | L39: SeisSol_ExaHyPE_WS
A40: 21 | B40: Female | C40: LMU Munich | D40: Germany | E40: Yes | F40: No | G40: Seismology | L40: SeisSol_ExaHyPE_WS
A41: 33 | B41: Male | C41: Self | D41: Germany | E41: No | F41: Yes | G41: Computer Science | L41: SeisSol_ExaHyPE_WS
A42: 27 | B42: Male | C42: Intel | D42: Germany | E42: No | F42: Yes | G42: Computer Science | L42: SeisSol_ExaHyPE_WS
A43: 35 | B43: Female | C43: Durham University | D43: United Kingdom | E43: No | F43: No | G43: Computer Science; Data Science | L43: SeisSol_ExaHyPE_WS
A44: 54 | B44: Male | C44: Minebea AccessSolutions Deuschland GmbH | D44: Germany | E44: No | F44: Yes | G44: Computer Science | L44: SeisSol_ExaHyPE_WS
A45: 43 | B45: Female | C45: UNICAMP | D45: Brazil | E45: Yes | F45: No | G45: Computer Science; Data Science; Energy Transformation/Storage | L45: SeisSol_ExaHyPE_WS
A46: 46 | B46: Male | C46: AMD | D46: Germany | E46: Yes | F46: Yes | G46: Computer Science | L46: SeisSol_ExaHyPE_WS
A47: 9 | B47: Male | C47: ETH Zurich | D47: Switzerland | E47: Yes | F47: No | G47: Seismology | L47: SeisSol_ExaHyPE_WS
... A57: 11 | B57: Male | C57: TUM | D57: Germany | E57: Yes | F57: No | G57: Computer Science; Tsunami | L57: SeisSol_ExaHyPE_WS
A58: 40 | B58: Male | C58: University of Trento | D58: Italy | E58: No | F58: No | G58: Other | H58: Numerical analysis, Numerical relativity | L58: SeisSol_ExaHyPE_WS
A59: 53 | B59: Male | C59: University of California, San Diego | D59: United States | E59: Yes | F59: No | G59: Computer Science; Marine Geology / Geophysics; Seismology; Other | H59: Structural Engineering | L59: SeisSol_ExaHyPE_WS
A60: 23 | B60: Male | C60: Durham University | D60: United Kingdom | E60: Yes | F60: No | G60: Other | H60: Astrophysics | L60: SeisSol_ExaHyPE_WS
A61: 38 | B61: Male | C61: University of Texas at Austin | D61: United States | E61: Yes | F61: No | G61: Seismology | H61: High Performance Computing | L61: SeisSol_ExaHyPE_WS

Sheet Barcelona_TsunamiGenesis
A1: ID | B1: Gender | C1: Affiliation | D1: Country of Affiliation | E1: Are you an Early Career Scientist? | F1: Do you work in industry, a Start-up or Small and Medium Enterprise? | G1: What is your scientific expertise? (Multiple Choice) | H1: Scientific expertise - Other(s): | I1: Have you been familiar with any of the involved Geo-INQUIRE services before? | J1: Registration date | K1: How did you hear about this event: | L1: Tags | O1: Countries | P1: No_Countries | Q1: Category
A2: 19 | B2: Female | C2: Cadi Ayyad University Morocco | D2: Morocco | E2: Yes | F2: No | G2: Environmental Protection; Geohazard; Marine Sciences; Tsunami | I2: No | J2: 45809.108 | K2: Geo-INQUIRE website | L2: Geohazard_WS1 | O2: {=UNIQUE(D2:D187)} -> Morocco | P2: =COUNTIF(D$2:D$120,O2) -> 3 | Q2: {=XLOOKUP(O2,Countries!A$2:A$98,Countries!B$2:B$98,"tbd",0)} -> Africa
A3: 25 | B3: Male | C3: Instituto de Ciencias del Mar CSIC | D3: Spain | E3: No | F3: No | G3: Geohazard; Marine Sciences; Seismology | H3: marine geophysics, tectonics and seismic reflection data | I3: No | J3: 45821.444 | K3: Colleagues | L3: Geohazard_WS1 | O3: Spain | P3: =COUNTIF(D$2:D$120,O3) -> 12 | Q3: {=XLOOKUP(O3,Countries!A$2:A$98,Countries!B$2:B$98,"tbd",0)} -> Europe
A4: 26 | B4: Male | C4: Institute of Engineering, UNAM | D4: Mexico | E4: No | F4: No | G4: Engineering; Geohazard; Seismology; Solid Earth; Tsunami | H4: Geophysics | I4: Yes | J4: 45821.767 | K4: Geo-INQUIRE linkedin | L4: Geohazard_WS1 | O4: Mexico | P4: =COUNTIF(D$2:D$120,O4) -> 2 | Q4: {=XLOOKUP(O4,Countries!A$2:A$98,Countries!B$2:B$98,"tbd",0)} -> Middle/South America
A5: 7 | B5: Male | C5: Addis Ababa University & Debre Berhan Universit, Ethiopia | D5: Ethiopia | E5: Yes | F5: Yes | G5: Geohazard; Seismology | I5: No | J5: 45799.611 | K5: Geo-INQUIRE website | L5: Geohazard_WS1 | O5: Ethiopia | P5: =COUNTIF(D$2:D$120,O5) -> 1 | Q5: {=XLOOKUP(O5,Countries!A$2:A$98,Countries!B$2:B$98,"tbd",0)} -> Africa
A6: 10 | B6: Male | C6: Politecnico di Milano - polimi | D6: Italy | E6: Yes | F6: No | G6: Environmental Protection; Engineering; Geohazard | I6: Yes | J6: 45803.711 | K6: Geo-INQUIRE linkedin | L6: Geohazard_WS1 | O6: Italy | P6: =COUNTIF(D$2:D$120,O6) -> 2 | Q6: {=XLOOKUP(O6,Countries!A$2:A$98,Countries!B$2:B$98,"tbd",0)} -> Europe
A7: 23 | B7: Male | C7: IH Cantabria | D7: Spain | E7: Yes | F7: No | G7: Geohazard; Marine Sciences; Tsunami | I7: Yes | J7: 45817.806 | K7: Colleagues | L7: Geohazard_WS1 | O7: Poland | P7: =COUNTIF(D$2:D$120,O7) -> 1 | Q7: {=XLOOKUP(O7,Countries!A$2:A$98,Countries!B$2:B$98,"tbd",0)} -> widening countries
A8: 22 | B8: Male | C8: UMA | D8: Spain | E8: Yes | F8: No | G8: Tsunami | I8: Yes | J8: 45813.557 | K8: Colleagues | L8: Geohazard_WS1 | O8: India | P8: =COUNTIF(D$2:D$120,O8) -> 1 | Q8: {=XLOOKUP(O8,Countries!A$2:A$98,Countries!B$2:B$98,"tbd",0)} -> Middle East
A9: 12 | B9: Male | C9: CN IGME (CSIC) | D9: Spain | E9: No | F9: No | G9: Environmental Protection; Engineering; Geohazard; Seismology; Tsunami; Volcanology | I9: Yes | J9: 45804.633 | K9: Colleagues | L9: Geohazard_WS1 | O9: Greece | P9: =COUNTIF(D$2:D$120,O9) -> 1 | Q9: {=XLOOKUP(O9,Countries!A$2:A$98,Countries!B$2:B$98,"tbd",0)} -> widening countries
A10: 11 | B10: Female | C10: ICM-CSIC | D10: Spain | E10: No | F10: No | G10: Geohazard; Marine Sciences; Solid Earth; Tsunami | I10: Yes | J10: 45804.465 | K10: Newsletter or website of the Ris (EPOS, ERIC, etc.) | L10: Geohazard_WS1 | O10: Iceland | P10: =COUNTIF(D$2:D$120,O10) -> 1 | Q10: {=XLOOKUP(O10,Countries!A$2:A$98,Countries!B$2:B$98,"tbd",0)} -> associated countries
A11: 14 | B11: Male | C11: Hassan II University of Casablanca | D11: Morocco | E11: Yes | F11: No | G11: Engineering; Geohazard; Seismology | I11: Yes | J11: 45805.73 | K11: Geo-INQUIRE website | L11: Geohazard_WS1 | O11: United States | P11: =COUNTIF(D$2:D$120,O11) -> 1 | Q11: {=XLOOKUP(O11,Countries!A$2:A$98,Countries!B$2:B$98,"tbd",0)} -> U.S. + Canada
A12: 2 | B12: Male | C12: Institute of Geophysics, Polish Academy of Siences | D12: Poland | E12: Yes | F12: No | G12: Engineering; Geohazard; Marine Sciences; Seismology; Solid Earth; Other | H12: Geophysics and Geology | I12: No | J12: 45782.799 | K12: Geo-INQUIRE website | L12: Geohazard_WS1 | O12: Germany | P12: =COUNTIF(D$2:D$120,O12) -> 1 | Q12: {=XLOOKUP(O12,Countries!A$2:A$98,Countries!B$2:B$98,"tbd",0)} -> Europe
A13: 16 | B13: Male | C13: Faculty of Sciences and Techniques of Tangier, Abdelmaled Essaadi university | D13: Morocco | E13: Yes | F13: No | G13: Geohazard; Marine Sciences; Seismology; Tsunami | H13: I am currently conducting a PhD candidate on tsunami hazard assessment along the Moroccan coasts. I have already performed several tsunami simulations using numerical tools such as COMCOT and NSWING, and I have published scientific articles related to tsunami scenarios triggered by submarine faults and landslides. | I13: Yes | J13: 45807.551 | K13: Geo-INQUIRE linkedin | L13: Geohazard_WS1
A14: 4 | B14: Female | C14: CSIR-Senior Research Fellow (PhD Student) at CSIR-National Geophysical Research Institute, Hyderabad, Telangana State, India, 500007. | D14: India | E14: Yes | F14: No | G14: Geohazard; Marine Sciences; Other | H14: Gas hydrates, Submarine slope failures | I14: Yes | J14: 45790.389 | K14: Other | L14: Geohazard_WS1 | P14: =SUM(P2:P11) -> 25
A15: 5 | B15: Female | C15: Aristotle University of Thessaloniki | D15: Greece | E15: Yes | F15: No | G15: Environmental Protection; Geohazard; Seismology; Solid Earth; Tsunami; Other | H15: Active Tectonics and Remote Sensing | I15: Yes | J15: 45790.522 | K15: Geo-INQUIRE mailinglist | L15: Geohazard_WS1
A16: 24 | B16: Male | C16: ICM, CSIC | D16: Spain | E16: No | F16: No | G16: Geohazard; Seismology; Solid Earth; Tsunami | H16: Seismic imaging of the uppermost lithosphere and numerical dynamic rupture simulations | I16: No | J16: 45821.403 | K16: Colleagues | L16: Geohazard_WS1 | P16: 3 | Q16: widening/associated countries
A17: 20 | B17: Male | C17: University of Málaga | D17: Spain | E17: Yes | F17: Yes | G17: Computer Science; Marine Sciences; Tsunami | I17: Yes | J17: 45813.553 | K17: Colleagues | L17: Geohazard_WS1 | P17: 8 | Q17: non-EU
A18: 13 | B18: Female | C18: Universidad Nacional Autónoma de México | D18: Mexico | E18: Yes | F18: No | G18: Engineering; Geohazard; Seismology | I18: No | J18: 45804.888 | K18: Colleagues | L18: Geohazard_WS1 | P18: 11 | Q18: different countries
A19: 21 | B19: Male | C19: Istituto Nazionale di Geofisica e Vulcanologia | D19: Spain | E19: Yes | F19: No | G19: Tsunami | I19: Yes | J19: 45813.556 | K19: Colleagues | L19: Geohazard_WS1 | P19: 13 | Q19: different scientific fields
A20: 3 | B20: Male | C20: University of Iceland | D20: Iceland | E20: No | F20: No | G20: Engineering; Marine Sciences; Tsunami | H20: Physical Oceanography | I20: Yes | J20: 45787.933 | K20: Newsletter or website of the Ris (EPOS, ERIC, etc.) | L20: Geohazard_WS1
A21: 9 | B21: Male | C21: University of Málaga | D21: Spain | E21: No | F21: No | G21: Tsunami | I21: Yes | J21: 45803.542 | K21: Geo-INQUIRE linkedin | L21: Geohazard_WS1
A22: 6 | B22: Male | C22: The Ohio State University | D22: United States | E22: No | F22: No | G22: Geohazard; Marine Sciences | I22: No | J22: 45795.703 | K22: Colleagues | L22: Geohazard_WS1
A23: 15 | B23: Female | C23: ICM-CSIC | D23: Spain | E23: Yes | F23: No | G23: Geohazard; Seismology; Solid Earth; Tsunami | I23: Yes | J23: 45806.436 | K23: Colleagues | L23: Geohazard_WS1
A24: 17 | B24: Male | C24: UNINA (University of Naples Federico II) | D24: Italy | E24: Yes | F24: No | G24: Geohazard; Tsunami | I24: Yes | J24: 45807.558 | K24: Geo-INQUIRE linkedin | L24: Geohazard_WS1
A25: 1 | B25: Male | C25: CSIC | D25: Spain | E25: No | F25: No | G25: Geohazard; Solid Earth; Tsunami | I25: Yes | J25: 45777.429 | K25: Newsletter or website of the Ris (EPOS, ERIC, etc.) | L25: Geohazard_WS1
A26: 8 | B26: Male | C26: Technical University of Munich | D26: Germany | E26: Yes | F26: No | G26: Computer Science; Seismology; Tsunami | I26: Yes | J26: 45800.569 | K26: Geo-INQUIRE mailinglist | L26: Geohazard_WS1
A27: 18 | B27: Female | C27: Barcelona Supercomputing Center | D27: Spain | E27: No | F27: No | G27: Geohazard; Seismology; Tsunami | I27: Yes | J27: 45807.564 | K27: Geo-INQUIRE mailinglist | L27: Geohazard_WS1

Sheet SDL_Trg
A1: ID | B1: Gender | C1: Affiliation | D1: Country of Affiliation | E1: Are you an Early Career Scientist? | F1: Do you work in industry, a Start-up or Small and Medium Enterprise? | G1: What is your scientific expertise? (Multiple Choice) | H1: Scientific expertise - Other(s): | I1: Have you been familiar | J1: Registration date | K1: How did you hear about this event: | L1: Tags | O1: Countries | P1: No_Countries | Q1: Category
A2: 38 | B2: Male | C2: Muslim Hands International | D2: Bangladesh | E2: No | F2: Yes | G2: Computer Science; Environmental Protection; Engineering; Geohazard; Other | H2: GIS, Remote Sensing, Data Science | I2: unknown | J2: 45908.59 | K2: Other | L2: SDL_Trg | O2: {=UNIQUE(D2:D187)} -> Bangladesh | P2: =COUNTIF(D$2:D$120,O2) -> 1 | Q2: {=XLOOKUP(O2,Countries!A$2:A$98,Countries!B$2:B$98,"tbd",0)} -> Middle East
A3: 37 | B3: Male | C3: Alma Mater Studiorum University of Bologna | D3: Italy | E3: No | F3: No | G3: Geohazard; Seismology; Solid Earth; Tsunami | I3: unknown | J3: 45908.523 | K3: Other | L3: SDL_Trg | O3: Italy | P3: =COUNTIF(D$2:D$120,O3) -> 12 | Q3: {=XLOOKUP(O3,Countries!A$2:A$98,Countries!B$2:B$98,"tbd",0)} -> Europe
A4: 16 | B4: Male | C4: GFZ Helmholtz Centre for Geosciences | D4: Germany | E4: No | F4: No | G4: Geohazard; Tsunami | I4: unknown | J4: 45877.683 | K4: Geo-INQUIRE mailinglist | L4: SDL_Trg | O4: Germany | P4: =COUNTIF(D$2:D$120,O4) -> 6 | Q4: {=XLOOKUP(O4,Countries!A$2:A$98,Countries!B$2:B$98,"tbd",0)} -> Europe
A5: 18 | B5: Diverse | C5: Barcelona Supercomputing Center | D5: Spain | E5: No | F5: No | G5: Computer Science; Geohazard; Other | H5: AI | I5: unknown | J5: 45879.883 | K5: Colleagues | L5: SDL_Trg | O5: Spain | P5: =COUNTIF(D$2:D$120,O5) -> 11 | Q5: {=XLOOKUP(O5,Countries!A$2:A$98,Countries!B$2:B$98,"tbd",0)} -> Europe
A6: 8 | B6: Female | C6: Universidad Católica de Chile | D6: Chile | E6: Yes | F6: Yes | G6: Engineering; Geohazard; Seismology; Tsunami | I6: unknown | J6: 45870.858 | K6: Geo-INQUIRE mailinglist | L6: SDL_Trg | O6: Chile | P6: =COUNTIF(D$2:D$120,O6) -> 1 | Q6: {=XLOOKUP(O6,Countries!A$2:A$98,Countries!B$2:B$98,"tbd",0)} -> Middle/South America
A7: 34 | B7: Female | C7: CINECA | D7: Italy | E7: No | F7: Yes | G7: Computer Science | I7: unknown | J7: 45905.478 | K7: Geo-INQUIRE website | L7: SDL_Trg | O7: Norway | P7: =COUNTIF(D$2:D$120,O7) -> 3 | Q7: {=XLOOKUP(O7,Countries!A$2:A$98,Countries!B$2:B$98,"tbd",0)} -> associated countries
A8: 1 | B8: Female | C8: LMU - Dept. of Geophysics | D8: Germany | E8: No | F8: No | G8: Computer Science | H8: HPC | I8: unknown | J8: 45862.368 | K8: Geo-INQUIRE mailinglist | L8: SDL_Trg | O8: Indonesia | P8: =COUNTIF(D$2:D$120,O8) -> 1 | Q8: {=XLOOKUP(O8,Countries!A$2:A$98,Countries!B$2:B$98,"tbd",0)} -> Asia
A9: 28 | B9: Male | C9: GFZ | D9: Germany | E9: Yes | F9: Yes | G9: Computer Science | I9: unknown | J9: 45897.481 | K9: Geo-INQUIRE website | L9: SDL_Trg | O9: Poland | P9: =COUNTIF(D$2:D$120,O9) -> 1 | Q9: {=XLOOKUP(O9,Countries!A$2:A$98,Countries!B$2:B$98,"tbd",0)} -> widening countries
A10: 14 | B10: Female | C10: BSC - CNS | D10: Spain | E10: No | F10: No | G10: Engineering | I10: unknown | J10: 45877.634 | K10: Geo-INQUIRE mailinglist | L10: SDL_Trg | O10: Georgia | P10: =COUNTIF(D$2:D$120,O10) -> 1 | Q10: {=XLOOKUP(O10,Countries!A$2:A$98,Countries!B$2:B$98,"tbd",0)} -> associated countries
A11: 17 | B11: Male | C11: Geociencias Barcelona (GEO3BCN-CSIC) | D11: Spain | E11: No | F11: No | G11: Computer Science; Geohazard; Solid Earth; Volcanology | I11: unknown | J11: 45879.434 | K11: Geo-INQUIRE mailinglist | L11: SDL_Trg | O11: Morocco | P11: =COUNTIF(D$2:D$120,O11) -> 1 | Q11: {=XLOOKUP(O11,Countries!A$2:A$98,Countries!B$2:B$98,"tbd",0)} -> Africa
A12: 20 | B12: Male | C12: IH Cantabria | D12: Spain | E12: Yes | F12: No | G12: Geohazard; Marine Sciences; Tsunami | I12: unknown | J12: 45888.518 | K12: Geo-INQUIRE mailinglist | L12: SDL_Trg | O12: Turkey | P12: =COUNTIF(D$2:D$120,O12) -> 1 | Q12: {=XLOOKUP(O12,Countries!A$2:A$98,Countries!B$2:B$98,"tbd",0)} -> associated countries
A13: 19 | B13: Male | C13: NGI | D13: Norway | E13: No | F13: No | G13: Geohazard; Seismology; Solid Earth; Tsunami | I13: unknown | J13: 45879.949 | K13: Geo-INQUIRE mailinglist | L13: SDL_Trg
A14: 10 | B14: Female | C14: Geosciences Barcelona -CSIC | D14: Spain | E14: Yes | F14: No | G14: Computer Science; Geohazard; Volcanology | I14: unknown | J14: 45877.443 | K14: Other | L14: SDL_Trg | P14: =SUM(P2:P12) -> 39
A15: 40 | B15: Female | C15: CSIC | D15: Spain | E15: Yes | F15: No | G15: Atmospheric Physics; Computer Science; Engineering; Geohazard | I15: unknown | J15: 45909.424 | K15: Geo-INQUIRE mailinglist | L15: SDL_Trg
A16: 7 | B16: Male | C16: GFZ Helmholtz Centre for Geosciences | D16: Germany | E16: No | F16: No | G16: Engineering | I16: unknown | J16: 45869.464 | K16: Geo-INQUIRE mailinglist | L16: SDL_Trg | P16: 6 | Q16: widening/associated countries
A17: 32 | B17: Male | C17: Jenderal Soedirman University | D17: Indonesia | E17: Yes | F17: No | G17: Environmental Protection; Geohazard; Marine Sciences; Seismology; Tsunami | I17: unknown | J17: 45903.717 | K17: Geo-INQUIRE website | L17: SDL_Trg | P17: 4 | Q17: non-EU
A18: 9 | B18: Female | C18: CINECA | D18: Italy | E18: No | F18: Yes | G18: Computer Science | I18: unknown | J18: 45874.351 | K18: Geo-INQUIRE website | L18: SDL_Trg | P18: 11 | Q18: different countries
A19: 22 | B19: Male | C19: Universidad de Málaga | D19: Spain | E19: No | F19: No | G19: Geohazard; Tsunami | H19: Mathematical modeling and numerical simulation | I19: unknown | J19: 45891.722 | K19: Geo-INQUIRE mailinglist | L19: SDL_Trg | P19: 14 | Q19: different scientific fields
A20: 11 | B20: Female | C20: NGI | D20: Norway | E20: No | F20: No | G20: Solid Earth; Tsunami | I20: unknown | J20: 45877.466 | K20: Other | L20: SDL_Trg
A21: 6 | B21: Male | C21: University of Silesia | D21: Poland | E21: Yes | F21: No | G21: Environmental Protection; Geohazard | I21: unknown | J21: 45868.624 | K21: Geo-INQUIRE website | L21: SDL_Trg
A22: 39 | B22: Female | C22: CSIC | D22: Spain | E22: No | F22: No | G22: Computer Science; Geohazard; Volcanology | I22: unknown | J22: 45909.412 | K22: Geo-INQUIRE mailinglist | L22: SDL_Trg
A23: 4 | B23: Male | C23: EMSO ERIC | D23: Italy | E23: No | F23: No | G23: Marine Sciences | I23: unknown | J23: 45868.542 | K23: Geo-INQUIRE mailinglist | L23: SDL_Trg
A24: 2 | B24: Diverse | C24: Istituto Nazionale di Geofisica e Vulcanologia | D24: Italy | E24: No | F24: No | G24: Computer Science; Volcanology | I24: unknown | J24: 45863.593 | K24: Geo-INQUIRE mailinglist | L24: SDL_Trg
A25: 13 | B25: Female | C25: BSC | D25: Spain | E25: No | F25: No | G25: Geohazard; Seismology | I25: unknown | J25: 45877.618 | K25: Geo-INQUIRE mailinglist | L25: SDL_Trg
A26: 26 | B26: Male | C26: UiB | D26: Norway | E26: No | F26: No | G26: Atmospheric Physics; Geohazard; Marine Sciences | I26: unknown | J26: 45896.596 | K26: Geo-INQUIRE website | L26: SDL_Trg
A27: 25 | B27: Male | C27: University of Málaga | D27: Spain | E27: Yes | F27: No | G27: Computer Science; Marine Sciences; Tsunami | I27: unknown | J27: 45895.472 | K27: Geo-INQUIRE mailinglist | L27: SDL_Trg
A28: 30 | B28: Male | C28: Università degli studi di Salerno | D28: Italy | E28: Yes | F28: No | G28: Seismology; Solid Earth | I28: unknown | J28: 45901.694 | K28: Colleagues | L28: SDL_Trg
A29: 15 | B29: Male | C29: INGV | D29: Italy | E29: No | F29: No | G29: Seismology; Tsunami | I29: unknown | J29: 45877.637 | K29: Geo-INQUIRE mailinglist | L29: SDL_Trg
A30: 23 | B30: Female | C30: Ilia State University | D30: Georgia | E30: Yes | F30: No | G30: Geohazard; Seismology | I30: unknown | J30: 45894.693 | K30: Geo-INQUIRE website | L30: SDL_Trg
A31: 35 | B31: Female | C31: INGV | D31: Italy | E31: No | F31: No | G31: Geohazard; Solid Earth; Volcanology | I31: unknown | J31: 45905.629 | K31: Geo-INQUIRE mailinglist | L31: SDL_Trg
A32: 3 | B32: Female | C32: mohammadia school of enginners (EMI) | D32: Morocco | E32: Yes | F32: No | G32: Engineering; Other | H32: Mining and Geology | I32: unknown | J32: 45866.595 | K32: Geo-INQUIRE website | L32: SDL_Trg
A33: 21 | B33: Male | C33: UNINA (University of Naples Federico II) | D33: Italy | E33: Yes | F33: No | G33: Geohazard; Seismology; Tsunami | I33: unknown | J33: 45889.569 | K33: Geo-INQUIRE website | L33: SDL_Trg
A34: 36 | B34: Female | C34: Istanbul University-Cerrahpasa | D34: Turkey | E34: Yes | F34: No | G34: Seismology | I34: unknown | J34: 45905.997 | K34: Geo-INQUIRE website | L34: SDL_Trg
A35: 33 | B35: Male | C35: Istituto Nazionale di Geofisica e Vulcanologia | D35: Italy | E35: No | F35: No | G35: Tsunami | I35: unknown | J35: 45904.559 | K35: Colleagues | L35: SDL_Trg
A36: 31 | B36: Male | C36: Cineca | D36: Italy | E36: No | F36: Yes | G36: Computer Science; Other | I36: unknown | J36: 45902.728 | K36: Colleagues | L36: SDL_Trg
A37: 24 | B37: Female | C37: INGV | D37: Italy | E37: No | F37: No | G37: Geohazard; Tsunami | I37: unknown | J37: 45895.406 | K37: Geo-INQUIRE mailinglist | L37: SDL_Trg
A38: 27 | B38: Male | C38: PERFACCT GmbH | D38: Germany | E38: No | F38: Yes | G38: Computer Science | H38: Software Engineering | I38: unknown | J38: 45897.476 | K38: Colleagues | L38: SDL_Trg
A39: 29 | B39: Female | C39: Barcelona Supercomputing Center | D39: Spain | E39: No | F39: No | G39: Geohazard; Seismology; Tsunami | I39: unknown | J39: 45901.69 | K39: Geo-INQUIRE mailinglist | L39: SDL_Trg
A40: 5 | B40: Male | C40: GFZ Helmholtz Centre for Geosciences, Potsdam, Germany | D40: Germany | E40: Yes | F40: No | G40: Geohazard | I40: unknown | J40: 45868.549 | K40: Colleagues | L40: SDL_Trg

Sheet VIS_WS
A1: ID | B1: Gender | C1: Affiliation | D1: Country of Affiliation | E1: Are you an Early Career Scientist? | F1: Do you work in industry, a Start-up or Small and Medium Enterprise? | G1: What is your scientific expertise? (Multiple Choice) | H1: Scientific expertise - Other(s): | I1: Have you been familiar with any of the involved Geo-INQUIRE services before? | J1: Registration date | K1: How did you hear about this event? | L1: Tags | O1: Countries | P1: No_Countries | Q1: Category
A2: 22 | B2: Male | C2: University of Florence | D2: Italy | E2: Yes | F2: No | G2: Geohazard; Seismology | I2: Yes | J2: 45890.758 | K2: Colleagues | L2: VIS_WS | O2: {=UNIQUE(D2:D187)} -> Italy | P2: =COUNTIF(D$2:D$120,O2) -> 13 | Q2: {=XLOOKUP(O2,Countries!A$2:A$98,Countries!B$2:B$98,"tbd",0)} -> Europe
A3: 12 | B3: Male | C3: INGV-OE | D3: Italy | E3: No | F3: No | G3: Computer Science; Seismology; Solid Earth; Volcanology | I3: No | J3: 45814.49 | K3: Colleagues | L3: VIS_WS | O3: Portugal | P3: =COUNTIF(D$2:D$120,O3) -> 2 | Q3: {=XLOOKUP(O3,Countries!A$2:A$98,Countries!B$2:B$98,"tbd",0)} -> widening countries
A4: 11 | B4: Female | C4: INGV Osservatorio Etneo | D4: Italy | E4: Yes | F4: No | G4: Computer Science; Geohazard; Solid Earth; Volcanology | H4: Volcano monitoring, Geophysics, Geodesy, Numerical modeling | I4: No | J4: 45813.656 | K4: Geo-INQUIRE mailinglist | L4: VIS_WS | O4: Hungary | P4: =COUNTIF(D$2:D$120,O4) -> 1 | Q4: {=XLOOKUP(O4,Countries!A$2:A$98,Countries!B$2:B$98,"tbd",0)} -> widening countries
A5: 10 | B5: Male | C5: Politecnico di Milano - polimi | D5: Italy | E5: Yes | F5: No | G5: Environmental Protection; Engineering; Geohazard; Seismology; Volcanology | I5: Yes | J5: 45811.708 | K5: Geo-INQUIRE linkedin | L5: VIS_WS
A6: 13 | B6: Female | C6: L'istituto Nazionale di Geofisica e Vulcanologia (Sezione di Pisa) | D6: Italy | E6: Yes | F6: No | G6: Computer Science; Volcanology | I6: No | J6: 45817.666 | K6: Colleagues | L6: VIS_WS
A7: 4 | B7: Female | C7: Istituto Nazionale di Geofisica e Vulcanologia, Osservatorio Etneo - Sezione di Catania | D7: Italy | E7: Yes | F7: No | G7: Seismology; Solid Earth; Volcanology | I7: No | J7: 45798.433 | K7: Colleagues | L7: VIS_WS
A8: 21 | B8: Female | C8: Politecnico di Milano | D8: Italy | E8: Yes | F8: Yes | G8: Engineering | I8: No | J8: 45878.906 | K8: Geo-INQUIRE linkedin | L8: VIS_WS
A9: 15 | B9: Male | C9: Institute of Geophysics, UNAM, Mexico City, Mexico - Dep. of Earth Science, University of Torino, Italy. | D9: Italy | E9: Yes | F9: No | G9: Geohazard; Volcanology; Other | H9: Thermal satellite remote sensing of volcanic activity; multiparametric volcano monitoring; applied geophysics in volcanological research | I9: No | J9: 45817.848 | K9: Newsletter or website of the Ris (EPOS, ERIC, etc.) | L9: VIS_WS
A10: 3 | B10: Male | C10: Instituto de Investigação em Vulcanologia e Avaliação de Riscos (IVAR) - Universidade dos Açores | D10: Portugal | E10: No | F10: No | G10: Atmospheric Physics; Geohazard; Seismology; Solid Earth; Volcanology; Other | H10: Infrasound | I10: No | J10: 45791.829 | K10: Colleagues | L10: VIS_WS | P10: 3 | Q10: widening/associated countries
A11: 6 | B11: Male | C11: Istituto Nazionale di Geofisica e Vulcanologia - Osservatorio Etneo | D11: Italy | E11: Yes | F11: No | G11: Computer Science; Seismology; Solid Earth; Volcanology; Other | H11: Volcanic early warning systems, short-term eruption forecasting, development of threshold-based and AI-integrated detection algorithms, monitoring of explosive activity at Stromboli and Etna, ground deformation analysis, volcanic and regional seismology, geophysical data interpretation, signal processing of seismic and acoustic data, multiparametric monitoring, time series analysis, statistical evaluation of early detection system vulnerabilities, machine learning applications in geophysics, classification of volcanic explosions using geophysical parameters, real-time monitoring system development, microseism analysis and ocean-seismic coupling, regression and clustering techniques, array tecniques for seismic and infrasound signals, seismic and infrasound sensors installation, data acquisition and management, structured and object-oriented programming in Matlab and Python, applied statistics and algebra for geophysical interpretation, academic tutoring and teaching support. | I11: No | J11: 45804.505 | K11: Colleagues | L11: VIS_WS | P11: 0 | Q11: non-EU
A12: 5 | B12: Female | C12: University of Napoli Federico II | D12: Italy | E12: Yes | F12: No | G12: Geohazard; Seismology; Volcanology | I12: No | J12: 45804.423 | K12: Colleagues | L12: VIS_WS | P12: 3 | Q12: different countries
A13: 20 | B13: Female | C13: Università degli Studi di Firenze | D13: Italy | E13: Yes | F13: No | G13: Geohazard | I13: Yes | J13: 45869.574 | K13: Colleagues | L13: VIS_WS | P13: 14 | Q13: different scientific fields
A14: 16 | B14: Female | C14: Dipartimento Scienze della Terra Università di Pisa | D14: Italy | E14: Yes | F14: No | G14: Geohazard; Marine Sciences; Seismology; Solid Earth | I14: No | J14: 45818.615 | K14: Colleagues | L14: VIS_WS
A15: 7 | B15: Male | C15: Eötvös Loránd University | D15: Hungary | E15: Yes | F15: No | G15: Atmospheric Physics; Computer Science; Seismology | I15: No | J15: 45806.909 | K15: Colleagues | L15: VIS_WS
A16: 2 | B16: Female | C16: Instituto de Investigação em Vulcanologia e Avaliação de Riscos (IVAR) - Universidade dos Açores | D16: Portugal | E16: Yes | F16: No | G16: Geohazard; Seismology; Volcanology | I16: No | J16: 45791.829 | K16: Colleagues | L16: VIS_WS
A17: 9 | B17: Female | C17: Università di Catania | D17: Italy | E17: Yes | F17: No | G17: Computer Science; Geohazard; Seismology; Volcanology; Other | H17: geochemistry | I17: Yes | J17: 45808.852 | K17: Geo-INQUIRE linkedin | L17: VIS_WS

Sheet EPOS Platform Trg - Online (12-
A1: ID | B1: Gender | C1: Affiliation | D1: Country of Affiliation | E1: Are you an Early Career Scientist? | F1: Do you work in industry, a Start-up or Small and Medium Enterprise? | G1: What is your scientific expertise? (Multiple Choice) | H1: Scientific expertise - Other(s): | I1: Have you used this installation (EPOS) before? | J1: Registration date | K1: Registration state | L1: Tags | N1: Countries | O1: No_Countries | P1: Category | Q1: Color
A2: 1 | B2: Male | C2: EPOS ERIC | D2: Italy | E2: No | F2: Uknown | G2: Data scientist, Software developer | I2: Yes | J2: 45728.461 | K2: Completed | L2: EPOSTrg_Online25 | N2: France | O2: =COUNTIF(D2:D26,"France") -> 2 | P2: Europe
A3: 2 | B3: Male | D3: Spain | E3: No | F3: Uknown | G3: Seismology | I3: No | J3: 45728.462 | K3: Completed | L3: EPOSTrg_Online25 | N3: Italy | O3: =COUNTIF(D2:D26,"Italy") -> 2 | P3: Europe
A4: 3 | B4: Female | C4: Luleå University of Technology | D4: Sweden | E4: No | F4: Uknown | G4: Geology, Data scientist | I4: No | J4: 45728.465 | K4: Completed | L4: EPOSTrg_Online25 | N4: Sweden | O4: =COUNTIF(D2:D26,"Sweden")+COUNTIF(D2:D26,"Sverige") -> 3 | P4: Europe
A5: 4 | B5: Male | D5: Spain | E5: Yes | F5: Uknown | G5: Geohazards, IT Architect | I5: No | J5: 45728.466 | K5: Completed | L5: EPOSTrg_Online25 | N5: Iceland | O5: =COUNTIF(D2:D26,"Iceland") -> 2 | P5: associated countries
A6: 5 | B6: Female | D6: france | E6: No | F6: Uknown | G6: Seismology | I6: Yes | J6: 45728.467 | K6: Completed | L6: EPOSTrg_Online25 | N6: Spain | O6: =COUNTIF(D2:D26,"Spain") -> 7 | P6: Europe
A7: 6 | B7: Male | C7: Lunds Universitet | D7: Sverige | E7: No | F7: Uknown | G7: Anthropogenic hazard, Geology | I7: No | J7: 45728.467 | K7: Completed | L7: EPOSTrg_Online25 | N7: Norway | O7: =COUNTIF(D2:D26,"Norway") -> 1 | P7: associated countries
A8: 7 | B8: Female | C8: Iceland GeoSurvey | D8: Iceland | E8: Yes | F8: Uknown | G8: Seismology | I8: No | J8: 45728.47 | K8: Completed | L8: EPOSTrg_Online25
A9: 8 | B9: Female | C9: IMO | D9: Iceland | E9: No | F9: Uknown | G9: Geology | I9: Yes | J9: 45728.473 | K9: Completed | L9: EPOSTrg_Online25
A10: 9 | B10: Male | C10: Universitat Politècnica de València | D10: Spain | E10: No | F10: Uknown | G10: Geodesy, Satellite data, Data scientist, Software developer | I10: No | J10: 45728.473 | K10: Completed | L10: EPOSTrg_Online25
A11: 10 | B11: Female | D11: spain | E11: No | F11: Uknown | G11: Multi-scale laboratories | I11: No | J11: 45728.474 | K11: Completed | L11: EPOSTrg_Online25
A12: 11 | B12: Female | C12: University of Granada | D12: Spain | E12: No | F12: Uknown | G12: Volcanology, Geology | I12: No | J12: 45728.477 | K12: Completed | L12: EPOSTrg_Online25
A13: 12 | B13: Female | C13: University of Bergen | D13: Norway | E13: No | F13: Uknown | G13: Geology | I13: Yes | J13: 45728.479 | K13: Completed | L13: EPOSTrg_Online25
A14: 13 | B14: Male | C14: EPOS ERIC | D14: Italy | E14: No | F14: Uknown | G14: IT Specialist | I14: No | J14: 45728.48 | K14: Completed | L14: EPOSTrg_Online25
A15: 14 | B15: Male | C15: Instituto Geográfico Nacional (Spain) and Universidad Politécnica de Madrid | D15: Spain | E15: No | F15: Uknown | G15: Geodesy, Volcanology, Geoelectromagnetism, Tsunami research, Geohazards, Data scientist, Software developer | I15: No | J15: 45728.48 | K15: Completed | L15: EPOSTrg_Online25
A16: 15 | B16: Female | C16: Luleå university of Technology | D16: Sweden | E16: Yes | F16: Uknown | G16: Geology, Data scientist | I16: No | J16: 45728.481 | K16: Completed | L16: EPOSTrg_Online25
A17: 16 | B17: Male | C17: CNRS and Université Clermont Auvergne/OPGC | D17: France | E17: No | F17: Uknown | G17: Volcanology, Satellite data, Geohazards | I17: Yes | J17: 45728.481 | K17: Completed | L17: EPOSTrg_Online25
A18: 17 | B18: Female | C18: University of Alicante | D18: Spain | E18: No | F18: Uknown | G18: Geohazards | I18: No | J18: 45728.503 | K18: Completed | L18: EPOSTrg_Online25
O25: 3 | P25: associated countries
O26: 14 | P26: Europe
O27: 0 | P27: widening countries
O28: 0 | P28: non-EU

Sheet EPOS Platform Trg - EGU25
A1: ID | B1: Gender | C1: Affiliation | D1: Country of Affiliation | E1: Are you an Early Career Scientist? | F1: Do you work in industry, a Start-up or Small and Medium Enterprise? | G1: What is your scientific expertise? (Multiple Choice) | H1: Scientific expertise - Other(s): | I1: Have you used this installation (EPOS) before? | J1: Registration date | K1: Registration state | L1: Tags | N1: Countries | O1: No_Countries | P1: Category | Q1: Color
A2: 1 | B2: Female | C2: University of Iceland, Natural Science Institute of Iceland | D2: Iceland | E2: No | F2: Uknown | G2: Volcanology, Geology, Geohazards | I2: Yes | J2: 45777.628 | K2: Completed | L2: EPOSTrg_EGU25 | N2: Iceland | O2: 1 | P2: associated countries
A3: 2 | B3: Female | D3: Norway | E3: Yes | F3: Uknown | G3: Geology, Earthquake engineering | I3: No | J3: 45777.629 | K3: Completed | L3: EPOSTrg_EGU25 | N3: Norway | O3: 1 | P3: associated countries
A4: 3 | B4: Male | C4: Sapienza University of Rome | D4: Italy | E4: Yes | F4: Uknown | G4: Satellite data, Geology, Geohazards | I4: No | J4: 45777.631 | K4: Completed | L4: EPOSTrg_EGU25 | N4: Italy | O4: 3 | P4: Europe
A5: 4 | B5: Male | C5: University of Naples | D5: Italy | E5: No | F5: Uknown | G5: Seismology | I5: No | J5: 45777.634 | K5: Completed | L5: EPOSTrg_EGU25 | N5: Germany, France | O5: 1 | P5: Europe
A6: 5 | B6: two people | C6: TU Munich, university of Toulouse | D6: Germany, France | E6: No | F6: Uknown | G6: Geology, geomechanics | I6: No | J6: 45777.639 | K6: Completed | L6: EPOSTrg_EGU25 | N6: Croatia | O6: 1 | P6: widening countries
A7: 6 | B7: Female | C7: EGI Foundation | D7: Netherlands | E7: No | F7: Uknown | G7: IT Specialist, Technical staff | I7: Yes | J7: 45777.647 | K7: Completed | L7: EPOSTrg_EGU25 | N7: Netherlands | O7: 1 | P7: Europe
A8: 7 | B8: Female | C8: University | D8: Italy | E8: Yes | F8: Uknown | G8: Seismology, Geodesy, Volcanology, Satellite data | I8: Yes | J8: 45777.653 | K8: Completed | L8: EPOSTrg_EGU25
A9: 8 | B9: Female | C9: University of Zagreb | D9: Croatia | E9: Yes | F9: Uknown | G9: IT Specialist | I9: No | J9: 45777.655 | K9: Completed | L9: EPOSTrg_EGU25
O13: 2 | P13: associated countries
O14: 5 | P14: Europe
O15: 1 | P15: widening countries
O16: 0 | P16: non-EU

Sheet EPOS Platform Trg - Clermont-Fe
A1: ID | B1: Gender | C1: Affiliation | D1: Country of Affiliation | E1: Are you an Early Career Scientist? | F1: Do you work in industry, a Start-up or Small and Medium Enterprise? | G1: What is your scientific expertise? (Multiple Choice) | H1: Scientific expertise - Other(s): | I1: Have you used this installation (EPOS) before? | J1: Registration date | K1: Registration state | L1: Tags | N1: Countries | O1: No_Countries | P1: Category | Q1: Color
A2: 1 | B2: Male | C2: Laboratoire Magmas et Volcans | D2: France | E2: No | F2: No | G2: Seismology, Volcanology, Geohazards, acoustics | I2: No | J2: 45791.428 | K2: Complete | L2: EPOSTrg_France | N2: France | O2: =COUNTIF(D2:D26,"France") -> 8 | P2: Europe
A3: 2 | B3: Male | C3: OPGC | D3: France | E3: Yes | F3: No | G3: Volcanology, Multi-scale laboratories | I3: Yes | J3: 45791.429 | K3: Complete | L3: EPOSTrg_France
A4: 3 | B4: Male | C4: University Clermont Auvergne and CNRS | D4: France | E4: No | F4: No | G4: Volcanology, Satellite data | I4: Yes | J4: 45791.431 | K4: Complete | L4: EPOSTrg_France
A5: 4 | B5: Female | C5: Université Clermont Auvergne - Laboratoire Magmas et Volcans | D5: France | E5: Yes | F5: No | G5: Seismology, Volcanology, Geology, Tsunami research | I5: No | J5: 45791.434 | K5: Complete | L5: EPOSTrg_France
A6: 5 | B6: Male | D6: France | E6: No | F6: No | G6: Volcanology | I6: Yes | J6: 45791.434 | K6: Complete | L6: EPOSTrg_France
A7: 6 | B7: Female | C7: LMV/OPGC | D7: France | E7: No | F7: No | G7: Volcanology, Geohazards, Marine Geosciences | I7: No | J7: 45791.442 | K7: Complete | L7: EPOSTrg_France
A8: 7 | B8: Female | C8: LMV-OPGC | D8: France | E8: No | F8: No | G8: Volcanology, Geology | I8: No | J8: 45791.443 | K8: Complete | L8: EPOSTrg_France
A9: 8 | B9: Female | C9: Laboratoire Magmas et Volcans | D9: France | E9: Yes | F9: No | G9: Volcanology, Geology | I9: No | J9: 45791.444 | K9: Complete | L9: EPOSTrg_France
O25: 0 | P25: associated countries
O26: 8 | P26: Europe
O27: 0 | P27: widening countries
O28: 0 | P28: non-EU

Sheet EPOS Platform Trg - S4E
A1: ID | B1: Gender | C1: Affiliation | D1: Country of Affiliation | E1: Are you an Early Career Scientist? | F1: Do you work in industry, a Start-up or Small and Medium Enterprise? | G1: What is your scientific expertise? (Multiple Choice) | H1: Scientific expertise - Other(s): | I1: Have you used this installation (EPOS) before? | J1: Registration date | K1: Registration state | L1: Tags | N1: Countries | O1: No_Countries | P1: Category | Q1: Color
A2: 1 | B2: Female | C2: University of Granada | D2: Spain | E2: Yes | F2: No | G2: Geology | I2: No | J2: 45800.448 | K2: Complete | L2: EPOSTrg_S4E | N2: France | O2: =COUNTIF(D2:D26,"France") -> 2 | P2: Europe
A3: 2 | B3: Male | C3: EMSC | D3: France | E3: No | F3: No | G3: Seismology, Volcanology | I3: Yes | J3: 45800.45 | K3: Complete | L3: EPOSTrg_S4E | N3: Spain | O3: 4 | P3: Europe
A4: 3 | B4: Female | C4: Sorbonne University | D4: France | E4: No | F4: No | G4: Data scientist | I4: No | J4: 45800.46 | K4: Complete | L4: EPOSTrg_S4E
A5: 4 | B5: Male | C5: CSIC | D5: Spain | E5: Yes | F5: No | G5: Volcanology, Geology | I5: No | J5: 45800.462 | K5: Complete | L5: EPOSTrg_S4E
A6: 5 | B6: Male | C6: Instituto Andaluz de Ciencias de la Tierra | D6: Spain | E6: Yes | F6: No | G6: Geology, Data scientist | I6: No | J6: 45800.463 | K6: Complete | L6: EPOSTrg_S4E
A7: 6 | B7: Female | C7: CSIC | D7: Spain | E7: Yes | F7: No | G7: Geology | I7: No | J7: 45800.463 | K7: Complete | L7: EPOSTrg_S4E
O25: 0 | P25: associated countries
O26: 6 | P26: Europe
O27: 0 | P27: widening countries
O28: 0 | P28: non-EU

Sheet EPOS Platform Trg - Summer Scho
A1: ID | B1: Gender | C1: Affiliation | D1: Country of Affiliation | E1: Are you an Early Career Scientist? | F1: Do you work in industry, a Start-up or Small and Medium Enterprise? | G1: What is your scientific expertise? (Multiple Choice) | H1: Scientific expertise - Other(s): | I1: Have you used this installation (EPOS) before? | J1: Registration date | K1: Registration state | L1: Tags | N1: Countries | O1: No_Countries | P1: Category | Q1: Color
A2: 1 | B2: Female | C2: CNRS | D2: France | E2: No | F2: No | G2: Seismology | I2: Yes | J2: 45833.623 | K2: Complete | L2: EPOS_SummerSchool | N2: France | O2: =COUNTIF(D2:D26,"France") -> 2 | P2: Europe
A3: 2 | B3: Female | C3: GNS Science | D3: New Zealand | E3: No | F3: No | G3: Geology, Geohazards | I3: No | J3: 45833.623 | K3: Complete | L3: EPOS_SummerSchool | N3: New Zealand | O3: =COUNTIF(D2:D26,"New Zealand") -> 2 | P3: non-EU
A4: 3 | B4: Female | C4: University of Iceland | D4: Iceland | E4: Yes | F4: No | G4: Volcanology, Geology, Geohazards | I4: No | J4: 45833.627 | K4: Complete | L4: EPOS_SummerSchool | N4: Iceland | O4: =COUNTIF(D2:D26,"Iceland") -> 1 | P4: associated countries
A5: 4 | B5: Female | C5: National Space Research and Development AGency | D5: Nigeria | E5: Yes | F5: No | G5: Satellite data, Geology, Geohazards, Data scientist | I5: No | J5: 45833.627 | K5: Complete | L5: EPOS_SummerSchool | N5: Nigeria | O5: =COUNTIF(D2:D26,"Nigeria") -> 1 | P5: non-EU
A6: 5 | B6: Female | C6: NIGGG-BAS | D6: Bulgaria | E6: No | F6: No | G6: Geoelectromagnetism, Geology, Geohazards | I6: Yes | J6: 45833.628 | K6: Complete | L6: EPOS_SummerSchool | N6: Bulgaria | O6: =COUNTIF(D2:D26,"Bulgaria") -> 1 | P6: widening countries
A7: 6 | B7: Female | C7: PhD in Seismology | D7: Turkey | E7: No | F7: No | G7: Seismology, Earthquake engineering | I7: No | J7: 45833.628 | K7: Complete | L7: EPOS_SummerSchool | N7: Turkey | O7: =COUNTIF(D2:D26,"Turkey") -> 1 | P7: non-EU
A8: 7 | B8: Female | C8: CSIC | D8: Spain | E8: No | F8: No | G8: Volcanology | I8: Yes | J8: 45833.628 | K8: Complete | L8: EPOS_SummerSchool | N8: Spain | O8: =COUNTIF(D2:D26,"Spain") -> 4 | P8: Europe
A9: 8 | B9: Male | C9: emsc | D9: FRANCE | E9: No | F9: No | G9: Seismology | I9: Yes | J9: 45833.629 | K9: Complete | L9: EPOS_SummerSchool | N9: North Macedonia | O9: =COUNTIF(D2:D26,"North Macedonia") -> 1 | P9: non-EU
A10: 9 | B10: Male | C10: Ss. Ciryl and Methodius University Skopje | D10: North Macedonia | E10: No | F10: No | G10: Seismology | I10: No | J10: 45833.629 | K10: Complete | L10: EPOS_SummerSchool | N10: Sweden | O10: =COUNTIF(D2:D26,"Sweden") -> 2 | P10: Europe
A11: 10 | B11: Female | C11: Institut de Ciències del Mar - CSIC | D11: Spain | E11: No | F11: No | G11: Geology | I11: No | J11: 45833.63 | K11: Complete | L11: EPOS_SummerSchool | N11: Slovakia | O11: =COUNTIF(D2:D26,"Slovakia") -> 1 | P11: widening countries
A12: 11 | B12: Male | C12: Lulea University of Technology | D12: Sweden | E12: Yes | F12: No | G12: Geoelectromagnetism | I12: Yes | J12: 45833.631 | K12: Complete | L12: EPOS_SummerSchool | N12: Romania | O12: =COUNTIF(D2:D26,"Romania")+COUNTIF(D2:D26,"NIEP") -> 2 | P12: Europe
A13: 12 | B13: Female | C13: Slovak Academy of Sciences | D13: Slovakia | E13: Yes | F13: No | G13: Satellite data, gravimetry, applied geophysics | I13: No | J13: 45833.631 | K13: Complete | L13: EPOS_SummerSchool | N13: Greece | O13: =COUNTIF(D2:D26,"Greece") -> 1 | P13: widening countries
A14: 13 | B14: Female | C14: Uppsala University | D14: Sweden | E14: Yes | F14: No | G14: Geology | I14: No | J14: 45833.631 | K14: Complete | L14: EPOS_SummerSchool | N14: Poland | O14: =COUNTIF(D2:D26,"Poland") -> 2 | P14: widening countries
A15: 14 | B15: Female | C15: National Institute for Earth Physics | D15: Romania | E15: Yes | F15: No | G15: Seismology | I15: Yes | J15: 45833.632 | K15: Complete | L15: EPOS_SummerSchool | N15: Italy | O15: =COUNTIF(D2:D26,"Italy") -> 3 | P15: Europe
A16: 15 | B16: Female | C16: Aristotle University of Thessaloniki | D16: Greece | E16: No | F16: No | G16: Seismology, Geodesy, Near-fault observations, Satellite data, Geology, Geohazards | I16: Yes | J16: 45833.632 | K16: Complete | L16: EPOS_SummerSchool | N16: Australia | O16: =COUNTIF(D2:D26,"Australia") -> 1 | P16: non-EU
A17: 16 | B17: Female | C17: Institute of Geophysics, Polish Academy of Sciences | D17: Poland | E17: Yes | F17: No | G17: Seismology, Anthropogenic hazard, Technical staff | I17: Yes | J17: 45833.632 | K17: Complete | L17: EPOS_SummerSchool
A18: 17 | B18: Male | C18: Researcher | D18: NIEP | E18: Yes | F18: No | G18: Seismology, Geoelectromagnetism, Geology | I18: No | J18: 45833.634 | K18: Complete | L18: EPOS_SummerSchool
A19: 18 | B19: Male | C19: GNS Science / GeoNet | D19: New Zealand | E19: No | F19: No | G19: Seismology, Geohazards, Data scientist | I19: No | J19: 45833.639 | K19: Complete | L19: EPOS_SummerSchool
A20: 19 | B20: Female | C20: Intituto Geográfico Nacional | D20: Spain | E20: No | F20: No | G20: Volcanology | I20: Yes | J20: 45833.64 | K20: Complete | L20: EPOS_SummerSchool
A21: 20 | B21: Female | C21: OGS | D21: Italy | E21: No | F21: No | G21: Seismology | I21: No | J21: 45833.64 | K21: Complete | L21: EPOS_SummerSchool
A22: 21 | B22: Male | C22: Sapienza University of Rome | D22: Italy | E22: Yes | F22: No | G22: Satellite data, Geohazards, Data scientist | I22: No | J22: 45833.641 | K22: Complete | L22: EPOS_SummerSchool
A23: 22 | B23: Female | C23: Institute of Geodesy and Cartography | D23: Poland | E23: Yes | F23: No | G23: Geodesy | I23: No | J23: 45833.641 | K23: Complete | L23: EPOS_SummerSchool
A24: 23 | B24: Male | C24: OGS | D24: Italy | E24: No | F24: No | G24: Seismology, Multi-scale laboratories, Tsunami research, Earthquake engineering, Geohazards | I24: Yes | J24: 45833.641 | K24: Complete | L24: EPOS_SummerSchool
A25: 24 | B25: Male | C25: Curtin University | D25: Australia | E25: No | F25: No | G25: Geology, Multi-scale laboratories, Data scientist | I25: No | J25: 45833.643 | K25: Complete | L25: EPOS_SummerSchool | O25: 1 | P25: associated countries
A26: 25 | B26: Female | C26: Rey Juan Carlos University | D26: Spain | E26: No | F26: No | G26: Geodesy, Volcanology, Satellite data, Geology, Multi-scale laboratories, Geohazards, Data scientist, Software developer, Technical staff | I26: No | J26: 45833.646 | K26: Complete | L26: EPOS_SummerSchool | O26: 13 | P26: Europe
O27: 5 | P27: widening countries
O28: 6 | P28: non-EU

Sheet EPOS Platform Trg - Spain
A1: ID | B1: Gender | C1: Affiliation | D1: Country of Affiliation | E1: Are you an Early Career Scientist? | F1: Do you work in industry, a Start-up or Small and Medium Enterprise? | G1: What is your scientific expertise? (Multiple Choice) | H1: Scientific expertise - Other(s): | I1: Have you used this installation (EPOS) before? | J1: Registration date | K1: Registration state | L1: Tags | N1: Countries | O1: No_Countries | P1: Category | Q1: Color
A2: 1 | B2: Female | D2: Spain | E2: No | F2: No | G2: Geoelectromagnetism | I2: Yes | J2: 45853.7 | L2: EPOS_Trg_Spain | N2: Spain | O2: =COUNTIF(D2:D26,"Spain") -> 24 | P2: Europe
A3: 2 | B3: Male | D3: Spain | E3: No | F3: No | G3: Geology, Multi-scale laboratories | I3: Yes | J3: 45853.701 | L3: EPOS_Trg_Spain | N3: Portugal | O3: =COUNTIF(D3:D27,"Portugal") -> 1
A4: 3 | B4: Male | D4: Spain | E4: No | F4: No | G4: Geology | I4: No | J4: 45853.701 | L4: EPOS_Trg_Spain
A5: 4 | B5: Female | D5: Spain | E5: No | F5: No | G5: Near-fault observations, Geology, Tsunami research, Geohazards | I5: Yes | J5: 45853.707 | L5: EPOS_Trg_Spain
A6: 5 | B6: Female | D6: Spain | E6: Yes | F6: No | G6: Geology | I6: Yes | J6: 45853.708 | L6: EPOS_Trg_Spain
A7: 6 | B7: Male | D7: Spain | E7: Yes | F7: No | G7: Geology, Geological heritage | I7: No | J7: 45853.708 | L7: EPOS_Trg_Spain
A8: 7 | B8: Female | C8: CSIC | D8: Spain | E8: No | F8: No | G8: Near-fault observations, Geology, Tsunami research, Geohazards | I8: No | J8: 45853.671 | L8: EPOS_Trg_Spain
A9: 8 | B9: Female | C9: University of Barcelona | D9: Spain | E9: No | F9: No | G9: Multi-scale laboratories | I9: No | J9: 45853.671 | L9: EPOS_Trg_Spain
A10: 9 | B10: Male | C10: Universitat de Barcelona | D10: Spain | E10: No | F10: No | G10: Geoelectromagnetism | I10: No | J10: 45853.672 | L10: EPOS_Trg_Spain
A11: 10 | B11: Female | C11: Geoscience Barcelona (Geo3BCN) | D11: Spain | E11: No | F11: No | G11: Geology | I11: No | J11: 45853.673 | L11: EPOS_Trg_Spain
A12: 11 | B12: Male | D12: Spain | E12: No | F12: No | G12: Seismology, Geodesy, Volcanology, Satellite data, Geology, Tsunami research, Earthquake engineering, Geohazards | I12: No | J12: 45853.675 | L12: EPOS_Trg_Spain
A13: 12 | B13: Male | C13: PhD student at ICM, CSIC | D13: Spain | E13: Yes | F13: No | G13: Geology | I13: No | J13: 45853.683 | L13: EPOS_Trg_Spain
A14: 13 | B14: Female | C14: University of Minho | D14: Portugal | E14: Yes | F14: No | G14: Geology, Geological heritage | I14: No | J14: 45853.693 | L14: EPOS_Trg_Spain
A15: 14 | B15: Male | C15: UCM-CSIC | D15: Spain | E15: Yes | F15: No | G15: Volcanology, Geoelectromagnetism | I15: No | J15: 45855.722 | L15: EPOS_Trg_Spain
A16: 15 | B16: Female | C16: Complutense University of Madrid | D16: Spain | E16: Yes | F16: No | G16: Seismology, Anthropogenic hazard | I16: Yes | J16: 45855.728 | L16: EPOS_Trg_Spain
A17: 16 | B17: Male | C17: Instituto Geográfico Nacional | D17: Spain | E17: No | F17: No | G17: Seismology, Volcanology, Geology | I17: No | J17: 45855.732 | L17: EPOS_Trg_Spain
A18: 17 | B18: Female | C18: IEO | D18: spain | E18: Yes | F18: No | G18: Data scientist | I18: No | J18: 45855.733 | L18: EPOS_Trg_Spain
A19: 18 | B19: Female | C19: IGN | D19: Spain | E19: Yes | F19: No | G19: Seismology, Volcanology, Oceanology | I19: No | J19: 45855.733 | L19: EPOS_Trg_Spain
A20: 19 | B20: Female | C20: CSIC | D20: Spain | E20: No | F20: No | G20: Manager | I20: No | J20: 45855.736 | L20: EPOS_Trg_Spain
A21: 20 | B21: Female | D21: Spain | E21: No | F21: No | G21: Seismology | I21: No | J21: 45855.738 | L21: EPOS_Trg_Spain
A22: 21 | B22: Female | C22: CSIC-INIA | D22: Spain | E22: No | F22: No | G22: Data scientist | I22: No | J22: 45855.738 | L22: EPOS_Trg_Spain
A23: 22 | B23: Male | C23: Univ Complutense | D23: Spain | E23: Yes | F23: No | G23: Volcanology, Geology | I23: Yes | J23: 45855.739 | L23: EPOS_Trg_Spain
A24: 23 | B24: Female | C24: Universidad Rey Juan Carlos | D24: Spain | E24: Yes | F24: No | G24: Geodesy, Volcanology, Geology, Multi-scale laboratories, Geohazards, Data scientist | I24: Yes | J24: 45855.74 | L24: EPOS_Trg_Spain
A25: 24 | B25: Male | C25: Instituto Geográfico Nacioal & Universidad Politécnica de Madrid | D25: Spain | E25: No | F25: No | G25: Geodesy, Volcanology, Tsunami research, Geohazards, Data scientist, Software developer | I25: Yes | J25: 45855.741 | L25: EPOS_Trg_Spain
A26: 25 | B26: Male | C26: ign | D26: spain | E26: No | F26: No | G26: Volcanology | I26: Yes | J26: 45855.742 | L26: EPOS_Trg_Spain | O26: 1 | P26: Europe
A27: 26 | B27: Female | C27: IGN | D27: Spain | E27: No | F27: No | G27: Seismology, Volcanology | I27: Yes | J27: 45855.743 | L27: EPOS_Trg_Spain | O27: 1 | P27: widening countries

Sheet EPOS Platform Trg - CZ
A1: ID | B1: Gender | C1: Affiliation | D1: Country of Affiliation | E1: Are you an Early Career Scientist? | F1: Do you work in industry, a Start-up or Small and Medium Enterprise? | G1: What is your scientific expertise? (Multiple Choice) | H1: Scientific expertise - Other(s): | I1: Have you used this installation (EPOS) before? | J1: Registration date | K1: Registration state | L1: Tags | N1: Countries | O1: No_Countries | P1: Category | Q1: Color
A2: 1 | B2: Male | C2: BRGM | D2: France | E2: No | F2: No | G2: Geology, IT Specialist | I2: Yes | J2: 45909.62 | L2: EPOS_Trg_CZ | N2: France | O2: =COUNTIF(D2:D26,"France") -> 1 | P2: Europe
A3: 2 | B3: Male | C3: GFU-CAS | D3: Czechia | E3: No | F3: No | G3: Volcanology, Geoelectromagnetism, Data scientist | I3: Yes | J3: 45909.625 | L3: EPOS_Trg_CZ | N3: Czechia | O3: 4 | P3: Europe
A4: 3 | B4: Male | C4: IG CAS CZ | D4: Czechia | E4: Yes | F4: No | G4: Seismology | I4: No | J4: 45909.627 | L4: EPOS_Trg_CZ
A5: 4 | B5: Male | C5: seismological service | D5: Czechia | E5: No | F5: No | G5: Seismology | I5: Yes | J5: 45909.632 | L5: EPOS_Trg_CZ
A6: 5 | B6: Female | C6: Institute of Geophysics, Czech Academy of Sciences | D6: Czechia | E6: Yes | F6: No | G6: gravimetry, density modelling | I6: No | J6: 45909.633 | L6: EPOS_Trg_CZ
A7: 6 | B7: Male | C7: IRSM CAS | D7: Czechia | E7: No | F7: No | G7: Near-fault observations, Geology, Geohazards, Data scientist, geomorphology, GIS | I7: No | J7: 45909.638 | L7: EPOS_Trg_CZ
A8: 7 | B8: Male | C8: VUGTK, v.v.i. | D8: Czechia | E8: No | F8: No | G8: Geodesy | I8: Yes | J8: 45909.654 | L8: EPOS_Trg_CZ
O25: 0 | P25: associated countries
O26: 6 | P26: Europe
O27: 0 | P27: widening countries
O28: 0 | P28: non-EU

Sheet AI_4_Seismology
A1: ID | B1: Gender | C1: Affiliation | D1: Country of Affiliation | E1: Are you an Early Career Scientist? | F1: Do you work in industry, a Start-up or Small and Medium Enterprise? | G1: What is your scientific expertise? (Multiple Choice) | H1: Scientific expertise - Other(s): | I1: Have you been familiar with the FAIR principles before? | J1: Registration date | K1: How did you hear about this event: | L1: Tags | O1: Countries | P1: No_Countries | Q1: Category
D2: Belgium | K2: ai4seismology
C3: Université libre de Bruxelles | D3: Belgium | K3: ai4seismology
D4: Switzerland | K4: ai4seismology
D5: Switzerland | K5: ai4seismology
C6: Swiss Seismological Service (SED), ETH Zurich | D6: Switzerland | K6: ai4seismology
C7: GFZ Potsdam | D7: Germany | K7: ai4seismology
C8: Universität Hamburg, Institut für Geophysik | D8: Germany | K8: ai4seismology
C9: GFZ Helmholtz-Zentrum für Geoforschung | D9: Germany | K9: ai4seismology
C10: ScaDS.AI | D10: Germany | K10: ai4seismology
D11: Germany | K11: ai4seismology
D12: Germany | K12: ai4seismology
D13: Germany | K13: ai4seismology
D14: Germany | K14: ai4seismology
C15: Leipzig University | D15: Germany | K15: ai4seismology
D16: Germany | K16: ai4seismology
C17: University of Helsinki | D17: Finland | K17: ai4seismology
C18: BRGM | D18: France | K18: ai4seismology
C19: BRGM | D19: France | K19: ai4seismology
C20: CNRS ISTerre | D20: France | K20: ai4seismology
C21: Université Grenoble Alpes, ISTerre | D21: France | K21: ai4seismology
D22: France | K22: ai4seismology
C23: CEA | D23: France | K23: ai4seismology
C24: BRGM | D24: France | K24: ai4seismology
D25: Italy | K25: ai4seismology
D26: Italy | K26: ai4seismology
D27: Italy | K27: ai4seismology
D28: Italy | K28: ai4seismology
C29: Sapienza University of Rome | D29: Italy | K29: ai4seismology
D30: Netherlands | K30: ai4seismology
D31: Norway | K31: ai4seismology
C32: King Abdullah University of Science and Technology | D32: Saudi Arabia | K32: ai4seismology
D33: Turkey | K33: ai4seismology

Sheet Quakeworx
A1: ID | B1: Gender | C1: Affiliation (no abbreviations) | D1: Country of Affiliation | E1: ECS | F1: SME | G1: What is your scientific expertise? (Multiple Choice) | H1: Scientific expertise - Other(s): | I1: Have you been familiar with Quakeworx before? | J1: Registration date | K1: How did you hear about this event? | L1: Tags
A2: 6 | B2: Diverse | C2: Virginia Polytechnic Institute and State University | D2: United States | F2: Academic Institution | G2: Energy Transformation/Storage; Engineering; Geohazard; Seismology | H2: Rock Mechanics, Rock Engineering, Rock Testing, Simulation and Modelling | I2: No | J2: Dec 12, 2024, 1:57 PM | K2: Colleagues | L2: Quakeworx
A3: 101 | B3: Male | C3: Universiti Teknologi PETRONAS, Malaysia | D3: Nigeria | F3: No | G3: Seismology; Solid Earth; Other | H3: Geology and Geophysics | I3: No | J3: Dec 19, 2024, 4:14 AM | K3: CRESCENT mailing list | L3: Quakeworx
A4: 64 | B4: Male | C4: Student | D4: Nepal | F4: No | G4: Geohazard; Seismology; Other | H4: Applied Geology | I4: No | J4: Dec 18, 2024, 8:00 AM | K4: Newsletter or Website of Geo-INQUIRE Partner | L4: Quakeworx
A5: 25 | B5: Male | C5: The University of Edinburgh | D5: United Kingdom | F5: No | G5: Seismology | H5: Ground motion simulations, Seismic hazard and risk assessment | I5: No | J5: Dec 13, 2024, 6:29 AM | K5: Colleagues | L5: Quakeworx
A6: 81 | B6: Male | C6: Baylor University | D6: United States | F6: No | G6: Seismology | I6: No | J6: Dec 18, 2024, 1:08 PM | K6: CRESCENT mailing list | L6: Quakeworx
A7: 95 | B7: Male | C7: Indonesian Agency for Meteorology Climatology and Geophysics | D7: Indonesia | F7: No | G7: Seismology; Solid Earth | I7: No | J7: Dec 19, 2024, 12:29 AM | K7: SCEC mailing list | L7: Quakeworx
A8: 79 | B8: Male | C8: Fundación Venezolana de Investigaciones Sismológicas | D8: Venezuela | F8: No | G8: Computer Science; Seismology | I8: No | J8: Dec 18, 2024, 12:32 PM | K8: Other | L8: Quakeworx
A9: 109 | B9: Male | C9: National Research and Innovation Agency | D9: Indonesia | F9: No | G9: Seismology | I9: No | J9: Dec 19, 2024, 6:15 PM | K9: AGU member community | L9: Quakeworx
A10: 97 | B10: Male | C10: Aristotle University of Thessaloniki | D10: Greece | F10: No | G10: Seismology | I10: No | J10: Dec 19, 2024, 2:10 AM | K10: AGU member community | L10: Quakeworx
A11: 145 | B11: Female | C11: Algerian Centre of Research Applied for Earthquake Engineering | D11: Algeria | F11: Other | G11: Geohazard; Solid Earth; Tsunami; Other | H11: neotectonics field | I11: No | J11: 45659.107 | K11: Other | L11: Quakeworx
A12: 21 | B12: Male | C12: King Abdullah University of science and technology | D12: Saudi Arabia | F12: No | G12: Engineering; Seismology | I12: No | J12: Dec 12, 2024, 10:10 PM | K12: SCEC mailing list | L12: Quakeworx
A13: 106 | B13: Male | C13: Centre for Excellence in Disaster Mitigation and Management, IIT Roorkee, India | D13: India | F13: No | G13: Engineering; Geohazard; Seismology | H13: Research Experience in Engineering seismology and Seismic Hazard Management and prepardness | I13: No | J13: Dec 19, 2024, 10:09 AM | K13: Other | L13: Quakeworx
A14: 90 | B14: Male | C14: National Geographical Institute | D14: Spain | F14: No | G14: Engineering; Geohazard; Seismology; Tsunami; Volcanology | I14: No | J14: Dec 18, 2024, 9:00 PM | K14: Geo-INQUIRE Website | L14: Quakeworx
A15: 63 | B15: Male | C15: CENEPRED | D15: Peru | F15: No | G15: Engineering; Geohazard; Solid Earth; Tsunami | I15: No | J15: Dec 18, 2024, 7:51 AM | K15: Geo-INQUIRE mailing list | L15: Quakeworx
A16: 45 | B16: Female | C16: Statewide California Earthquake Center | D16: United States | F16: No | G16: Computer Science; Geohazard; Seismology; Other | H16: Seismology, Geophysics, Earthquake Education and Outreach | I16: No | J16: Dec 16, 2024, 10:23 PM | K16: SCEC mailing list | L16: Quakeworx
A17: 8 | B17: Male | C17: University of Naples Federico II | D17: Italy | F17: No | G17: Engineering | I17: No | J17: Dec 12, 2024, 1:58 PM | K17: SCEC mailing list | L17: Quakeworx
A18: 115 | B18: Male | C18: CERI-University of Memphis | D18: United States | F18: No | G18: Seismology; Other | H18: Geophysics | I18: No | J18: Dec 20, 2024, 12:35 PM | K18: SZ4D mailing list | L18: Quakeworx
A19: 13 | B19: Female | C19: USC | D19: United States | F19: No | G19: Seismology | I19: Yes | J19: Dec 12, 2024, 2:25 PM | K19: SCEC mailing list | L19: Quakeworx
A20: 137 | B20: Male | C20: Geotech Research Team, Department of Earth Sciences, Faculty of Sciences of Meknes, University Moulay Ismail | D20: Morocco | F20: No | G20: Geohazard; Seismology; Solid Earth | I20: No | J20: Dec 30, 2024, 3:52 AM | K20: Colleagues | L20: Quakeworx
A21: 143 | B21: Female | C21: University of California, Riverside | D21: United States | F21: No | G21: Seismology | I21: No | J21: 45658.672 | K21: SCEC mailing list | L21: Quakeworx
A22: 149 | B22: Male | C22: UCLA | D22: United States | F22: No | G22: Computer Science | I22: No | J22: 45660.484 | K22: Colleagues | L22: Quakeworx
A23: 62 | B23: Male | C23: Universidad Nacional de Asunción | D23: Paraguay | F23: No | G23: Atmospheric Physics; Seismology | I23: No | J23: Dec 18, 2024, 7:46 AM | K23: Colleagues | L23: Quakeworx
A24: 54 | B24: Diverse | C24: Washington Geological Survey | D24: United States | F24: No | G24: Geohazard; Marine Sciences; Seismology; Tsunami | I24: No | J24: Dec 17, 2024, 8:48 PM | K24: SCEC mailing list | L24: Quakeworx
A25: 119 | B25: Female | C25: Bogazici University Kandilli Observatory and Earthquake Research Institute | D25: Turkey | F25: No | G25: Engineering; Seismology; Solid Earth | I25: No | J25: Dec 21, 2024, 12:26 AM | K25: Other | L25: Quakeworx
A26: 61 | B26: Male | C26: Earthquake Engineering | D26: Ecuador | F26: No | G26: Engineering; Geohazard; Seismology | I26: Yes | J26: Dec 18, 2024, 7:43 AM | K26: AGU member community | L26: Quakeworx
A27: 151 | B27: Female | C27: San Jose State University | D27: United States | F27: No | G27: Solid Earth; Other | H27: Geology | I27: No | J27: 45660.731 | K27: Other | L27: Quakeworx
A28: 75 | B28: Male | C28: University of Texas at Dallas | D28: United States | F28: No | G28: Computer Science; Seismology | I28: No | J28: Dec 18, 2024, 9:36 AM | K28: Colleagues | L28: Quakeworx
A29: 51 | B29: Female | C29: QUT | D29: Australia | F29: No | G29: Computer Science; Seismology; Solid Earth | I29: No | J29: Dec 17, 2024, 4:24 PM | K29: Other | L29: Quakeworx
A30: 35 | B30: Male | C30: Tsinghua University | D30: China | F30: No | G30: Computer Science; Engineering; Seismology | H30: Scientific Machine Learning, Nonlinear/Linear Numerical Solver | I30: No | J30: Dec 15, 2024, 10:25 AM | K30: AGU member community | L30: Quakeworx
A31: 40 | B31: Male | C31: China University of Geosciences, Beijing | D31: China | F31: No | G31: Geohazard; Seismology | I31: No | J31: Dec 15, 2024, 4:56 PM | K31: Colleagues | L31: Quakeworx
A32: 104 | B32: Female | C32: Moody's | D32: United States | F32: Industry | G32: Geohazard; Seismology | I32: No | J32: Dec 19, 2024, 8:44 AM | K32: Colleagues | L32: Quakeworx
A33: 22 | B33: Male | C33: King Abdullah University of Science and Technology (KAUST) | D33: Saudi Arabia | F33: No | G33: Computer Science; Environmental Protection; Geohazard; Seismology; Tsunami | I33: No | J33: Dec 12, 2024, 10:15 PM | K33: Other | L33: Quakeworx
A34: 142 | B34: Female | C34: University of Iceland (Háskóli Íslands) | D34: Iceland | F34: No | G34: Engineering; Seismology | H34: Engineering Seismology | I34: No | J34: 45658.393 | K34: Geo-INQUIRE Website | L34: Quakeworx
A35: 85 | B35: Male | C35: Philippine Institute of Volcanology and Seismology | D35: Philippines | F35: No | G35: Seismology; Tsunami; Other | H35: Physics, Seismology, Tsunami | I35: No | J35: Dec 18, 2024, 3:07 PM | K35: Other | L35: Quakeworx
A36: 91 | B36: Female | C36: Goa university, India | D36: India | F36: No | G36: Geohazard; Seismology; Other | H36: Oil and gas, Geophysics | I36: No | J36: Dec 18, 2024, 9:11 PM | K36: AGU member community | L36: Quakeworx
A37: 103 | B37: Female | C37: California State University Northridge | D37: United States | F37: No | G37: Geohazard; Seismology; Other | H37: Geodesy | I37: No | J37: Dec 19, 2024, 8:36 AM | K37: Other | L37: Quakeworx
A38: 102 | B38: Male | C38: CSIR Fourth Paradigm Institute | D38: India | F38: No | G38: Geohazard; Seismology; Solid Earth; Tsunami; Volcanology | I38: No | J38: Dec 19, 2024, 4:45 AM | K38: AGU member community | L38: Quakeworx
A39: 128 | B39: Male | C39: Department of Geology, Faculty of Sciences Ben M'Sick. Hassan II University, Casablanca, Morocco. | D39: Morocco | F39: No | G39: Geohazard; Seismology; Solid Earth | I39: No | J39: Dec 23, 2024, 8:18 AM | K39: Geo-INQUIRE Website | L39: Quakeworx
A40: 152 | B40: Male | C40: Idaho National Laboratory | D40: United States | F40: No | G40: Engineering | I40: No | J40: 45660.731 | K40: Colleagues | L40: Quakeworx
A41: 121 | B41: Female | C41: Caraga State University | D41: Philippines | F41: No | G41: Geohazard; Seismology; Solid Earth | I41: No | J41: Dec 21, 2024, 3:19 PM | K41: Geo-INQUIRE mailing list | L41: Quakeworx
A42: 20 | B42: Male | C42: Center for Earthquake Research Information, The University of Memphis | D42: United States | F42: No | G42: Geohazard; Seismology | H42: Rupture Dynamics, Slope Stability, and Space Geodesy. | I42: No | J42: Dec 12, 2024, 7:14 PM | K42: SCEC mailing list | L42: Quakeworx
A43: 19 | B43: Male | C43: California Institute of Technology | D43: United States | F43: No | G43: Solid Earth | I43: No | J43: Dec 12, 2024, 6:52 PM | K43: SCEC mailing list | L43: Quakeworx
A44: 57 | B44: Male | C44: Universidade de São Paulo | D44: Brazil | F44: No | G44: Seismology; Solid Earth | I44: No | J44: Dec 18, 2024, 2:39 AM | K44: Other | L44: Quakeworx
A45: 50 | B45: Male | C45: University of Nevada, Reno | D45: United States | F45: No | G45: Seismology | I45: No | J45: Dec 17, 2024, 2:51 PM | K45: Colleagues | L45: Quakeworx
A46: 80 | B46: Male | C46: Stanford University, Geophysics Department | D46: United States | F46: No | G46: Computer Science; Seismology; Solid Earth | H46: Earthquake Seismology, Seismic Imaging/Inversion, Earthquake Rupture Mechanics, Machine Learning, HPC | I46: Yes | J46: Dec 18, 2024, 1:06 PM | K46: Other | L46: Quakeworx
A47: 38 | B47: Male | C47: Institute of Geology, China Earthquake Administration | D47: China | F47: No | G47: Solid Earth | I47: No | J47: Dec 15, 2024, 3:54 PM | K47: Colleagues | L47: Quakeworx
A48: 18 | B48: Male | C48: Centro de Investigación de Astrofísica y Ciencias Espaciales, UNAN-Managua | D48: Nicaragua | F48: No | G48: Atmospheric Physics; Computer Science; Seismology; Solid Earth; Tsunami; Volcanology | H48: I work in Geophysics and Atmospheric Physics | I48: No | J48: Dec 12, 2024, 5:36 PM | K48: Linkedin | L48: Quakeworx
A49: 48 | B49: Female | C49: Lawrence Livermore National Laboratory | D49: United States | F49: No | G49: Energy Transformation/Storage; Seismology | H49: statistical earthquake forecasting | I49: No | J49: Dec 17, 2024, 8:22 AM | K49: Other | L49: Quakeworx
A50: 140 | B50: Male | C50: Polytechnic University of Tirana, Institute of Geosciences | D50: Albania | F50: No | G50: Computer Science; Engineering; Seismology; Solid Earth | I50: Yes | J50: Dec 30, 2024, 6:15 AM | K50: Colleagues | L50: Quakeworx
A51: 42 | B51: Female | C51: Southern University of Science and Technology | D51: China | F51: No | G51: Seismology | I51: No | J51: Dec 15, 2024, 11:01 PM | K51: Geo-INQUIRE Website | L51: Quakeworx
A52: 23 | B52: Male | C52: Institut des sciences de la Terre, Université Grenoble Alpes | D52: France | F52: No | G52: Seismology; Solid Earth | I52: No | J52: Dec 12, 2024, 11:06 PM | K52: SCEC mailing list | L52: Quakeworx
A53: 92 | B53: Male | C53: University of Pittsburgh | D53: United States | F53: No | G53: Energy Transformation/Storage; Seismology; Other | H53: applied Geophysics: well logging, gravity, ERT, GPR, Magnetic techniques. | I53: Yes | J53: Dec 18, 2024, 10:13 PM | K53: Colleagues | L53: Quakeworx
A54: 135 | B54: Male | C54: Geology & Geophysics, Louisiana State University | D54: United States | F54: No | G54: Environmental Protection; Geohazard; Seismology | H54: Multi-hazard Risk Assessment | I54: No | J54: Dec 28, 2024, 11:37 AM | K54: Geo-INQUIRE Website | L54: Quakeworx
A55: 58 | B55: Male | C55: University of Pittsburgh | D55: United States | F55: No | G55: Geohazard; Seismology; Solid Earth; Other | H55: Microseismic analysis | I55: No | J55: Dec 18, 2024, 7:22 AM | K55: Other | L55: Quakeworx
A56: 76 | B56: Male | C56: SEG, CRESENT, EarthScope Consortium | D56: Pakistan | F56: No | G56: Seismology; Volcanology | I56: No | J56: Dec 18, 2024, 9:42 AM | K56: CRESCENT mailing list | L56: Quakeworx
A57: 36 | B57: Male | C57: Tsinghua University | D57: China | F57: No | G57: Computer Science; Environmental Protection; Engineering; Seismology | I57: Yes | J57: Dec 15, 2024, 10:30 AM | K57: AGU member community | L57: Quakeworx
A58: 125 | B58: Female | C58: University of Puerto Rico | D58: Puerto Rico | F58: No | G58: Engineering | I58: No | J58: Dec 22, 2024, 5:00 PM | K58: AGU member community | L58: Quakeworx
A59: 17 | B59: Male | C59: Lawrence Berkeley National Laboratory | D59: United States | F59: No | G59: Engineering; Seismology | I59: No | J59: Dec 12, 2024, 5:28 PM | K59: SCEC mailing list | L59: Quakeworx
A60: 144 | B60: Male | C60: South China Sea Institute of Oceanology,Chinese Academy of Sciences | D60: China | F60: No | G60: Solid Earth | I60: No | J60: 45659.066 | K60: Geo-INQUIRE Website | L60: Quakeworx
A61: 43 | B61: Male | C61: California Institute of Technology | D61: United States | F61: No | G61: Energy Transformation/Storage; Geohazard; Solid Earth | I61: No | J61: Dec 16, 2024, 2:16 PM | K61: SCEC mailing list | L61: Quakeworx
A62: 108 | B62: Male | C62: Center for Earthquake Research and Information, University of Memphis | D62: United States | F62: No | G62: Seismology | I62: No | J62: Dec 19, 2024, 11:24 AM | K62: Other | L62: Quakeworx
A63: 117 | B63: Female | C63: Geology Student | D63: Colombia | F63: No | G63: Computer Science; Seismology | H63: planetary geology | I63: No | J63: Dec 20, 2024, 6:45 PM | K63: SCEC mailing list | L63: Quakeworx
A64: 123 | B64: Male | C64: University of Benin | D64: Nigeria | F64: No | G64: Seismology | I64: No | J64: Dec 21, 2024, 10:00 PM | K64: Linkedin | L64: Quakeworx
A65: 150 | B65: Female | C65: UCLA | D65: United States | F65: No | G65: Computer Science; Engineering | I65: No | J65: 45660.497 | K65: Other | L65: Quakeworx
A66: 53 | B66: Male | C66: Southern University of Science and Technology | D66: China | F66: Other | G66: Geohazard; Seismology | H66: Earthquake Physics | I66: No | J66: Dec 17, 2024, 7:22 PM | K66: SCEC mailing list | L66: Quakeworx
A67: 122 | B67: Male | C67: University of Puerto Rico at Mayaguez | D67: Puerto Rico | F67: No | G67: Seismology | I67: No | J67: Dec 21, 2024, 7:04 PM | K67: Other | L67: Quakeworx
A68: 14 | B68: Male | C68: University of Southern California | D68: United States | F68: No | G68: Engineering; Geohazard; Seismology | I68: No | J68: Dec 12, 2024, 2:33 PM | K68: SCEC mailing list | L68: Quakeworx
A69: 98 | B69: Male | C69: Center for Research in Astronomy, Astrophysics and Geophysics | D69: Algeria | F69: No | G69: Geohazard; Seismology | I69: No | J69: Dec 19, 2024, 2:15 AM | K69: Colleagues | L69: Quakeworx
A70: 141 | B70: Male | C70: sachinkhupat057@gmail.com | D70: India | F70: No | G70: Geohazard; Seismology | H70: • To undertake research studies on microearthquake investigation, strong motion measurement and seismic design parameter studies for hydroelectric projects (HE) in India, Nepal & Bhutan • To assist in undertaking studies in seismic hazard assessment for HE Projects • To undertake Reservoir Induced Seismicity studies for Nuclear Power Plants in India | I70: No | J70: 45658.177 | K70: Other | L70: Quakeworx
A71: 136 | B71: Female | C71: University of the Philippines | D71: Philippines | F71: No | G71: Solid Earth; Other | H71: Economic Geology | I71: No | J71: Dec 30, 2024, 1:32 AM | K71: Other | L71: Quakeworx
A72: 24 | B72: Female | C72: Postdoc, IPGP France | D72: France | F72: No | G72: Seismology | I72: No | J72: Dec 13, 2024, 3:29 AM | K72: SCEC mailing list | L72: Quakeworx
A73: 29 | B73: Female | C73: Lawrence Livermore National Laboratoy | D73: United States | F73: No | G73: Seismology | H73: Earthquake physics | I73: No | J73: Dec 14, 2024, 1:10 PM | K73: SCEC mailing list | L73: Quakeworx
A74: 5 | B74: Male | C74: PhD Student | D74: Italy | F74: No | G74: Engineering; Geohazard; Seismology | H74: Earthquake Engineering | I74: No | J74: Dec 12, 2024, 4:46 AM | K74: Geo-INQUIRE Website | L74: Quakeworx
A75: 72 | B75: Male | C75: California Institute of technology | D75: United States | F75: No | G75: Computer Science; Engineering; Geohazard | I75: No | J75: Dec 18, 2024, 9:08 AM | K75: Geo-INQUIRE mailing list | L75: Quakeworx
A76: 33 | B76: Male | C76: University of Southern California | D76: United States | F76: No | G76: Seismology; Solid Earth | H76: Geodynamics, earthquake cycle modelling | I76: No | J76: Dec 15, 2024, 9:28 AM | K76: AGU member community | L76: Quakeworx
A77: 56 | B77: Female | C77: Institute of Earthquake Forecasting, China Earthquake Administration | D77: China | F77: No | G77: Seismology | H77: solid mechanics, seismicity and earthquake simulation | I77: No | J77: Dec 18, 2024, 1:26 AM | K77: Other | L77: Quakeworx
A78: 69 | B78: Female | C78: National Autonomous University of Mexico | D78: Mexico | F78: No | G78: Geohazard; Seismology; Solid Earth | I78: No | J78: Dec 18, 2024, 8:51 AM | K78: Other | L78: Quakeworx
A79: 148 | B79: Female | C79: GFZ-Potsdam | D79: Germany | F79: No | G79: Seismology | I79: No | J79: 45660.067 | K79: Geo-INQUIRE mailing list | L79: Quakeworx
A80: 138 | B80: Female | C80: National Research Institute of Astronomy and Geophysics (NRIAG) | D80: Egypt | F80: No | G80: Geohazard; Seismology | I80: No | J80: Dec 30, 2024, 5:37 AM | K80: Colleagues | L80: Quakeworx
A81: 147 | B81: Male | C81: Georgia Institute of Technology | D81: United States | F81: No | G81: Geohazard; Seismology; Solid Earth; Tsunami | I81: No | J81: 45659.526 | K81: SCEC mailing list | L81: Quakeworx
A82: 28 | B82: Male | C82: Statewide California Earthquake Center | D82: United States | F82: No | G82: Computer Science; Geohazard; Seismology | I82: Yes | J82: Dec 13, 2024, 10:32 PM | K82: SCEC mailing list | L82: Quakeworx
A83: 78 | B83: Male | C83: National Seismic Monitoring Center Pakistan | D83: Pakistan | F83: No | G83: Geohazard; Seismology; Tsunami | I83: No | J83: Dec 18, 2024, 11:57 AM | K83: AGU member community | L83: Quakeworx
A84: 114 | B84: Male | C84: Earthscope | D84: Nigeria | F84: No | G84: Geohazard; Seismology | I84: No | J84: Dec 20, 2024, 7:45 AM | K84: AGU member community | L84: Quakeworx
A85: 96 | B85: Male | C85: National University of Science and Technology | D85: Zimbabwe | F85: No | G85: Geohazard; Seismology | I85: No | J85: Dec 19, 2024, 12:45 AM | K85: AGU member community | L85: Quakeworx
A86: 111 | B86: Male | C86: Research Associate | D86: Singapore | F86: No | G86: Geohazard; Seismology | I86: No | J86: Dec 19, 2024, 11:45 PM | K86: AGU member community | L86: Quakeworx
A87: 94 | B87: Male | C87: MAKERERE UNIVERSITY | D87: Uganda | F87: No | G87: Geohazard; Seismology | I87: No | J87: Dec 18, 2024, 11:09 PM | K87: AGU member community | L87: Quakeworx
A88: 26 | B88: Male | C88: University of British Columbia | D88: Canada | F88: No | G88: Geohazard; Seismology | I88: No | J88: Dec 13, 2024, 10:34 AM | K88: Colleagues | L88: Quakeworx
A89: 74 | B89: Male | C89: U.S. Geological Survey | D89: United States | F89: No | G89: Computer Science; Geohazard; Seismology | I89: Yes | J89: Dec 18, 2024, 9:17 AM | K89: Colleagues | L89: Quakeworx
A90: 88 | B90: Male | C90: Tongji University, Shanghai, China | D90: China | F90: No | G90: Geohazard; Seismology | I90: No | J90: Dec 18, 2024, 8:36 PM | K90: Other | L90: Quakeworx
A91: 113 | B91: Female | C91: Puerto Rico Seismic Ntwork/University of Puerto Rico Mayagüez Campus | D91: Puerto Rico | F91: No | G91: Seismology; Other | H91: Earthquake detection and location, picking p and s phases for a local and teleseismic event, mineralogy, geochemistry, seismology | I91: No | J91: Dec 20, 2024, 5:56 AM | K91: Geo-INQUIRE mailing list | L91: Quakeworx
A92: 99 | B92: Female | C92: Barcelona Supercomputing Center | D92: Spain | F92: No | G92: Geohazard; Seismology | H92: Machine Learning | I92: No | J92: Dec 19, 2024, 2:32 AM | K92: Geo-INQUIRE mailing list | L92: Quakeworx
A93: 73 | B93: Female | C93: The University of Memphis | D93: United States | F93: No | G93: Seismology | H93: Co-seismic deformation | I93: No | J93: Dec 18, 2024, 9:12 AM | K93: Colleagues | L93: Quakeworx
A94: 110 | B94: Male | C94: University of California, Riverside | D94: United States | F94: No | G94: Seismology; Tsunami | I94: Yes | J94: Dec 19, 2024, 9:36 PM | K94: SCEC mailing list | L94: Quakeworx
A95: 59 | B95: Female | C95: Cal Poly Pomona | D95: United States | F95: No | G95: Geohazard; Seismology | I95: No | J95: Dec 18, 2024, 7:24 AM | K95: CRESCENT mailing list | L95: Quakeworx
A96: 11 | B96: Male | C96: CERI, University of Memphis | D96: United States | F96: No | G96: Geohazard; Seismology | I96: Yes | J96: Dec 12, 2024, 2:11 PM | K96: SCEC mailing list | L96: Quakeworx
A97: 112 | B97: Female | C97: University of Trieste | D97: Italy | F97: No | G97: Seismology; Solid Earth | I97: No | J97: Dec 20, 2024, 3:10 AM | K97: Other | L97: Quakeworx
A98: 130 | B98: Male | C98: Faculty of sciences and techniques | D98: Morocco | F98: No | G98: Geohazard; Solid Earth | I98: No | J98: Dec 23, 2024, 2:15 PM | K98: AGU member community | L98: Quakeworx
A99: 65 | B99: Male | C99: Geophysics and Natural Hazard Laboratory, Scientific Institute Mohammed V University in Rabat Morocco | D99: Morocco | F99: No | G99: Geohazard; Seismology; Solid Earth | I99: Yes | J99: Dec 18, 2024, 8:24 AM | K99: AGU member community | L99: Quakeworx
A100: 47 | B100: Female | C100: University of Nevada Reno | D100: United States | F100: No | G100: Seismology | I100: No | J100: Dec 17, 2024, 8:18 AM | K100: Colleagues | L100: Quakeworx
...

Sheet EPISODES_Hackathon
A1: ID | B1: Gender | C1: Affiliation | D1: Country of Affiliation | E1: Are you an Early Career Scientist? | F1: Do you work in industry, a Start-up or Small and Medium Enterprise? | G1: What is your scientific expertise? (Multiple Choice) | H1: Scientific expertise - Other(s): | I1: Have you used the EPOS TCS AH Episodes platform before? | J1: Registration date | K1: Registration state | L1: How did you hear about this event? | M1: Tags | O1: Countries | P1: No_Countries | Q1: Category
A2: 5 | B2: Female | C2: Technische Hochschule Augsburg | D2: Germany | E2: Yes | F2: No | G2: Computer Science; Engineering; Geohazard | I2: No | J2: 45706.902 | K2: Completed | M2: Hackathon1 | O2: {=UNIQUE(D2:D187)} -> Germany | P2: =COUNTIF(D$2:D$120,O2) -> 1 | Q2: {=XLOOKUP(O2,Countries!A$2:A$98,Countries!B$2:B$98,"tbd",0)} -> Europe
A3: 9 | B3: Female | C3: Chalmers University of Technology | D3: Sweden | E3: Yes | F3: No | G3: Geohazard; Seismology; Solid Earth | H3: Tectonophyscis | I3: No | J3: 45716.825 | K3: Completed | M3: Hackathon1 | O3: Sweden | P3: =COUNTIF(D$2:D$120,O3) -> 1 | Q3: {=XLOOKUP(O3,Countries!A$2:A$98,Countries!B$2:B$98,"tbd",0)} -> Europe
A4: 10 | B4: Female | C4: State Mining Authority | D4: Poland | E4: No | F4: No | G4: Geohazard; Seismology; Other | H4: Mining geophysics | I4: No | J4: Mar 3, 2025, 3:04 PM | K4: Completed | M4: Hackathon1 | O4: Poland | P4: =COUNTIF(D$2:D$120,O4) -> 14 | Q4: {=XLOOKUP(O4,Countries!A$2:A$98,Countries!B$2:B$98,"tbd",0)} -> widening countries
A5: 4 | B5: Male | C5: Faculty of Sciences Ben M'Sick. Hassan II University of Casablanca, Morocco. | D5: Morocco | E5: Yes | F5: No | G5: Engineering; Geohazard; Seismology; Solid Earth | I5: No | J5: 45705.862 | K5: Completed | M5: Hackathon1 | O5: Morocco | P5: =COUNTIF(D$2:D$120,O5) -> 1 | Q5: {=XLOOKUP(O5,Countries!A$2:A$98,Countries!B$2:B$98,"tbd",0)} -> Africa
A6: 17 | B6: Female | C6: Faculty of Geology, University of Warsaw | D6: Poland | E6: No | F6: No | G6: Other | H6: geoinformatics | I6: No | J6: Mar 11, 2025, 11:00 AM | K6: Completed | M6: Hackathon1 | O6: North Macedonia | P6: =COUNTIF(D$2:D$120,O6) -> 1 | Q6: {=XLOOKUP(O6,Countries!A$2:A$98,Countries!B$2:B$98,"tbd",0)} -> associated countries
A7: 18 | B7: Male | C7: IG PAS | D7: Poland | E7: Yes | F7: No | G7: Seismology | I7: No | J7: Mar 12, 2025, 4:24 PM | K7: Completed | M7: Hackathon1 | O7: Hungary | P7: =COUNTIF(D$2:D$120,O7) -> 1 | Q7: {=XLOOKUP(O7,Countries!A$2:A$98,Countries!B$2:B$98,"tbd",0)} -> widening countries
A8: 20 | B8: Female | C8: University of Warsaw, Faculty of Physics | D8: Poland | E8: Yes | F8: No | G8: Other | H8: Astrophysics | I8: No | J8: Mar 12, 2025, 4:53 PM | K8: Completed | M8: Hackathon1 | O8: Italy | P8: =COUNTIF(D$2:D$120,O8) -> 1 | Q8: {=XLOOKUP(O8,Countries!A$2:A$98,Countries!B$2:B$98,"tbd",0)} -> Europe
A9: 8 | B9: Male | C9: Ss. Cyril and Methodius University Skopje | D9: North Macedonia | E9: Yes | F9: No | G9: Geohazard; Seismology | I9: No | J9: 45715.603 | K9: Completed | M9: Hackathon1
A10: 3 | B10: Female | C10: AGH University of Krakow | D10: Poland | E10: Yes | F10: Yes | G10: Engineering; Seismology; Solid Earth | I10: Yes | J10: 45695.762 | K10: Completed | M10: Hackathon1 | P10: =SUM(P2:P8) -> 20
A11: 12 | B11: Female | C11: Polish Geological Institute - National Research Institute | D11: Poland | E11: No | F11: No | G11: Seismology | I11: No | J11: Mar 5, 2025, 12:54 PM | K11: Completed | M11: Hackathon1
A12: 1 | B12: Male | C12: University of Pécs | D12: Hungary | E12: Yes | F12: No | G12: Environmental Protection; Geohazard; Marine Sciences; Tsunami | H12: Marine Natural Hazards such as tsunami, storm, tidal flood, submarine landslide, and coastal morphology evolution | I12: No | J12: 45686.198 | K12: Completed | M12: Hackathon1 | P12: 16 | Q12: widening/associated countries
A13: 15 | B13: Male | C13: Uniwersytet Jagielloński | D13: Poland | E13: Yes | F13: No | G13: Computer Science; Environmental Protection; Geohazard; Solid Earth | I13: No | J13: Mar 9, 2025, 7:49 PM | K13: Completed | M13: Hackathon1 | P13: 1 | Q13: non-EU
A14: 11 | B14: Male | C14: THE POLISH GEOLOGICAL INSTITUTE - NATIONAL RESEARCH INSTITUTE | D14: Poland | E14: No | F14: No | G14: Seismology | I14: Yes | J14: Mar 5, 2025, 12:12 PM | K14: Completed | M14: Hackathon1 | P14: 7 | Q14: different countries
A15: 13 | B15: Male | C15: Instytut Nauk Geologicznych, Wydział Geografii i Geologii Uniwersytetu Jagiellońskiego | D15: Poland | E15: No | F15: No | G15: Other | H15: Geology | I15: No | J15: Mar 7, 2025, 2:11 PM | K15: Completed | M15: Hackathon1 | P15: 14 | Q15: different scientific fields
A16: 16 | B16: Female | C16: Jagiellonian University | D16: Poland | E16: Yes | F16: No | G16: Other | H16: none yet | I16: No | J16: Mar 11, 2025, 8:12 AM | K16: Completed | M16: Hackathon1
A17: 2 | B17: Male | C17: University of Silesia in Katowice | D17: Poland | E17: Yes | F17: No | G17: Geohazard; Seismology | I17: Yes | J17: 45688.616 | K17: Completed | M17: Hackathon1
A18: 14 | B18: Female | C18: Uniwersytet Warszawski | D18: Poland | E18: No | F18: No | G18: Solid Earth | I18: No | J18: Mar 7, 2025, 3:29 PM | K18: Completed | M18: Hackathon1
A19: 7 | B19: Male | C19: Adam Mickiewicz University in Poznań | D19: Poland | E19: Yes | F19: No | G19: Environmental Protection; Geohazard; Other | H19: Paleoseismology | I19: No | J19: 45714.549 | K19: Completed | M19: Hackathon1
A20: 6 | B20: Male | C20: University of Bologna | D20: Italy | E20: Yes | F20: No | G20: Geohazard; Seismology; Solid Earth | H20: Ground Motion Modelling | I20: Yes | J20: 45710.096 | K20: Completed | M20: Hackathon1
A21: 19 | B21: Male | C21: University of Warsaw | D21: Poland | E21: Yes | F21: No | G21: Other | H21: Earth magnetism | I21: No | J21: Mar 12, 2025, 4:34 PM | K21: Completed | M21: Hackathon1

Sheet FAIR7
A1: ID | B1: Gender | C1: Affiliation | D1: Country of Affiliation | E1: Are you an Early Career Scientist? | F1: Do you work in industry, a Start-up or Small and Medium Enterprise? | G1: What is your scientific expertise? (Multiple Choice) | H1: Scientific expertise - Other(s): | I1: Have you been familiar with the FAIR principles before? | J1: Registration date | K1: How did you hear about this event: | L1: Tags | O1: Countries | P1: No_Countries | Q1: Category
A2: 13 | B2: Female | C2: Graduated from Saarland University | D2: Germany | E2: Yes | F2: No | G2: Other | H2: Bioinformatics | I2: Yes | J2: May 12, 2025, 8:24 PM | K2: Other | L2: FAIR7 | O2: {=UNIQUE(D2:D187)} -> Germany | P2: =COUNTIF(D$2:D$120,O2) -> 4 | Q2: {=XLOOKUP(O2,Countries!A$2:A$98,Countries!B$2:B$98,"tbd",0)} -> Europe
A3: 19 | B3: Female | C3: GFZ Helmholtz-Zentrum für Geoforschung | D3: Germany | E3: Yes | F3: No | G3: Solid Earth; Other | H3: Organic Geochemistry | I3: Yes | J3: May 15, 2025, 5:08 PM | K3: Geo-INQUIRE mailinglist | L3: FAIR7 | O3: Portugal | P3: =COUNTIF(D$2:D$120,O3) -> 2 | Q3: {=XLOOKUP(O3,Countries!A$2:A$98,Countries!B$2:B$98,"tbd",0)} -> widening countries
A4: 12 | B4: Male | C4: UBI | D4: Portugal | E4: No | F4: No | G4: Computer Science | I4: Yes | J4: May 7, 2025, 3:56 PM | K4: Newsletter or website of the Ris (EPOS, ERIC, etc.) | L4: FAIR7 | O4: Italy | P4: =COUNTIF(D$2:D$120,O4) -> 5 | Q4: {=XLOOKUP(O4,Countries!A$2:A$98,Countries!B$2:B$98,"tbd",0)} -> Europe
A5: 16 | B5: Male | C5: University of Bari Aldo Moro | D5: Italy | E5: Yes | F5: No | G5: Geohazard | I5: Yes | J5: May 15, 2025, 4:27 PM | K5: Geo-INQUIRE mailinglist | L5: FAIR7 | O5: Belgium | P5: =COUNTIF(D$2:D$120,O5) -> 2 | Q5: {=XLOOKUP(O5,Countries!A$2:A$98,Countries!B$2:B$98,"tbd",0)} -> Europe
A6: 20 | B6: Female | C6: LMU - Dept. of Geophysics | D6: Germany | E6: No | F6: No | G6: Computer Science | H6: HPC | I6: Yes | J6: May 16, 2025, 11:24 AM | K6: Geo-INQUIRE website | L6: FAIR7 | O6: United States | P6: =COUNTIF(D$2:D$120,O6) -> 1 | Q6: {=XLOOKUP(O6,Countries!A$2:A$98,Countries!B$2:B$98,"tbd",0)} -> U.S. + Canada
A7: 17 | B7: Female | C7: ISPRA | D7: Italy | E7: No | F7: No | G7: Computer Science; Environmental Protection | I7: Yes | J7: May 15, 2025, 4:36 PM | K7: Geo-INQUIRE mailinglist | L7: FAIR7 | O7: Spain | P7: =COUNTIF(D$2:D$120,O7) -> 2 | Q7: {=XLOOKUP(O7,Countries!A$2:A$98,Countries!B$2:B$98,"tbd",0)} -> Europe
A8: 2 | B8: Male | C8: ROB | D8: Belgium | E8: No | F8: No | G8: Computer Science; Solid Earth | I8: Yes | J8: 45755.481 | K8: Geo-INQUIRE website | L8: FAIR7 | O8: Albania | P8: =COUNTIF(D$2:D$120,O8) -> 1 | Q8: {=XLOOKUP(O8,Countries!A$2:A$98,Countries!B$2:B$98,"tbd",0)} -> associated countries
A9: 5 | B9: Female | C9: INGV/EPOS | D9: Italy | E9: No | F9: No | G9: Other | I9: Yes | J9: 45755.629 | K9: Other | L9: FAIR7 | O9: Turkey | P9: =COUNTIF(D$2:D$120,O9) -> 1 | Q9: {=XLOOKUP(O9,Countries!A$2:A$98,Countries!B$2:B$98,"tbd",0)} -> associated countries
A10: 8 | B10: Female | C10: San José State University | D10: United States | E10: No | F10: No | G10: Seismology; Solid Earth | I10: Yes | J10: 45761.829 | K10: Colleagues | L10: FAIR7 | O10: France | P10: =COUNTIF(D$2:D$120,O10) -> 2 | Q10: {=XLOOKUP(O10,Countries!A$2:A$98,Countries!B$2:B$98,"tbd",0)} -> Europe
A11: 7 | B11: Female | C11: Instituto Pirenaico de Ecología (IPE-CSIC) | D11: Spain | E11: No | F11: No | G11: Environmental Protection; Marine Sciences | H11: Plastic pollution | I11: Yes | J11: 45761.403 | K11: Other | L11: FAIR7
A12: 18 | B12: Male | C12: EMSO ERIC | D12: Italy | E12: No | F12: No | G12: Computer Science; Engineering; Marine Sciences | I12: Yes | J12: May 15, 2025, 4:37 PM | K12: Geo-INQUIRE mailinglist | L12: FAIR7 | P12: =SUM(P2:P10) -> 20
A13: 4 | B13: Diverse | C13: Istituto Nazionale di Geofisica e Vulcanologia | D13: Italy | E13: No | F13: No | G13: Volcanology | I13: Yes | J13: 45755.527 | K13: Geo-INQUIRE mailinglist | L13: FAIR7
A14: 1 | B14: Male | C14: Royal Observatory of Belgium | D14: Belgium | E14: No | F14: No | G14: Atmospheric Physics; Solid Earth | H14: GNSS | I14: No | J14: 45755.478 | K14: Geo-INQUIRE mailinglist | L14: FAIR7 | P14: 4 | Q14: widening/associated countries
A15: 9 | B15: Male | C15: Institute of Geoscience | D15: Albania | E15: Yes | F15: No | G15: Computer Science; Seismology | I15: No | J15: 45772.506 | K15: Geo-INQUIRE website | L15: FAIR7 | P15: 1 | Q15: non-EU
A16: 6 | B16: Female | C16: CESAM | Universidade de Aveiro | D16: Portugal | E16: No | F16: No | G16: Marine Sciences; Other | H16: Science Management | I16: Yes | J16: 45757.484 | K16: Newsletter or website of the Ris (EPOS, ERIC, etc.) | L16: FAIR7 | P16: 9 | Q16: different countries
